Workbook
Name A156A1: '🗂️ Proyectos'!$A$156

Sheet BBDD
A1: Proyecto | B1: Responsable | C1: Lámpara | D1: Estado | E1: Área | F1: Proceso | G1: TIPO DE BASTIDOR | H1: General | I1: Proceso | J1: Hrs/m
A2: Ikon Light system | B2: Claudio Peralta | C2: Cruz | D2: Pendiente | E2: CNC | F2: CNC | G2: BASTIDOR DE TABICA 150X12 | H2: CNC | I2: CNC | J2: 0.2 | P2: HRS | Q2: MIN
A3: Contract + | B3: Ihor Alieksieiev | C3: Parafarmacia | D3: Proceso | E3: Fabricación | F3: Corte manual | G3: BASTIDOR DE TABICA 150X12 | H3: Fabricación | I3: Ensamblaje | J3: 0.62 | L3: IMPRIMACION M2 | M3: Pintura | N3: Lijado y/o Masillado | O3: 0.1 | P3: =O3*1.4 -> 0.14 | Q3: =P3*60 -> 8.4
A4: Ceilica | B4: Serhii Kotluienko | C4: Gracos | D4: Terminada | E4: Fabricación | F4: Ensamblaje | G4: BASTIDOR DE TABICA 150X12 | H4: Fabricación | I4: Colocación de perfiles | J4: 0.2 | L4: IMPRIMACION M2 | M4: Pintura | N4: Imprimación/Pintura | O4: 0.19 | P4: =O4*1.4 -> 0.266 | Q4: =P4*60 -> 15.96
A5: Cullera | B5: Tetiana Mesriakin | C5: Gracos 2 | E5: Pintura | F5: Lijado y/o Masillado | G5: BASTIDOR DE TABICA 150X12 | H5: Fabricación | I5: Embalaje/carga/descarga material | J5: 0.15 | L5: PINTURA M2 | M5: Pintura | N5: Lijado y/o Masillado | O5: 0.15 | P5: =O5*0.39 -> 0.0585 | Q5: =P5*60 -> 3.51
A6: Picanya | B6: John Castelblanco | C6: Hair | E6: Fabricación | F6: Colocación de perfiles | G6: BASTIDOR DE TABICA 150X12 | H6: Pintura | I6: Lijado y/o Masillado | J6: 0.5 | L6: PINTURA M2 | M6: Pintura | N6: Imprimación/Pintura | O6: 0.28 | P6: =O6*0.39 -> 0.1092 | Q6: =P6*60 -> 6.552
A7: Druni cc la Villa (Canarias) | B7: Cesar Rodriguez | C7: Palmera | E7: Pintura | F7: Imprimación/Pintura | G7: BASTIDOR DE TABICA 150X12 | H7: Pintura | I7: Imprimación/Pintura | J7: 0.4 | L7: IMPRIMACION TABICA TRASERA | M7: Pintura | N7: Lijado y/o Masillado | O7: 0.21
A8: Druni cc las arenas (Canarias) | B8: Instalador | C8: Techo palmera | E8: Fabricación | F8: Pegado de composite/chapa | G8: BASTIDOR DE TABICA 150X12 COMPLETO | H8: CNC | I8: CNC | J8: =J2 -> 0.2 | L8: IMPRIMACION TABICA TRASERA | M8: Pintura | N8: Imprimación/Pintura | O8: 0.315
A9: Druni Cordoba fase 2 | B9: Daniil Shcheglov | C9: Pilar Palmera | E9: Fabricación | F9: Embalaje/carga/descarga material | G9: BASTIDOR DE TABICA 150X12 COMPLETO | H9: Fabricación | I9: Ensamblaje | J9: =J3 -> 0.62
A10: BYD Tarragona | C10: Mueble palmera | E10: Limpieza | F10: Limpieza | G10: BASTIDOR DE TABICA 150X12 COMPLETO | H10: Fabricación | I10: Colocación de perfiles | J10: =J4 -> 0.2
A11: BYD Paterna | C11: Prototipo | E11: Fabricación | F11: Supervisión/reunión | G11: BASTIDOR DE TABICA 150X12 COMPLETO | H11: Fabricación | I11: Embalaje/carga/descarga material | J11: =J5 -> 0.15
A12: Prototipo | C12: Selcos | E12: Producción | F12: Inventario | G12: BASTIDOR DE TABICA 150X12 COMPLETO | H12: Pintura | I12: Lijado y/o Masillado | J12: =J6+0.315 -> 0.815
A13: Arenal CC Marineda | C13: Selcos metacrilato | E13: Fabricación | F13: Transporte material | G13: BASTIDOR DE TABICA 150X12 COMPLETO | H13: Pintura | I13: Imprimación/Pintura | J13: =J7+0.21 -> 0.61
A14: Prueba | C14: Cromado | E14: Fabricación | F14: Descarga de material | G14: BASTIDOR DE TABICA CURVA 150X12 | H14: CNC | I14: CNC | J14: 0.2
A15: Arenal el rosal | C15: Ameba | E15: Pintura | F15: Limpieza de cabina | G15: BASTIDOR DE TABICA CURVA 150X12 | H15: Fabricación | I15: Ensamblaje | J15: 0.79
A16: Druni cc Lìlla | C16: Punto | E16: Limpieza | F16: Limpieza puesto de trabajo | G16: BASTIDOR DE TABICA CURVA 150X12 | H16: Fabricación | I16: Colocación de perfiles | J16: 0.2
A17: Hotel - Ana | C17: Producción | E17: Fabricación | F17: Mantenimiento | G17: BASTIDOR DE TABICA CURVA 150X12 | H17: Fabricación | I17: Embalaje/carga/descarga material | J17: 0.15
A18: Druni CC los alcores | C18: Curvas madera | E18: Fabricación | F18: Colocar tela | G18: BASTIDOR DE TABICA CURVA 150X12 | H18: Pintura | I18: Lijado y/o Masillado | J18: 0.6
A19: Druni Corralejo | C19: Revestimiento | E19: Fabricación | F19: Trabajo en nave 3 | G19: BASTIDOR DE TABICA CURVA 150X12 | H19: Pintura | I19: Imprimación/Pintura | J19: 0.4
A20: Druni Morrojable | C20: Ranura para placas | E20: Fabricación | F20: Preparación de material | G20: BASTIDOR DE TABICA CURVA 150X12 COMPLETO | H20: CNC | I20: CNC | J20: 0.2
A21: Proveedor | C21: Canopi | G21: BASTIDOR DE TABICA CURVA 150X12 COMPLETO | H21: Fabricación | I21: Ensamblaje | J21: 0.79
A22: Inventario | C22: Arandelas | G22: BASTIDOR DE TABICA CURVA 150X12 COMPLETO | H22: Fabricación | I22: Colocación de perfiles | J22: 0.2
A23: Druni CC Safari | C23: Caja chapa | G23: BASTIDOR DE TABICA CURVA 150X12 COMPLETO | H23: Fabricación | I23: Embalaje/carga/descarga material | J23: 0.15
A24: Druni CC Meridiano fase 2 | C24: Plantillas | G24: BASTIDOR DE TABICA CURVA 150X12 COMPLETO | H24: Pintura | I24: Lijado y/o Masillado | J24: =J18+0.315 -> 0.915
A25: Druni CC Biosfera | C25: Escalera | G25: BASTIDOR DE TABICA CURVA 150X12 COMPLETO | H25: Pintura | I25: Imprimación/Pintura | J25: =J19+0.21 -> 0.61
A26: Urbysol | C26: Nave | G26: BASTIDOR NORMAL 150 | H26: CNC | I26: CNC | J26: =J32+(2/50.54) -> 0.38957262
A27: Druni Catarroja | C27: Transporte | G27: BASTIDOR NORMAL 150 | H27: Fabricación | I27: Ensamblaje | J27: =1+(3.5/50.54) -> 1.0692521
A28: Druni Aguilas | C28: Bastidor Sol | G28: BASTIDOR NORMAL 150 | H28: Fabricación | I28: Colocación de perfiles | J28: 0.2
A29: Arenal Ourense | C29: Bastidor Sol plus | G29: BASTIDOR NORMAL 150 | H29: Fabricación | I29: Embalaje/carga/descarga material | J29: =0.15+(0.5/50.54) -> 0.15989315
A30: BYD Paterna | C30: Carga de lámparas/material | G30: BASTIDOR NORMAL 150 | H30: Pintura | I30: Lijado y/o Masillado | J30: =0.6+0.005+0.00055 -> 0.60555
A31: Estudio Ama | C31: Varias lamparas | G31: BASTIDOR NORMAL 150 | H31: Pintura | I31: Imprimación/Pintura | J31: =0.5+(0.009)+(0.0005)+0.014 -> 0.5235
A32: Casadecor | C32: Machimbrado | G32: BASTIDOR NORMAL 100 | H32: CNC | I32: CNC | J32: 0.35
A33: Druni Maisonnave Alicante | C33: supervisión | G33: BASTIDOR NORMAL 100 | H33: Fabricación | I33: Ensamblaje | J33: 1
A34: Novodecor | C34: Gestión nave | G34: BASTIDOR NORMAL 100 | H34: Fabricación | I34: Colocación de perfiles | J34: 0.2
A35: Druni Torre del mar | C35: Registro | G35: BASTIDOR NORMAL 100 | H35: Fabricación | I35: Embalaje/carga/descarga material | J35: 0.15
A36: Druni cc la Vie | C36: Perfil tela | G36: BASTIDOR NORMAL 100 | H36: Pintura | I36: Lijado y/o Masillado | J36: 0.6
A37: NOVODECOR Delybreads | C37: Perfil grand | G37: BASTIDOR NORMAL 100 | H37: Pintura | I37: Imprimación/Pintura | J37: 0.5
A38: Druni cc Leon | C38: Pasillo | G38: BASTIDOR NORMAL 50 | H38: CNC | I38: CNC | J38: 0.29
A39: Arenal vialia | C39: Bastidor normal 150 | G39: BASTIDOR NORMAL 50 | H39: Fabricación | I39: Ensamblaje | J39: 1
A40: Druni X Madrid | C40: Bastidor normal 100 | G40: BASTIDOR NORMAL 50 | H40: Fabricación | I40: Colocación de perfiles | J40: 0.2
A41: Saiho | C41: Caja de envío | G41: BASTIDOR NORMAL 50 | H41: Fabricación | I41: Embalaje/carga/descarga material | J41: 0.15
A42: Druni Baricentro | C42: Reunión | G42: BASTIDOR NORMAL 50 | H42: Pintura | I42: Lijado y/o Masillado | J42: 0.6
A43: Druni Añaza | C43: Mueble | G43: BASTIDOR NORMAL 50 | H43: Pintura | I43: Imprimación/Pintura | J43: 0.5
A44: Druni Parc Central | C44: Rayos | G44: HAIR - ESPEJO | H44: Fabricación | I44: Pegado de composite/chapa | J44: 0.52
A45: Culdesac-Coldculture | C45: Sol dinámico | G45: HAIR - ESPEJO | H45: Fabricación | I45: Embalaje/carga/descarga material | J45: =0.31+0.15 -> 0.46
A46: Druni PonteVella | C46: Curvas | G46: HAIR - ESPEJO | H46: CNC | I46: CNC | J46: 0.37
A47: BYD Barcelona | C47: Focos Nakamuta | G47: HAIR - ESPEJO | H47: Fabricación | I47: Ensamblaje | J47: 0.32
A48: YPLUSFIVE | C48: Lineales | G48: HAIR - ESPEJO | H48: Fabricación | I48: Colocación de perfiles | J48: 0.15
A49: Guerola oficinas Colon | C49: Estanteria | G49: HAIR - ESPEJO | H49: Pintura | I49: Imprimación/Pintura | J49: 0.1
C50: Bastidor separador | G50: CURVA SIMPLE | H50: CNC | I50: CNC | J50: 0.4
C51: Techo Stand | G51: CURVA SIMPLE | H51: Fabricación | I51: Ensamblaje | J51: 0.16
C52: Bastidor tela y metacrilato | G52: CURVA SIMPLE | H52: Fabricación | I52: Colocación de perfiles | J52: 0
C53: Policarbonato | G53: CURVA SIMPLE | H53: Fabricación | I53: Embalaje/carga/descarga material | J53: 0.1
C54: Bastidor especial | G54: CURVA SIMPLE | H54: Pintura | I54: Lijado y/o Masillado | J54: 0.6
C55: Malla Saiho | G55: CURVA SIMPLE | H55: Pintura | I55: Imprimación/Pintura | J55: 0.75
C56: Sol | G56: CURVA DOBLE | H56: CNC | I56: CNC | J56: 0.48
C57: Pilar | G57: CURVA DOBLE | H57: Fabricación | I57: Ensamblaje | J57: 0.16
C58: Cupula | G58: CURVA DOBLE | H58: Fabricación | I58: Colocación de perfiles | J58: 0
C59: Prototipo 2 | G59: CURVA DOBLE | H59: Fabricación | I59: Embalaje/carga/descarga material | J59: 0.1
C60: Prototipo 3 | G60: CURVA DOBLE | H60: Pintura | I60: Lijado y/o Masillado | J60: 0.7
C61: Capsula | G61: CURVA DOBLE | H61: Pintura | I61: Imprimación/Pintura | J61: 0.95
C62: Caja | G62: CANOPI | H62: CNC | I62: CNC | J62: 0.2
G63: CANOPI | H63: Fabricación | I63: Ensamblaje | J63: 0.9
G64: CANOPI | H64: Fabricación | I64: Colocación de perfiles | J64: 0.25
G65: CANOPI | H65: Fabricación | I65: Embalaje/carga/descarga material | J65: 0.15
G66: CANOPI | H66: Pintura | I66: Lijado y/o Masillado | J66: 0.5
G67: CANOPI | H67: Pintura | I67: Imprimación/Pintura | J67: 0.55
G68: BASTIDOR DE METACRILATO RECTO | H68: Fabricación | I68: Ensamblaje | J68: =0.57+0.33 -> 0.9
G69: BASTIDOR DE METACRILATO RECTO | H69: Fabricación | I69: Embalaje/carga/descarga material | J69: 0.17
G70: BASTIDOR DE METACRILATO CURVO | H70: Fabricación | I70: Ensamblaje | J70: =2.15+0.35 -> 2.5
G71: BASTIDOR DE METACRILATO CURVO | H71: Fabricación | I71: Embalaje/carga/descarga material | J71: 0.13
G72: BASTIDOR DE TABICA 300X12 | H72: CNC | I72: CNC | J72: =J2 -> 0.2
G73: BASTIDOR DE TABICA 300X12 | H73: Fabricación | I73: Ensamblaje | J73: 0.73
G74: BASTIDOR DE TABICA 300X12 | H74: Fabricación | I74: Colocación de perfiles | J74: 0.2
G75: BASTIDOR DE TABICA 300X12 | H75: Fabricación | I75: Embalaje/carga/descarga material | J75: 0.25
G76: BASTIDOR DE TABICA 300X12 | H76: Pintura | I76: Lijado y/o Masillado | J76: 0.531
G77: BASTIDOR DE TABICA 300X12 | H77: Pintura | I77: Imprimación/Pintura | J77: 0.472
G78: BASTIDOR DE TABICA CURVA 300X12 | H78: CNC | I78: CNC
G79: BASTIDOR DE TABICA CURVA 300X12 | H79: Fabricación | I79: Ensamblaje
G80: BASTIDOR DE TABICA CURVA 300X12 | H80: Fabricación | I80: Colocación de perfiles
G81: BASTIDOR DE TABICA CURVA 300X12 | H81: Fabricación | I81: Embalaje/carga/descarga material
G82: BASTIDOR DE TABICA CURVA 300X12 | H82: Pintura | I82: Lijado y/o Masillado
G83: BASTIDOR DE TABICA CURVA 300X12 | H83: Pintura | I83: Imprimación/Pintura
G84: CUPULA DE MADERA | H84: Fabricación | I84: Ensamblaje
G85: CUPULA DE MADERA | H85: Pintura | I85: Lijado y/o Masillado
G86: CUPULA DE MADERA | H86: Pintura | I86: Imprimación/Pintura
G87: CUPULA DE COMPOSITE | H87: Fabricación | I87: Ensamblaje | J87: 0.25
G88: CUPULA DE COMPOSITE | H88: Fabricación | I88: Embalaje/carga/descarga material | J88: 0.05
G89: CUPULA DE COMPOSITE | H89: Fabricación | I89: Corte manual | J89: 0.01
G90: BASTIDOR SEPARADOR DE SOL | H90: Fabricación | I90: Ensamblaje | J90: 0.7
G91: BASTIDOR SEPARADOR DE SOL | H91: Fabricación | I91: Embalaje/carga/descarga material | J91: 0.05
G92: RANURA PARA CHAPA | H92: CNC | I92: CNC | J92: 0.0475
G93: RANURA PARA CHAPA | H93: Fabricación | I93: Embalaje/carga/descarga material | J93: 0.0237
G94: RANURA PARA CHAPA | H94: Pintura | I94: Lijado y/o Masillado | J94: 0.01425
G95: RANURA PARA CHAPA | H95: Pintura | I95: Imprimación/Pintura | J95: 0.0594
G96: MALLA SAIHO VEGETACION | H96: Fabricación | I96: Ensamblaje | J96: 2
G97: MALLA SAIHO VEGETACION | H97: Fabricación | I97: Embalaje/carga/descarga material | J97: 0.05
G98: BASTIDOR ESPECIAL CURVA CULDESAC | H98: CNC | I98: CNC | J98: 0.2
G99: BASTIDOR ESPECIAL CURVA CULDESAC | H99: Fabricación | I99: Ensamblaje | J99: =0.79+(2/4.71) -> 1.2146284
G100: BASTIDOR ESPECIAL CURVA CULDESAC | H100: Fabricación | I100: Colocación de perfiles | J100: =0.2+(2/4.71) -> 0.62462845
...

Sheet 🗂️ Proyectos
A1: Proyecto | B1: Lampara | C1: Tipo_bastidor | D1: Medida | E1: Fecha_de_entrega | F1: Área | G1: Proceso | H1: Hr_plan | I1: Hr_total | J1: Hr_normal | K1: Hr_extra | L1: Prom/hr | M1: Hr_Pend | N1: Desviación | O1: %_Avance | P1: Estado | Q1: Estado_proyecto | R1: Avance
A2: Druni CC los alcores | B2: Gracos 2 | C2: BASTIDOR NORMAL 150 | D2: 50.54 | E2: 46080 | F2: CNC | G2: CNC | H2: =IFERROR(__xludf.DUMMYFUNCTION("(IFERROR(FILTER(BBDD!$J:$J,BBDD!$G:$G=C2,BBDD!$H:$H=F2,BBDD!$I:$I=G2),""NO TIENE PROCESO""))*D2"),19.689) -> 19.689 | I2: =J2+K2 -> 16.49 | J2: =SUMIFS('👷horas'!$J:$J,'👷horas'!$D:$D,A2,'👷horas'!$E:$E,B2,'👷horas'!$F:$F,F2,'👷horas'!$G:$G,G2) -> 16.49 | K2: =SUMIFS('👷horas'!$K:$K,'👷horas'!$D:$D,A2,'👷horas'!$E:$E,B2,'👷horas'!$F:$F,F2,'👷horas'!$G:$G,G2) -> 0 | L2: =I2/D2 -> 0.32627622 | M2: =IF(P2="TERMINADO",0,H2-(J2+K2)) -> 0 | N2: =1-(I2/H2) -> 0.16247651 | O2: =IF(NOT(ISNUMBER(H2)),0,IF(P2="Terminado",1,IF(J2=0,0,MIN(1,J2/H2)))) -> 1 | P2: Terminado | Q2: =IF(COUNTIFS(A:A,A2,P:P,"Terminado")=COUNTIF(A:A,A2),"Terminado",IF(COUNTIFS(A:A,A2,P:P,"En proceso")>0,"En proceso","Pendiente")) -> Terminado | R2: =IFERROR(__xludf.DUMMYFUNCTION("SPARKLINE(O2,{""charttype"",""bar"";""max"",1;""color1"",IF(P2=""Terminado"",""#4CAF50"",IF(O2>=0.5,""#FFA500"",""#F44336""))})"),"")
A3: Druni CC los alcores | B3: Gracos 2 | C3: BASTIDOR NORMAL 150 | D3: 50.54 | E3: 46080 | F3: Fabricación | G3: Ensamblaje | H3: =IFERROR(__xludf.DUMMYFUNCTION("(IFERROR(FILTER(BBDD!$J:$J,BBDD!$G:$G=C3,BBDD!$H:$H=F3,BBDD!$I:$I=G3),""NO TIENE PROCESO""))*D3"),54.04) -> 54.04 | I3: =J3+K3 -> 49.5 | J3: =SUMIFS('👷horas'!$J:$J,'👷horas'!$D:$D,A3,'👷horas'!$E:$E,B3,'👷horas'!$F:$F,F3,'👷horas'!$G:$G,G3) -> 37 | K3: =SUMIFS('👷horas'!$K:$K,'👷horas'!$D:$D,A3,'👷horas'!$E:$E,B3,'👷horas'!$F:$F,F3,'👷horas'!$G:$G,G3) -> 12.5 | L3: =I3/D3 -> 0.97942224 | M3: =IF(P3="TERMINADO",0,H3-(J3+K3)) -> 0 | N3: =1-(I3/H3) -> 0.084011843 | O3: =IF(NOT(ISNUMBER(H3)),0,IF(P3="Terminado",1,IF(J3=0,0,MIN(1,J3/H3)))) -> 1 | P3: Terminado | Q3: =IF(COUNTIFS(A:A,A3,P:P,"Terminado")=COUNTIF(A:A,A3),"Terminado",IF(COUNTIFS(A:A,A3,P:P,"En proceso")>0,"En proceso","Pendiente")) -> Terminado | R3: =IFERROR(__xludf.DUMMYFUNCTION("SPARKLINE(O3,{""charttype"",""bar"";""max"",1;""color1"",IF(P3=""Terminado"",""#4CAF50"",IF(O3>=0.5,""#FFA500"",""#F44336""))})"),"")
A4: Druni CC los alcores | B4: Gracos 2 | C4: BASTIDOR NORMAL 150 | D4: 50.54 | E4: 46080 | F4: Fabricación | G4: Colocación de perfiles | H4: =IFERROR(__xludf.DUMMYFUNCTION("(IFERROR(FILTER(BBDD!$J:$J,BBDD!$G:$G=C4,BBDD!$H:$H=F4,BBDD!$I:$I=G4),""NO TIENE PROCESO""))*D4"),10.108) -> 10.108 | I4: =J4+K4 -> 11.39 | J4: =SUMIFS('👷horas'!$J:$J,'👷horas'!$D:$D,A4,'👷horas'!$E:$E,B4,'👷horas'!$F:$F,F4,'👷horas'!$G:$G,G4) -> 11.39 | K4: =SUMIFS('👷horas'!$K:$K,'👷horas'!$D:$D,A4,'👷horas'!$E:$E,B4,'👷horas'!$F:$F,F4,'👷horas'!$G:$G,G4) -> 0 | L4: =I4/D4 -> 0.22536605 | M4: =IF(P4="TERMINADO",0,H4-(J4+K4)) -> 0 | N4: =1-(I4/H4) -> -0.12683023 | O4: =IF(NOT(ISNUMBER(H4)),0,IF(P4="Terminado",1,IF(J4=0,0,MIN(1,J4/H4)))) -> 1 | P4: Terminado | Q4: =IF(COUNTIFS(A:A,A4,P:P,"Terminado")=COUNTIF(A:A,A4),"Terminado",IF(COUNTIFS(A:A,A4,P:P,"En proceso")>0,"En proceso","Pendiente")) -> Terminado | R4: =IFERROR(__xludf.DUMMYFUNCTION("SPARKLINE(O4,{""charttype"",""bar"";""max"",1;""color1"",IF(P4=""Terminado"",""#4CAF50"",IF(O4>=0.5,""#FFA500"",""#F44336""))})"),"")
A5: Druni CC los alcores | B5: Gracos 2 | C5: BASTIDOR NORMAL 150 | D5: 50.54 | E5: 46080 | F5: Fabricación | G5: Embalaje/carga/descarga material | H5: =IFERROR(__xludf.DUMMYFUNCTION("(IFERROR(FILTER(BBDD!$J:$J,BBDD!$G:$G=C5,BBDD!$H:$H=F5,BBDD!$I:$I=G5),""NO TIENE PROCESO""))*D5"),8.081) -> 8.081 | I5: =J5+K5 -> 5.5 | J5: =SUMIFS('👷horas'!$J:$J,'👷horas'!$D:$D,A5,'👷horas'!$E:$E,B5,'👷horas'!$F:$F,F5,'👷horas'!$G:$G,G5) -> 5.5 | K5: =SUMIFS('👷horas'!$K:$K,'👷horas'!$D:$D,A5,'👷horas'!$E:$E,B5,'👷horas'!$F:$F,F5,'👷horas'!$G:$G,G5) -> 0 | L5: =I5/D5 -> 0.10882469 | M5: =IF(P5="TERMINADO",0,H5-(J5+K5)) -> 0 | N5: =1-(I5/H5) -> 0.31939116 | O5: =IF(NOT(ISNUMBER(H5)),0,IF(P5="Terminado",1,IF(J5=0,0,MIN(1,J5/H5)))) -> 1 | P5: Terminado | Q5: =IF(COUNTIFS(A:A,A5,P:P,"Terminado")=COUNTIF(A:A,A5),"Terminado",IF(COUNTIFS(A:A,A5,P:P,"En proceso")>0,"En proceso","Pendiente")) -> Terminado | R5: =IFERROR(__xludf.DUMMYFUNCTION("SPARKLINE(O5,{""charttype"",""bar"";""max"",1;""color1"",IF(P5=""Terminado"",""#4CAF50"",IF(O5>=0.5,""#FFA500"",""#F44336""))})"),"")
A6: Druni CC los alcores | B6: Gracos 2 | C6: BASTIDOR NORMAL 150 | D6: 50.54 | E6: 46080 | F6: Pintura | G6: Lijado y/o Masillado | H6: =IFERROR(__xludf.DUMMYFUNCTION("(IFERROR(FILTER(BBDD!$J:$J,BBDD!$G:$G=C6,BBDD!$H:$H=F6,BBDD!$I:$I=G6),""NO TIENE PROCESO""))*D6"),30.604497000000002) -> 30.604497 | I6: =J6+K6 -> 48.9025 | J6: =SUMIFS('👷horas'!$J:$J,'👷horas'!$D:$D,A6,'👷horas'!$E:$E,B6,'👷horas'!$F:$F,F6,'👷horas'!$G:$G,G6) -> 41.9025 | K6: =SUMIFS('👷horas'!$K:$K,'👷horas'!$D:$D,A6,'👷horas'!$E:$E,B6,'👷horas'!$F:$F,F6,'👷horas'!$G:$G,G6) -> 7 | L6: =I6/D6 -> 0.96759992 | M6: =IF(P6="TERMINADO",0,H6-(J6+K6)) -> 0 | N6: =1-(I6/H6) -> -0.59788609 | O6: =IF(NOT(ISNUMBER(H6)),0,IF(P6="Terminado",1,IF(J6=0,0,MIN(1,J6/H6)))) -> 1 | P6: Terminado | Q6: =IF(COUNTIFS(A:A,A6,P:P,"Terminado")=COUNTIF(A:A,A6),"Terminado",IF(COUNTIFS(A:A,A6,P:P,"En proceso")>0,"En proceso","Pendiente")) -> Terminado | R6: =IFERROR(__xludf.DUMMYFUNCTION("SPARKLINE(O6,{""charttype"",""bar"";""max"",1;""color1"",IF(P6=""Terminado"",""#4CAF50"",IF(O6>=0.5,""#FFA500"",""#F44336""))})"),"")
A7: Druni CC los alcores | B7: Gracos 2 | C7: BASTIDOR NORMAL 150 | D7: 50.54 | E7: 46080 | F7: Pintura | G7: Imprimación/Pintura | H7: =IFERROR(__xludf.DUMMYFUNCTION("(IFERROR(FILTER(BBDD!$J:$J,BBDD!$G:$G=C7,BBDD!$H:$H=F7,BBDD!$I:$I=G7),""NO TIENE PROCESO""))*D7"),26.45769) -> 26.45769 | I7: =J7+K7 -> 18.7 | J7: =SUMIFS('👷horas'!$J:$J,'👷horas'!$D:$D,A7,'👷horas'!$E:$E,B7,'👷horas'!$F:$F,F7,'👷horas'!$G:$G,G7) -> 11.7 | K7: =SUMIFS('👷horas'!$K:$K,'👷horas'!$D:$D,A7,'👷horas'!$E:$E,B7,'👷horas'!$F:$F,F7,'👷horas'!$G:$G,G7) -> 7 | L7: =I7/D7 -> 0.37000396 | M7: =IF(P7="TERMINADO",0,H7-(J7+K7)) -> 0 | N7: =1-(I7/H7) -> 0.29321116 | O7: =IF(NOT(ISNUMBER(H7)),0,IF(P7="Terminado",1,IF(J7=0,0,MIN(1,J7/H7)))) -> 1 | P7: Terminado | Q7: =IF(COUNTIFS(A:A,A7,P:P,"Terminado")=COUNTIF(A:A,A7),"Terminado",IF(COUNTIFS(A:A,A7,P:P,"En proceso")>0,"En proceso","Pendiente")) -> Terminado | R7: =IFERROR(__xludf.DUMMYFUNCTION("SPARKLINE(O7,{""charttype"",""bar"";""max"",1;""color1"",IF(P7=""Terminado"",""#4CAF50"",IF(O7>=0.5,""#FFA500"",""#F44336""))})"),"")
A8: Druni CC los alcores | B8: Gracos | C8: BASTIDOR NORMAL 100 | D8: 17.91 | E8: 46080 | F8: =IFERROR(__xludf.DUMMYFUNCTION("FILTER(BBDD!H:H,BBDD!G:G=C8)"),"CNC") -> CNC | G8: =IFERROR(__xludf.DUMMYFUNCTION("FILTER(BBDD!I:I,BBDD!G:G=C8)"),"CNC") -> CNC | H8: =IFERROR(__xludf.DUMMYFUNCTION("(IFERROR(FILTER(BBDD!$J:$J,BBDD!$G:$G=C8,BBDD!$H:$H=F8,BBDD!$I:$I=G8),""NO TIENE PROCESO""))*D8"),6.2684999999999995) -> 6.2685 | I8: =J8+K8 -> 6.3 | J8: =SUMIFS('👷horas'!$J:$J,'👷horas'!$D:$D,A8,'👷horas'!$E:$E,B8,'👷horas'!$F:$F,F8,'👷horas'!$G:$G,G8) -> 6.3 | K8: =SUMIFS('👷horas'!$K:$K,'👷horas'!$D:$D,A8,'👷horas'!$E:$E,B8,'👷horas'!$F:$F,F8,'👷horas'!$G:$G,G8) -> 0 | L8: =I8/D8 -> 0.35175879 | M8: =IF(P8="TERMINADO",0,H8-(J8+K8)) -> 0 | N8: =1-(I8/H8) -> -0.0050251256 | O8: =IF(NOT(ISNUMBER(H8)),0,IF(P8="Terminado",1,IF(J8=0,0,MIN(1,J8/H8)))) -> 1 | P8: Terminado | Q8: =IF(COUNTIFS(A:A,A8,P:P,"Terminado")=COUNTIF(A:A,A8),"Terminado",IF(COUNTIFS(A:A,A8,P:P,"En proceso")>0,"En proceso","Pendiente")) -> Terminado | R8: =IFERROR(__xludf.DUMMYFUNCTION("SPARKLINE(O8,{""charttype"",""bar"";""max"",1;""color1"",IF(P8=""Terminado"",""#4CAF50"",IF(O8>=0.5,""#FFA500"",""#F44336""))})"),"")
A9: Druni CC los alcores | B9: Gracos | C9: BASTIDOR NORMAL 100 | D9: 17.91 | E9: 46080 | F9: =IFERROR(__xludf.DUMMYFUNCTION("""COMPUTED_VALUE"""),"Fabricación") -> Fabricación | G9: =IFERROR(__xludf.DUMMYFUNCTION("""COMPUTED_VALUE"""),"Ensamblaje") -> Ensamblaje | H9: =IFERROR(__xludf.DUMMYFUNCTION("(IFERROR(FILTER(BBDD!$J:$J,BBDD!$G:$G=C9,BBDD!$H:$H=F9,BBDD!$I:$I=G9),""NO TIENE PROCESO""))*D9"),17.91) -> 17.91 | I9: =J9+K9 -> 18 | J9: =SUMIFS('👷horas'!$J:$J,'👷horas'!$D:$D,A9,'👷horas'!$E:$E,B9,'👷horas'!$F:$F,F9,'👷horas'!$G:$G,G9) -> 18 | K9: =SUMIFS('👷horas'!$K:$K,'👷horas'!$D:$D,A9,'👷horas'!$E:$E,B9,'👷horas'!$F:$F,F9,'👷horas'!$G:$G,G9) -> 0 | L9: =I9/D9 -> 1.0050251 | M9: =IF(P9="TERMINADO",0,H9-(J9+K9)) -> 0 | N9: =1-(I9/H9) -> -0.0050251256 | O9: =IF(NOT(ISNUMBER(H9)),0,IF(P9="Terminado",1,IF(J9=0,0,MIN(1,J9/H9)))) -> 1 | P9: Terminado | Q9: =IF(COUNTIFS(A:A,A9,P:P,"Terminado")=COUNTIF(A:A,A9),"Terminado",IF(COUNTIFS(A:A,A9,P:P,"En proceso")>0,"En proceso","Pendiente")) -> Terminado | R9: =IFERROR(__xludf.DUMMYFUNCTION("SPARKLINE(O9,{""charttype"",""bar"";""max"",1;""color1"",IF(P9=""Terminado"",""#4CAF50"",IF(O9>=0.5,""#FFA500"",""#F44336""))})"),"")
A10: Druni CC los alcores | B10: Gracos | C10: BASTIDOR NORMAL 100 | D10: 17.91 | E10: 46080 | F10: =IFERROR(__xludf.DUMMYFUNCTION("""COMPUTED_VALUE"""),"Fabricación") -> Fabricación | G10: =IFERROR(__xludf.DUMMYFUNCTION("""COMPUTED_VALUE"""),"Colocación de perfiles") -> Colocación de perfiles | H10: =IFERROR(__xludf.DUMMYFUNCTION("(IFERROR(FILTER(BBDD!$J:$J,BBDD!$G:$G=C10,BBDD!$H:$H=F10,BBDD!$I:$I=G10),""NO TIENE PROCESO""))*D10"),3.5820000000000003) -> 3.582 | I10: =J10+K10 -> 3.594 | J10: =SUMIFS('👷horas'!$J:$J,'👷horas'!$D:$D,A10,'👷horas'!$E:$E,B10,'👷horas'!$F:$F,F10,'👷horas'!$G:$G,G10) -> 3.594 | K10: =SUMIFS('👷horas'!$K:$K,'👷horas'!$D:$D,A10,'👷horas'!$E:$E,B10,'👷horas'!$F:$F,F10,'👷horas'!$G:$G,G10) -> 0 | L10: =I10/D10 -> 0.20067002 | M10: =IF(P10="TERMINADO",0,H10-(J10+K10)) -> 0 | N10: =1-(I10/H10) -> -0.0033500838 | O10: =IF(NOT(ISNUMBER(H10)),0,IF(P10="Terminado",1,IF(J10=0,0,MIN(1,J10/H10)))) -> 1 | P10: Terminado | Q10: =IF(COUNTIFS(A:A,A10,P:P,"Terminado")=COUNTIF(A:A,A10),"Terminado",IF(COUNTIFS(A:A,A10,P:P,"En proceso")>0,"En proceso","Pendiente")) -> Terminado | R10: =IFERROR(__xludf.DUMMYFUNCTION("SPARKLINE(O10,{""charttype"",""bar"";""max"",1;""color1"",IF(P10=""Terminado"",""#4CAF50"",IF(O10>=0.5,""#FFA500"",""#F44336""))})"),"")
A11: Druni CC los alcores | B11: Gracos | C11: BASTIDOR NORMAL 100 | D11: 17.91 | E11: 46080 | F11: =IFERROR(__xludf.DUMMYFUNCTION("""COMPUTED_VALUE"""),"Fabricación") -> Fabricación | G11: =IFERROR(__xludf.DUMMYFUNCTION("""COMPUTED_VALUE"""),"Embalaje/carga/descarga material") -> Embalaje/carga/descarga material | H11: =IFERROR(__xludf.DUMMYFUNCTION("(IFERROR(FILTER(BBDD!$J:$J,BBDD!$G:$G=C11,BBDD!$H:$H=F11,BBDD!$I:$I=G11),""NO TIENE PROCESO""))*D11"),2.6865) -> 2.6865 | I11: =J11+K11 -> 2.5 | J11: =SUMIFS('👷horas'!$J:$J,'👷horas'!$D:$D,A11,'👷horas'!$E:$E,B11,'👷horas'!$F:$F,F11,'👷horas'!$G:$G,G11) -> 2.5 | K11: =SUMIFS('👷horas'!$K:$K,'👷horas'!$D:$D,A11,'👷horas'!$E:$E,B11,'👷horas'!$F:$F,F11,'👷horas'!$G:$G,G11) -> 0 | L11: =I11/D11 -> 0.13958682 | M11: =IF(P11="TERMINADO",0,H11-(J11+K11)) -> 0 | N11: =1-(I11/H11) -> 0.06942118 | O11: =IF(NOT(ISNUMBER(H11)),0,IF(P11="Terminado",1,IF(J11=0,0,MIN(1,J11/H11)))) -> 1 | P11: Terminado | Q11: =IF(COUNTIFS(A:A,A11,P:P,"Terminado")=COUNTIF(A:A,A11),"Terminado",IF(COUNTIFS(A:A,A11,P:P,"En proceso")>0,"En proceso","Pendiente")) -> Terminado | R11: =IFERROR(__xludf.DUMMYFUNCTION("SPARKLINE(O11,{""charttype"",""bar"";""max"",1;""color1"",IF(P11=""Terminado"",""#4CAF50"",IF(O11>=0.5,""#FFA500"",""#F44336""))})"),"")
A12: Druni CC los alcores | B12: Gracos | C12: BASTIDOR NORMAL 100 | D12: 17.91 | E12: 46080 | F12: =IFERROR(__xludf.DUMMYFUNCTION("""COMPUTED_VALUE"""),"Pintura") -> Pintura | G12: =IFERROR(__xludf.DUMMYFUNCTION("""COMPUTED_VALUE"""),"Lijado y/o Masillado") -> Lijado y/o Masillado | H12: =IFERROR(__xludf.DUMMYFUNCTION("(IFERROR(FILTER(BBDD!$J:$J,BBDD!$G:$G=C12,BBDD!$H:$H=F12,BBDD!$I:$I=G12),""NO TIENE PROCESO""))*D12"),10.746) -> 10.746 | I12: =J12+K12 -> 16.5975 | J12: =SUMIFS('👷horas'!$J:$J,'👷horas'!$D:$D,A12,'👷horas'!$E:$E,B12,'👷horas'!$F:$F,F12,'👷horas'!$G:$G,G12) -> 16.5975 | K12: =SUMIFS('👷horas'!$K:$K,'👷horas'!$D:$D,A12,'👷horas'!$E:$E,B12,'👷horas'!$F:$F,F12,'👷horas'!$G:$G,G12) -> 0 | L12: =I12/D12 -> 0.92671692 | M12: =IF(P12="TERMINADO",0,H12-(J12+K12)) -> 0 | N12: =1-(I12/H12) -> -0.5445282 | O12: =IF(NOT(ISNUMBER(H12)),0,IF(P12="Terminado",1,IF(J12=0,0,MIN(1,J12/H12)))) -> 1 | P12: Terminado | Q12: =IF(COUNTIFS(A:A,A12,P:P,"Terminado")=COUNTIF(A:A,A12),"Terminado",IF(COUNTIFS(A:A,A12,P:P,"En proceso")>0,"En proceso","Pendiente")) -> Terminado | R12: =IFERROR(__xludf.DUMMYFUNCTION("SPARKLINE(O12,{""charttype"",""bar"";""max"",1;""color1"",IF(P12=""Terminado"",""#4CAF50"",IF(O12>=0.5,""#FFA500"",""#F44336""))})"),"")
A13: Druni CC los alcores | B13: Gracos | C13: BASTIDOR NORMAL 100 | D13: 17.91 | E13: 46080 | F13: =IFERROR(__xludf.DUMMYFUNCTION("""COMPUTED_VALUE"""),"Pintura") -> Pintura | G13: =IFERROR(__xludf.DUMMYFUNCTION("""COMPUTED_VALUE"""),"Imprimación/Pintura") -> Imprimación/Pintura | H13: =IFERROR(__xludf.DUMMYFUNCTION("(IFERROR(FILTER(BBDD!$J:$J,BBDD!$G:$G=C13,BBDD!$H:$H=F13,BBDD!$I:$I=G13),""NO TIENE PROCESO""))*D13"),8.955) -> 8.955 | I13: =J13+K13 -> 9 | J13: =SUMIFS('👷horas'!$J:$J,'👷horas'!$D:$D,A13,'👷horas'!$E:$E,B13,'👷horas'!$F:$F,F13,'👷horas'!$G:$G,G13) -> 9 | K13: =SUMIFS('👷horas'!$K:$K,'👷horas'!$D:$D,A13,'👷horas'!$E:$E,B13,'👷horas'!$F:$F,F13,'👷horas'!$G:$G,G13) -> 0 | L13: =I13/D13 -> 0.50251256 | M13: =IF(P13="TERMINADO",0,H13-(J13+K13)) -> 0 | N13: =1-(I13/H13) -> -0.0050251256 | O13: =IF(NOT(ISNUMBER(H13)),0,IF(P13="Terminado",1,IF(J13=0,0,MIN(1,J13/H13)))) -> 1 | P13: Terminado | Q13: =IF(COUNTIFS(A:A,A13,P:P,"Terminado")=COUNTIF(A:A,A13),"Terminado",IF(COUNTIFS(A:A,A13,P:P,"En proceso")>0,"En proceso","Pendiente")) -> Terminado | R13: =IFERROR(__xludf.DUMMYFUNCTION("SPARKLINE(O13,{""charttype"",""bar"";""max"",1;""color1"",IF(P13=""Terminado"",""#4CAF50"",IF(O13>=0.5,""#FFA500"",""#F44336""))})"),"")
A14: Druni Parc Central | B14: Cruz | C14: BASTIDOR DE TABICA 150X12 | D14: 17.5 | E14: 46084 | F14: =IFERROR(__xludf.DUMMYFUNCTION("FILTER(BBDD!H:H,BBDD!G:G=C14)"),"CNC") -> CNC | G14: =IFERROR(__xludf.DUMMYFUNCTION("FILTER(BBDD!I:I,BBDD!G:G=C14)"),"CNC") -> CNC | H14: =IFERROR(__xludf.DUMMYFUNCTION("(IFERROR(FILTER(BBDD!$J:$J,BBDD!$G:$G=C14,BBDD!$H:$H=F14,BBDD!$I:$I=G14),""NO TIENE PROCESO""))*D14"),3.5) -> 3.5 | I14: =J14+K14 -> 1.5 | J14: =SUMIFS('👷horas'!$J:$J,'👷horas'!$D:$D,A14,'👷horas'!$E:$E,B14,'👷horas'!$F:$F,F14,'👷horas'!$G:$G,G14) -> 1.5 | K14: =SUMIFS('👷horas'!$K:$K,'👷horas'!$D:$D,A14,'👷horas'!$E:$E,B14,'👷horas'!$F:$F,F14,'👷horas'!$G:$G,G14) -> 0 | L14: =I14/D14 -> 0.085714286 | M14: =IF(P14="TERMINADO",0,H14-(J14+K14)) -> 0 | N14: =1-(I14/H14) -> 0.57142857 | O14: =IF(NOT(ISNUMBER(H14)),0,IF(P14="Terminado",1,IF(J14=0,0,MIN(1,J14/H14)))) -> 1 | P14: Terminado | Q14: =IF(COUNTIFS(A:A,A14,P:P,"Terminado")=COUNTIF(A:A,A14),"Terminado",IF(COUNTIFS(A:A,A14,P:P,"En proceso")>0,"En proceso","Pendiente")) -> Terminado | R14: =IFERROR(__xludf.DUMMYFUNCTION("SPARKLINE(O14,{""charttype"",""bar"";""max"",1;""color1"",IF(P14=""Terminado"",""#4CAF50"",IF(O14>=0.5,""#FFA500"",""#F44336""))})"),"")
A15: Druni Parc Central | B15: Cruz | C15: BASTIDOR DE TABICA 150X12 | D15: 17.5 | E15: 46084 | F15: =IFERROR(__xludf.DUMMYFUNCTION("""COMPUTED_VALUE"""),"Fabricación") -> Fabricación | G15: =IFERROR(__xludf.DUMMYFUNCTION("""COMPUTED_VALUE"""),"Ensamblaje") -> Ensamblaje | H15: =IFERROR(__xludf.DUMMYFUNCTION("(IFERROR(FILTER(BBDD!$J:$J,BBDD!$G:$G=C15,BBDD!$H:$H=F15,BBDD!$I:$I=G15),""NO TIENE PROCESO""))*D15"),10.85) -> 10.85 | I15: =J15+K15 -> 11.75 | J15: =SUMIFS('👷horas'!$J:$J,'👷horas'!$D:$D,A15,'👷horas'!$E:$E,B15,'👷horas'!$F:$F,F15,'👷horas'!$G:$G,G15) -> 11.75 | K15: =SUMIFS('👷horas'!$K:$K,'👷horas'!$D:$D,A15,'👷horas'!$E:$E,B15,'👷horas'!$F:$F,F15,'👷horas'!$G:$G,G15) -> 0 | L15: =I15/D15 -> 0.67142857 | M15: =IF(P15="TERMINADO",0,H15-(J15+K15)) -> 0 | N15: =1-(I15/H15) -> -0.082949309 | O15: =IF(NOT(ISNUMBER(H15)),0,IF(P15="Terminado",1,IF(J15=0,0,MIN(1,J15/H15)))) -> 1 | P15: Terminado | Q15: =IF(COUNTIFS(A:A,A15,P:P,"Terminado")=COUNTIF(A:A,A15),"Terminado",IF(COUNTIFS(A:A,A15,P:P,"En proceso")>0,"En proceso","Pendiente")) -> Terminado | R15: =IFERROR(__xludf.DUMMYFUNCTION("SPARKLINE(O15,{""charttype"",""bar"";""max"",1;""color1"",IF(P15=""Terminado"",""#4CAF50"",IF(O15>=0.5,""#FFA500"",""#F44336""))})"),"")
A16: Druni Parc Central | B16: Cruz | C16: BASTIDOR DE TABICA 150X12 | D16: 17.5 | E16: 46084 | F16: =IFERROR(__xludf.DUMMYFUNCTION("""COMPUTED_VALUE"""),"Fabricación") -> Fabricación | G16: =IFERROR(__xludf.DUMMYFUNCTION("""COMPUTED_VALUE"""),"Colocación de perfiles") -> Colocación de perfiles | H16: =IFERROR(__xludf.DUMMYFUNCTION("(IFERROR(FILTER(BBDD!$J:$J,BBDD!$G:$G=C16,BBDD!$H:$H=F16,BBDD!$I:$I=G16),""NO TIENE PROCESO""))*D16"),3.5) -> 3.5 | I16: =J16+K16 -> 5.5 | J16: =SUMIFS('👷horas'!$J:$J,'👷horas'!$D:$D,A16,'👷horas'!$E:$E,B16,'👷horas'!$F:$F,F16,'👷horas'!$G:$G,G16) -> 5.5 | K16: =SUMIFS('👷horas'!$K:$K,'👷horas'!$D:$D,A16,'👷horas'!$E:$E,B16,'👷horas'!$F:$F,F16,'👷horas'!$G:$G,G16) -> 0 | L16: =I16/D16 -> 0.31428571 | M16: =IF(P16="TERMINADO",0,H16-(J16+K16)) -> 0 | N16: =1-(I16/H16) -> -0.57142857 | O16: =IF(NOT(ISNUMBER(H16)),0,IF(P16="Terminado",1,IF(J16=0,0,MIN(1,J16/H16)))) -> 1 | P16: Terminado | Q16: =IF(COUNTIFS(A:A,A16,P:P,"Terminado")=COUNTIF(A:A,A16),"Terminado",IF(COUNTIFS(A:A,A16,P:P,"En proceso")>0,"En proceso","Pendiente")) -> Terminado | R16: =IFERROR(__xludf.DUMMYFUNCTION("SPARKLINE(O16,{""charttype"",""bar"";""max"",1;""color1"",IF(P16=""Terminado"",""#4CAF50"",IF(O16>=0.5,""#FFA500"",""#F44336""))})"),"")
A17: Druni Parc Central | B17: Cruz | C17: BASTIDOR DE TABICA 150X12 | D17: 17.5 | E17: 46084 | F17: =IFERROR(__xludf.DUMMYFUNCTION("""COMPUTED_VALUE"""),"Fabricación") -> Fabricación | G17: =IFERROR(__xludf.DUMMYFUNCTION("""COMPUTED_VALUE"""),"Embalaje/carga/descarga material") -> Embalaje/carga/descarga material | H17: =IFERROR(__xludf.DUMMYFUNCTION("(IFERROR(FILTER(BBDD!$J:$J,BBDD!$G:$G=C17,BBDD!$H:$H=F17,BBDD!$I:$I=G17),""NO TIENE PROCESO""))*D17"),2.625) -> 2.625 | I17: =J17+K17 -> 2 | J17: =SUMIFS('👷horas'!$J:$J,'👷horas'!$D:$D,A17,'👷horas'!$E:$E,B17,'👷horas'!$F:$F,F17,'👷horas'!$G:$G,G17) -> 2 | K17: =SUMIFS('👷horas'!$K:$K,'👷horas'!$D:$D,A17,'👷horas'!$E:$E,B17,'👷horas'!$F:$F,F17,'👷horas'!$G:$G,G17) -> 0 | L17: =I17/D17 -> 0.11428571 | M17: =IF(P17="TERMINADO",0,H17-(J17+K17)) -> 0 | N17: =1-(I17/H17) -> 0.23809524 | O17: =IF(NOT(ISNUMBER(H17)),0,IF(P17="Terminado",1,IF(J17=0,0,MIN(1,J17/H17)))) -> 1 | P17: Terminado | Q17: =IF(COUNTIFS(A:A,A17,P:P,"Terminado")=COUNTIF(A:A,A17),"Terminado",IF(COUNTIFS(A:A,A17,P:P,"En proceso")>0,"En proceso","Pendiente")) -> Terminado | R17: =IFERROR(__xludf.DUMMYFUNCTION("SPARKLINE(O17,{""charttype"",""bar"";""max"",1;""color1"",IF(P17=""Terminado"",""#4CAF50"",IF(O17>=0.5,""#FFA500"",""#F44336""))})"),"")
A18: Druni Parc Central | B18: Cruz | C18: BASTIDOR DE TABICA 150X12 | D18: 17.5 | E18: 46084 | F18: =IFERROR(__xludf.DUMMYFUNCTION("""COMPUTED_VALUE"""),"Pintura") -> Pintura | G18: =IFERROR(__xludf.DUMMYFUNCTION("""COMPUTED_VALUE"""),"Lijado y/o Masillado") -> Lijado y/o Masillado | H18: =IFERROR(__xludf.DUMMYFUNCTION("(IFERROR(FILTER(BBDD!$J:$J,BBDD!$G:$G=C18,BBDD!$H:$H=F18,BBDD!$I:$I=G18),""NO TIENE PROCESO""))*D18"),8.75) -> 8.75 | I18: =J18+K18 -> 19.5 | J18: =SUMIFS('👷horas'!$J:$J,'👷horas'!$D:$D,A18,'👷horas'!$E:$E,B18,'👷horas'!$F:$F,F18,'👷horas'!$G:$G,G18) -> 18 | K18: =SUMIFS('👷horas'!$K:$K,'👷horas'!$D:$D,A18,'👷horas'!$E:$E,B18,'👷horas'!$F:$F,F18,'👷horas'!$G:$G,G18) -> 1.5 | L18: =I18/D18 -> 1.1142857 | M18: =IF(P18="TERMINADO",0,H18-(J18+K18)) -> 0 | N18: =1-(I18/H18) -> -1.2285714 | O18: =IF(NOT(ISNUMBER(H18)),0,IF(P18="Terminado",1,IF(J18=0,0,MIN(1,J18/H18)))) -> 1 | P18: Terminado | Q18: =IF(COUNTIFS(A:A,A18,P:P,"Terminado")=COUNTIF(A:A,A18),"Terminado",IF(COUNTIFS(A:A,A18,P:P,"En proceso")>0,"En proceso","Pendiente")) -> Terminado | R18: =IFERROR(__xludf.DUMMYFUNCTION("SPARKLINE(O18,{""charttype"",""bar"";""max"",1;""color1"",IF(P18=""Terminado"",""#4CAF50"",IF(O18>=0.5,""#FFA500"",""#F44336""))})"),"")
A19: Druni Parc Central | B19: Cruz | C19: BASTIDOR DE TABICA 150X12 | D19: 17.5 | E19: 46084 | F19: =IFERROR(__xludf.DUMMYFUNCTION("""COMPUTED_VALUE"""),"Pintura") -> Pintura | G19: =IFERROR(__xludf.DUMMYFUNCTION("""COMPUTED_VALUE"""),"Imprimación/Pintura") -> Imprimación/Pintura | H19: =IFERROR(__xludf.DUMMYFUNCTION("(IFERROR(FILTER(BBDD!$J:$J,BBDD!$G:$G=C19,BBDD!$H:$H=F19,BBDD!$I:$I=G19),""NO TIENE PROCESO""))*D19"),7.0) -> 7 | I19: =J19+K19 -> 6.3 | J19: =SUMIFS('👷horas'!$J:$J,'👷horas'!$D:$D,A19,'👷horas'!$E:$E,B19,'👷horas'!$F:$F,F19,'👷horas'!$G:$G,G19) -> 6.3 | K19: =SUMIFS('👷horas'!$K:$K,'👷horas'!$D:$D,A19,'👷horas'!$E:$E,B19,'👷horas'!$F:$F,F19,'👷horas'!$G:$G,G19) -> 0 | L19: =I19/D19 -> 0.36 | M19: =IF(P19="TERMINADO",0,H19-(J19+K19)) -> 0 | N19: =1-(I19/H19) -> 0.1 | O19: =IF(NOT(ISNUMBER(H19)),0,IF(P19="Terminado",1,IF(J19=0,0,MIN(1,J19/H19)))) -> 1 | P19: Terminado | Q19: =IF(COUNTIFS(A:A,A19,P:P,"Terminado")=COUNTIF(A:A,A19),"Terminado",IF(COUNTIFS(A:A,A19,P:P,"En proceso")>0,"En proceso","Pendiente")) -> Terminado | R19: =IFERROR(__xludf.DUMMYFUNCTION("SPARKLINE(O19,{""charttype"",""bar"";""max"",1;""color1"",IF(P19=""Terminado"",""#4CAF50"",IF(O19>=0.5,""#FFA500"",""#F44336""))})"),"")
A20: Druni Parc Central | B20: Ameba | C20: BASTIDOR DE TABICA CURVA 150X12 | D20: 13.7 | E20: 46084 | F20: =IFERROR(__xludf.DUMMYFUNCTION("FILTER(BBDD!H:H,BBDD!G:G=C20)"),"CNC") -> CNC | G20: =IFERROR(__xludf.DUMMYFUNCTION("FILTER(BBDD!I:I,BBDD!G:G=C20)"),"CNC") -> CNC | H20: =IFERROR(__xludf.DUMMYFUNCTION("(IFERROR(FILTER(BBDD!$J:$J,BBDD!$G:$G=C20,BBDD!$H:$H=F20,BBDD!$I:$I=G20),""NO TIENE PROCESO""))*D20"),2.74) -> 2.74 | I20: =J20+K20 -> 1 | J20: =SUMIFS('👷horas'!$J:$J,'👷horas'!$D:$D,A20,'👷horas'!$E:$E,B20,'👷horas'!$F:$F,F20,'👷horas'!$G:$G,G20) -> 1 | K20: =SUMIFS('👷horas'!$K:$K,'👷horas'!$D:$D,A20,'👷horas'!$E:$E,B20,'👷horas'!$F:$F,F20,'👷horas'!$G:$G,G20) -> 0 | L20: =I20/D20 -> 0.072992701 | M20: =IF(P20="TERMINADO",0,H20-(J20+K20)) -> 0 | N20: =1-(I20/H20) -> 0.6350365 | O20: =IF(NOT(ISNUMBER(H20)),0,IF(P20="Terminado",1,IF(J20=0,0,MIN(1,J20/H20)))) -> 1 | P20: Terminado | Q20: =IF(COUNTIFS(A:A,A20,P:P,"Terminado")=COUNTIF(A:A,A20),"Terminado",IF(COUNTIFS(A:A,A20,P:P,"En proceso")>0,"En proceso","Pendiente")) -> Terminado | R20: =IFERROR(__xludf.DUMMYFUNCTION("SPARKLINE(O20,{""charttype"",""bar"";""max"",1;""color1"",IF(P20=""Terminado"",""#4CAF50"",IF(O20>=0.5,""#FFA500"",""#F44336""))})"),"")
A21: Druni Parc Central | B21: Ameba | C21: BASTIDOR DE TABICA CURVA 150X12 | D21: 13.7 | E21: 46084 | F21: =IFERROR(__xludf.DUMMYFUNCTION("""COMPUTED_VALUE"""),"Fabricación") -> Fabricación | G21: =IFERROR(__xludf.DUMMYFUNCTION("""COMPUTED_VALUE"""),"Ensamblaje") -> Ensamblaje | H21: =IFERROR(__xludf.DUMMYFUNCTION("(IFERROR(FILTER(BBDD!$J:$J,BBDD!$G:$G=C21,BBDD!$H:$H=F21,BBDD!$I:$I=G21),""NO TIENE PROCESO""))*D21"),10.823) -> 10.823 | I21: =J21+K21 -> 11.5 | J21: =SUMIFS('👷horas'!$J:$J,'👷horas'!$D:$D,A21,'👷horas'!$E:$E,B21,'👷horas'!$F:$F,F21,'👷horas'!$G:$G,G21) -> 11.5 | K21: =SUMIFS('👷horas'!$K:$K,'👷horas'!$D:$D,A21,'👷horas'!$E:$E,B21,'👷horas'!$F:$F,F21,'👷horas'!$G:$G,G21) -> 0 | L21: =I21/D21 -> 0.83941606 | M21: =IF(P21="TERMINADO",0,H21-(J21+K21)) -> 0 | N21: =1-(I21/H21) -> -0.062551973 | O21: =IF(NOT(ISNUMBER(H21)),0,IF(P21="Terminado",1,IF(J21=0,0,MIN(1,J21/H21)))) -> 1 | P21: Terminado | Q21: =IF(COUNTIFS(A:A,A21,P:P,"Terminado")=COUNTIF(A:A,A21),"Terminado",IF(COUNTIFS(A:A,A21,P:P,"En proceso")>0,"En proceso","Pendiente")) -> Terminado | R21: =IFERROR(__xludf.DUMMYFUNCTION("SPARKLINE(O21,{""charttype"",""bar"";""max"",1;""color1"",IF(P21=""Terminado"",""#4CAF50"",IF(O21>=0.5,""#FFA500"",""#F44336""))})"),"")
A22: Druni Parc Central | B22: Ameba | C22: BASTIDOR DE TABICA CURVA 150X12 | D22: 13.7 | E22: 46084 | F22: =IFERROR(__xludf.DUMMYFUNCTION("""COMPUTED_VALUE"""),"Fabricación") -> Fabricación | G22: =IFERROR(__xludf.DUMMYFUNCTION("""COMPUTED_VALUE"""),"Colocación de perfiles") -> Colocación de perfiles | H22: =IFERROR(__xludf.DUMMYFUNCTION("(IFERROR(FILTER(BBDD!$J:$J,BBDD!$G:$G=C22,BBDD!$H:$H=F22,BBDD!$I:$I=G22),""NO TIENE PROCESO""))*D22"),2.74) -> 2.74 | I22: =J22+K22 -> 8.5 | J22: =SUMIFS('👷horas'!$J:$J,'👷horas'!$D:$D,A22,'👷horas'!$E:$E,B22,'👷horas'!$F:$F,F22,'👷horas'!$G:$G,G22) -> 8.5 | K22: =SUMIFS('👷horas'!$K:$K,'👷horas'!$D:$D,A22,'👷horas'!$E:$E,B22,'👷horas'!$F:$F,F22,'👷horas'!$G:$G,G22) -> 0 | L22: =I22/D22 -> 0.62043796 | M22: =IF(P22="TERMINADO",0,H22-(J22+K22)) -> 0 | N22: =1-(I22/H22) -> -2.1021898 | O22: =IF(NOT(ISNUMBER(H22)),0,IF(P22="Terminado",1,IF(J22=0,0,MIN(1,J22/H22)))) -> 1 | P22: Terminado | Q22: =IF(COUNTIFS(A:A,A22,P:P,"Terminado")=COUNTIF(A:A,A22),"Terminado",IF(COUNTIFS(A:A,A22,P:P,"En proceso")>0,"En proceso","Pendiente")) -> Terminado | R22: =IFERROR(__xludf.DUMMYFUNCTION("SPARKLINE(O22,{""charttype"",""bar"";""max"",1;""color1"",IF(P22=""Terminado"",""#4CAF50"",IF(O22>=0.5,""#FFA500"",""#F44336""))})"),"")
A23: Druni Parc Central | B23: Ameba | C23: BASTIDOR DE TABICA CURVA 150X12 | D23: 13.7 | E23: 46084 | F23: =IFERROR(__xludf.DUMMYFUNCTION("""COMPUTED_VALUE"""),"Fabricación") -> Fabricación | G23: =IFERROR(__xludf.DUMMYFUNCTION("""COMPUTED_VALUE"""),"Embalaje/carga/descarga material") -> Embalaje/carga/descarga material | H23: =IFERROR(__xludf.DUMMYFUNCTION("(IFERROR(FILTER(BBDD!$J:$J,BBDD!$G:$G=C23,BBDD!$H:$H=F23,BBDD!$I:$I=G23),""NO TIENE PROCESO""))*D23"),2.0549999999999997) -> 2.055 | I23: =J23+K23 -> 0.1 | J23: =SUMIFS('👷horas'!$J:$J,'👷horas'!$D:$D,A23,'👷horas'!$E:$E,B23,'👷horas'!$F:$F,F23,'👷horas'!$G:$G,G23) -> 0.1 | K23: =SUMIFS('👷horas'!$K:$K,'👷horas'!$D:$D,A23,'👷horas'!$E:$E,B23,'👷horas'!$F:$F,F23,'👷horas'!$G:$G,G23) -> 0 | L23: =I23/D23 -> 0.0072992701 | M23: =IF(P23="TERMINADO",0,H23-(J23+K23)) -> 0 | N23: =1-(I23/H23) -> 0.9513382 | O23: =IF(NOT(ISNUMBER(H23)),0,IF(P23="Terminado",1,IF(J23=0,0,MIN(1,J23/H23)))) -> 1 | P23: Terminado | Q23: =IF(COUNTIFS(A:A,A23,P:P,"Terminado")=COUNTIF(A:A,A23),"Terminado",IF(COUNTIFS(A:A,A23,P:P,"En proceso")>0,"En proceso","Pendiente")) -> Terminado | R23: =IFERROR(__xludf.DUMMYFUNCTION("SPARKLINE(O23,{""charttype"",""bar"";""max"",1;""color1"",IF(P23=""Terminado"",""#4CAF50"",IF(O23>=0.5,""#FFA500"",""#F44336""))})"),"")
A24: Druni Parc Central | B24: Ameba | C24: BASTIDOR DE TABICA CURVA 150X12 | D24: 13.7 | E24: 46084 | F24: =IFERROR(__xludf.DUMMYFUNCTION("""COMPUTED_VALUE"""),"Pintura") -> Pintura | G24: =IFERROR(__xludf.DUMMYFUNCTION("""COMPUTED_VALUE"""),"Lijado y/o Masillado") -> Lijado y/o Masillado | H24: =IFERROR(__xludf.DUMMYFUNCTION("(IFERROR(FILTER(BBDD!$J:$J,BBDD!$G:$G=C24,BBDD!$H:$H=F24,BBDD!$I:$I=G24),""NO TIENE PROCESO""))*D24"),8.219999999999999) -> 8.22 | I24: =J24+K24 -> 11 | J24: =SUMIFS('👷horas'!$J:$J,'👷horas'!$D:$D,A24,'👷horas'!$E:$E,B24,'👷horas'!$F:$F,F24,'👷horas'!$G:$G,G24) -> 11 | K24: =SUMIFS('👷horas'!$K:$K,'👷horas'!$D:$D,A24,'👷horas'!$E:$E,B24,'👷horas'!$F:$F,F24,'👷horas'!$G:$G,G24) -> 0 | L24: =I24/D24 -> 0.80291971 | M24: =IF(P24="TERMINADO",0,H24-(J24+K24)) -> 0 | N24: =1-(I24/H24) -> -0.33819951 | O24: =IF(NOT(ISNUMBER(H24)),0,IF(P24="Terminado",1,IF(J24=0,0,MIN(1,J24/H24)))) -> 1 | P24: Terminado | Q24: =IF(COUNTIFS(A:A,A24,P:P,"Terminado")=COUNTIF(A:A,A24),"Terminado",IF(COUNTIFS(A:A,A24,P:P,"En proceso")>0,"En proceso","Pendiente")) -> Terminado | R24: =IFERROR(__xludf.DUMMYFUNCTION("SPARKLINE(O24,{""charttype"",""bar"";""max"",1;""color1"",IF(P24=""Terminado"",""#4CAF50"",IF(O24>=0.5,""#FFA500"",""#F44336""))})"),"")
A25: Druni Parc Central | B25: Ameba | C25: BASTIDOR DE TABICA CURVA 150X12 | D25: 13.7 | E25: 46084 | F25: =IFERROR(__xludf.DUMMYFUNCTION("""COMPUTED_VALUE"""),"Pintura") -> Pintura | G25: =IFERROR(__xludf.DUMMYFUNCTION("""COMPUTED_VALUE"""),"Imprimación/Pintura") -> Imprimación/Pintura | H25: =IFERROR(__xludf.DUMMYFUNCTION("(IFERROR(FILTER(BBDD!$J:$J,BBDD!$G:$G=C25,BBDD!$H:$H=F25,BBDD!$I:$I=G25),""NO TIENE PROCESO""))*D25"),5.48) -> 5.48 | I25: =J25+K25 -> 4 | J25: =SUMIFS('👷horas'!$J:$J,'👷horas'!$D:$D,A25,'👷horas'!$E:$E,B25,'👷horas'!$F:$F,F25,'👷horas'!$G:$G,G25) -> 4 | K25: =SUMIFS('👷horas'!$K:$K,'👷horas'!$D:$D,A25,'👷horas'!$E:$E,B25,'👷horas'!$F:$F,F25,'👷horas'!$G:$G,G25) -> 0 | L25: =I25/D25 -> 0.2919708 | M25: =IF(P25="TERMINADO",0,H25-(J25+K25)) -> 0 | N25: =1-(I25/H25) -> 0.27007299 | O25: =IF(NOT(ISNUMBER(H25)),0,IF(P25="Terminado",1,IF(J25=0,0,MIN(1,J25/H25)))) -> 1 | P25: Terminado | Q25: =IF(COUNTIFS(A:A,A25,P:P,"Terminado")=COUNTIF(A:A,A25),"Terminado",IF(COUNTIFS(A:A,A25,P:P,"En proceso")>0,"En proceso","Pendiente")) -> Terminado | R25: =IFERROR(__xludf.DUMMYFUNCTION("SPARKLINE(O25,{""charttype"",""bar"";""max"",1;""color1"",IF(P25=""Terminado"",""#4CAF50"",IF(O25>=0.5,""#FFA500"",""#F44336""))})"),"")
A26: Druni Parc Central | B26: Hair | C26: HAIR - ESPEJO | D26: 12.24 | E26: 46084 | F26: =IFERROR(__xludf.DUMMYFUNCTION("FILTER(BBDD!H:H,BBDD!G:G=C26)"),"Fabricación") -> Fabricación | G26: =IFERROR(__xludf.DUMMYFUNCTION("FILTER(BBDD!I:I,BBDD!G:G=C26)"),"Pegado de composite/chapa") -> Pegado de composite/chapa | H26: =IFERROR(__xludf.DUMMYFUNCTION("(IFERROR(FILTER(BBDD!$J:$J,BBDD!$G:$G=C26,BBDD!$H:$H=F26,BBDD!$I:$I=G26),""NO TIENE PROCESO""))*D26"),6.364800000000001) -> 6.3648 | I26: =J26+K26 -> 0 | J26: =SUMIFS('👷horas'!$J:$J,'👷horas'!$D:$D,A26,'👷horas'!$E:$E,B26,'👷horas'!$F:$F,F26,'👷horas'!$G:$G,G26) -> 0 | K26: =SUMIFS('👷horas'!$K:$K,'👷horas'!$D:$D,A26,'👷horas'!$E:$E,B26,'👷horas'!$F:$F,F26,'👷horas'!$G:$G,G26) -> 0 | L26: =I26/D26 -> 0 | M26: =IF(P26="TERMINADO",0,H26-(J26+K26)) -> 0 | N26: =1-(I26/H26) -> 1 | O26: =IF(NOT(ISNUMBER(H26)),0,IF(P26="Terminado",1,IF(J26=0,0,MIN(1,J26/H26)))) -> 1 | P26: Terminado | Q26: =IF(COUNTIFS(A:A,A26,P:P,"Terminado")=COUNTIF(A:A,A26),"Terminado",IF(COUNTIFS(A:A,A26,P:P,"En proceso")>0,"En proceso","Pendiente")) -> Terminado | R26: =IFERROR(__xludf.DUMMYFUNCTION("SPARKLINE(O26,{""charttype"",""bar"";""max"",1;""color1"",IF(P26=""Terminado"",""#4CAF50"",IF(O26>=0.5,""#FFA500"",""#F44336""))})"),"")
A27: Druni Parc Central | B27: Hair | C27: HAIR - ESPEJO | D27: 12.24 | E27: 46084 | F27: =IFERROR(__xludf.DUMMYFUNCTION("""COMPUTED_VALUE"""),"Fabricación") -> Fabricación | G27: =IFERROR(__xludf.DUMMYFUNCTION("""COMPUTED_VALUE"""),"Embalaje/carga/descarga material") -> Embalaje/carga/descarga material | H27: =IFERROR(__xludf.DUMMYFUNCTION("(IFERROR(FILTER(BBDD!$J:$J,BBDD!$G:$G=C27,BBDD!$H:$H=F27,BBDD!$I:$I=G27),""NO TIENE PROCESO""))*D27"),5.6304) -> 5.6304 | I27: =J27+K27 -> 1 | J27: =SUMIFS('👷horas'!$J:$J,'👷horas'!$D:$D,A27,'👷horas'!$E:$E,B27,'👷horas'!$F:$F,F27,'👷horas'!$G:$G,G27) -> 0 | K27: =SUMIFS('👷horas'!$K:$K,'👷horas'!$D:$D,A27,'👷horas'!$E:$E,B27,'👷horas'!$F:$F,F27,'👷horas'!$G:$G,G27) -> 1 | L27: =I27/D27 -> 0.081699346 | M27: =IF(P27="TERMINADO",0,H27-(J27+K27)) -> 0 | N27: =1-(I27/H27) -> 0.82239273 | O27: =IF(NOT(ISNUMBER(H27)),0,IF(P27="Terminado",1,IF(J27=0,0,MIN(1,J27/H27)))) -> 1 | P27: Terminado | Q27: =IF(COUNTIFS(A:A,A27,P:P,"Terminado")=COUNTIF(A:A,A27),"Terminado",IF(COUNTIFS(A:A,A27,P:P,"En proceso")>0,"En proceso","Pendiente")) -> Terminado | R27: =IFERROR(__xludf.DUMMYFUNCTION("SPARKLINE(O27,{""charttype"",""bar"";""max"",1;""color1"",IF(P27=""Terminado"",""#4CAF50"",IF(O27>=0.5,""#FFA500"",""#F44336""))})"),"")
A28: Druni Parc Central | B28: Hair | C28: HAIR - ESPEJO | D28: 12.24 | E28: 46084 | F28: =IFERROR(__xludf.DUMMYFUNCTION("""COMPUTED_VALUE"""),"CNC") -> CNC | G28: =IFERROR(__xludf.DUMMYFUNCTION("""COMPUTED_VALUE"""),"CNC") -> CNC | H28: =IFERROR(__xludf.DUMMYFUNCTION("(IFERROR(FILTER(BBDD!$J:$J,BBDD!$G:$G=C28,BBDD!$H:$H=F28,BBDD!$I:$I=G28),""NO TIENE PROCESO""))*D28"),4.5288) -> 4.5288 | I28: =J28+K28 -> 2.1 | J28: =SUMIFS('👷horas'!$J:$J,'👷horas'!$D:$D,A28,'👷horas'!$E:$E,B28,'👷horas'!$F:$F,F28,'👷horas'!$G:$G,G28) -> 2.1 | K28: =SUMIFS('👷horas'!$K:$K,'👷horas'!$D:$D,A28,'👷horas'!$E:$E,B28,'👷horas'!$F:$F,F28,'👷horas'!$G:$G,G28) -> 0 | L28: =I28/D28 -> 0.17156863 | M28: =IF(P28="TERMINADO",0,H28-(J28+K28)) -> 0 | N28: =1-(I28/H28) -> 0.53630101 | O28: =IF(NOT(ISNUMBER(H28)),0,IF(P28="Terminado",1,IF(J28=0,0,MIN(1,J28/H28)))) -> 1 | P28: Terminado | Q28: =IF(COUNTIFS(A:A,A28,P:P,"Terminado")=COUNTIF(A:A,A28),"Terminado",IF(COUNTIFS(A:A,A28,P:P,"En proceso")>0,"En proceso","Pendiente")) -> Terminado | R28: =IFERROR(__xludf.DUMMYFUNCTION("SPARKLINE(O28,{""charttype"",""bar"";""max"",1;""color1"",IF(P28=""Terminado"",""#4CAF50"",IF(O28>=0.5,""#FFA500"",""#F44336""))})"),"")
A29: Druni Parc Central | B29: Hair | C29: HAIR - ESPEJO | D29: 9 | E29: 46084 | F29: =IFERROR(__xludf.DUMMYFUNCTION("""COMPUTED_VALUE"""),"Fabricación") -> Fabricación | G29: =IFERROR(__xludf.DUMMYFUNCTION("""COMPUTED_VALUE"""),"Ensamblaje") -> Ensamblaje | H29: =IFERROR(__xludf.DUMMYFUNCTION("(IFERROR(FILTER(BBDD!$J:$J,BBDD!$G:$G=C29,BBDD!$H:$H=F29,BBDD!$I:$I=G29),""NO TIENE PROCESO""))*D29"),2.88) -> 2.88 | I29: =J29+K29 -> 10.3 | J29: =SUMIFS('👷horas'!$J:$J,'👷horas'!$D:$D,A29,'👷horas'!$E:$E,B29,'👷horas'!$F:$F,F29,'👷horas'!$G:$G,G29) -> 6.3 | K29: =SUMIFS('👷horas'!$K:$K,'👷horas'!$D:$D,A29,'👷horas'!$E:$E,B29,'👷horas'!$F:$F,F29,'👷horas'!$G:$G,G29) -> 4 | L29: =I29/D29 -> 1.1444444 | M29: =IF(P29="TERMINADO",0,H29-(J29+K29)) -> 0 | N29: =1-(I29/H29) -> -2.5763889 | O29: =IF(NOT(ISNUMBER(H29)),0,IF(P29="Terminado",1,IF(J29=0,0,MIN(1,J29/H29)))) -> 1 | P29: Terminado | Q29: =IF(COUNTIFS(A:A,A29,P:P,"Terminado")=COUNTIF(A:A,A29),"Terminado",IF(COUNTIFS(A:A,A29,P:P,"En proceso")>0,"En proceso","Pendiente")) -> Terminado | R29: =IFERROR(__xludf.DUMMYFUNCTION("SPARKLINE(O29,{""charttype"",""bar"";""max"",1;""color1"",IF(P29=""Terminado"",""#4CAF50"",IF(O29>=0.5,""#FFA500"",""#F44336""))})"),"")
A30: Druni Parc Central | B30: Hair | C30: HAIR - ESPEJO | D30: 9 | E30: 46084 | F30: =IFERROR(__xludf.DUMMYFUNCTION("""COMPUTED_VALUE"""),"Fabricación") -> Fabricación | G30: =IFERROR(__xludf.DUMMYFUNCTION("""COMPUTED_VALUE"""),"Colocación de perfiles") -> Colocación de perfiles | H30: =IFERROR(__xludf.DUMMYFUNCTION("(IFERROR(FILTER(BBDD!$J:$J,BBDD!$G:$G=C30,BBDD!$H:$H=F30,BBDD!$I:$I=G30),""NO TIENE PROCESO""))*D30"),1.3499999999999999) -> 1.35 | I30: =J30+K30 -> 7.3333333 | J30: =SUMIFS('👷horas'!$J:$J,'👷horas'!$D:$D,A30,'👷horas'!$E:$E,B30,'👷horas'!$F:$F,F30,'👷horas'!$G:$G,G30) -> 6.8333333 | K30: =SUMIFS('👷horas'!$K:$K,'👷horas'!$D:$D,A30,'👷horas'!$E:$E,B30,'👷horas'!$F:$F,F30,'👷horas'!$G:$G,G30) -> 0.5 | L30: =I30/D30 -> 0.81481481 | M30: =IF(P30="TERMINADO",0,H30-(J30+K30)) -> 0 | N30: =1-(I30/H30) -> -4.4320988 | O30: =IF(NOT(ISNUMBER(H30)),0,IF(P30="Terminado",1,IF(J30=0,0,MIN(1,J30/H30)))) -> 1 | P30: Terminado | Q30: =IF(COUNTIFS(A:A,A30,P:P,"Terminado")=COUNTIF(A:A,A30),"Terminado",IF(COUNTIFS(A:A,A30,P:P,"En proceso")>0,"En proceso","Pendiente")) -> Terminado | R30: =IFERROR(__xludf.DUMMYFUNCTION("SPARKLINE(O30,{""charttype"",""bar"";""max"",1;""color1"",IF(P30=""Terminado"",""#4CAF50"",IF(O30>=0.5,""#FFA500"",""#F44336""))})"),"")
A31: Druni Parc Central | B31: Hair | C31: HAIR - ESPEJO | D31: 9 | E31: 46084 | F31: =IFERROR(__xludf.DUMMYFUNCTION("""COMPUTED_VALUE"""),"Pintura") -> Pintura | G31: =IFERROR(__xludf.DUMMYFUNCTION("""COMPUTED_VALUE"""),"Imprimación/Pintura") -> Imprimación/Pintura | H31: =IFERROR(__xludf.DUMMYFUNCTION("(IFERROR(FILTER(BBDD!$J:$J,BBDD!$G:$G=C31,BBDD!$H:$H=F31,BBDD!$I:$I=G31),""NO TIENE PROCESO""))*D31"),0.9) -> 0.9 | I31: =J31+K31 -> 2 | J31: =SUMIFS('👷horas'!$J:$J,'👷horas'!$D:$D,A31,'👷horas'!$E:$E,B31,'👷horas'!$F:$F,F31,'👷horas'!$G:$G,G31) -> 2 | K31: =SUMIFS('👷horas'!$K:$K,'👷horas'!$D:$D,A31,'👷horas'!$E:$E,B31,'👷horas'!$F:$F,F31,'👷horas'!$G:$G,G31) -> 0 | L31: =I31/D31 -> 0.22222222 | M31: =IF(P31="TERMINADO",0,H31-(J31+K31)) -> 0 | N31: =1-(I31/H31) -> -1.2222222 | O31: =IF(NOT(ISNUMBER(H31)),0,IF(P31="Terminado",1,IF(J31=0,0,MIN(1,J31/H31)))) -> 1 | P31: Terminado | Q31: =IF(COUNTIFS(A:A,A31,P:P,"Terminado")=COUNTIF(A:A,A31),"Terminado",IF(COUNTIFS(A:A,A31,P:P,"En proceso")>0,"En proceso","Pendiente")) -> Terminado | R31: =IFERROR(__xludf.DUMMYFUNCTION("SPARKLINE(O31,{""charttype"",""bar"";""max"",1;""color1"",IF(P31=""Terminado"",""#4CAF50"",IF(O31>=0.5,""#FFA500"",""#F44336""))})"),"")
A32: Druni Cordoba fase 2 | B32: Cupula | C32: CUPULA DE COMPOSITE | D32: 1.3 | E32: 46087 | F32: =IFERROR(__xludf.DUMMYFUNCTION("FILTER(BBDD!H:H,BBDD!G:G=C32)"),"Fabricación") -> Fabricación | G32: =IFERROR(__xludf.DUMMYFUNCTION("FILTER(BBDD!I:I,BBDD!G:G=C32)"),"Ensamblaje") -> Ensamblaje | H32: =IFERROR(__xludf.DUMMYFUNCTION("(IFERROR(FILTER(BBDD!$J:$J,BBDD!$G:$G=C32,BBDD!$H:$H=F32,BBDD!$I:$I=G32),""NO TIENE PROCESO""))*D32"),0.325) -> 0.325 | I32: =J32+K32 -> 13.5 | J32: =SUMIFS('👷horas'!$J:$J,'👷horas'!$D:$D,A32,'👷horas'!$E:$E,B32,'👷horas'!$F:$F,F32,'👷horas'!$G:$G,G32) -> 13 | K32: =SUMIFS('👷horas'!$K:$K,'👷horas'!$D:$D,A32,'👷horas'!$E:$E,B32,'👷horas'!$F:$F,F32,'👷horas'!$G:$G,G32) -> 0.5 | L32: =I32/D32 -> 10.384615 | M32: =IF(P32="TERMINADO",0,H32-(J32+K32)) -> 0 | N32: =1-(I32/H32) -> -40.538462 | O32: =IF(NOT(ISNUMBER(H32)),0,IF(P32="Terminado",1,IF(J32=0,0,MIN(1,J32/H32)))) -> 1 | P32: Terminado | Q32: =IF(COUNTIFS(A:A,A32,P:P,"Terminado")=COUNTIF(A:A,A32),"Terminado",IF(COUNTIFS(A:A,A32,P:P,"En proceso")>0,"En proceso","Pendiente")) -> Terminado | R32: =IFERROR(__xludf.DUMMYFUNCTION("SPARKLINE(O32,{""charttype"",""bar"";""max"",1;""color1"",IF(P32=""Terminado"",""#4CAF50"",IF(O32>=0.5,""#FFA500"",""#F44336""))})"),"")
A33: Druni Cordoba fase 2 | B33: Cupula | C33: CUPULA DE COMPOSITE | D33: 1.3 | E33: 46087 | F33: =IFERROR(__xludf.DUMMYFUNCTION("""COMPUTED_VALUE"""),"Fabricación") -> Fabricación | G33: =IFERROR(__xludf.DUMMYFUNCTION("""COMPUTED_VALUE"""),"Embalaje/carga/descarga material") -> Embalaje/carga/descarga material | H33: =IFERROR(__xludf.DUMMYFUNCTION("(IFERROR(FILTER(BBDD!$J:$J,BBDD!$G:$G=C33,BBDD!$H:$H=F33,BBDD!$I:$I=G33),""NO TIENE PROCESO""))*D33"),0.065) -> 0.065 | I33: =J33+K33 -> 6 | J33: =SUMIFS('👷horas'!$J:$J,'👷horas'!$D:$D,A33,'👷horas'!$E:$E,B33,'👷horas'!$F:$F,F33,'👷horas'!$G:$G,G33) -> 6 | K33: =SUMIFS('👷horas'!$K:$K,'👷horas'!$D:$D,A33,'👷horas'!$E:$E,B33,'👷horas'!$F:$F,F33,'👷horas'!$G:$G,G33) -> 0 | L33: =I33/D33 -> 4.6153846 | M33: =IF(P33="TERMINADO",0,H33-(J33+K33)) -> 0 | N33: =1-(I33/H33) -> -91.307692 | O33: =IF(NOT(ISNUMBER(H33)),0,IF(P33="Terminado",1,IF(J33=0,0,MIN(1,J33/H33)))) -> 1 | P33: Terminado | Q33: =IF(COUNTIFS(A:A,A33,P:P,"Terminado")=COUNTIF(A:A,A33),"Terminado",IF(COUNTIFS(A:A,A33,P:P,"En proceso")>0,"En proceso","Pendiente")) -> Terminado | R33: =IFERROR(__xludf.DUMMYFUNCTION("SPARKLINE(O33,{""charttype"",""bar"";""max"",1;""color1"",IF(P33=""Terminado"",""#4CAF50"",IF(O33>=0.5,""#FFA500"",""#F44336""))})"),"")
A34: Druni Cordoba fase 2 | B34: Cupula | C34: CUPULA DE COMPOSITE | D34: 1.3 | E34: 46087 | F34: =IFERROR(__xludf.DUMMYFUNCTION("""COMPUTED_VALUE"""),"Fabricación") -> Fabricación | G34: =IFERROR(__xludf.DUMMYFUNCTION("""COMPUTED_VALUE"""),"Corte manual") -> Corte manual | H34: =IFERROR(__xludf.DUMMYFUNCTION("(IFERROR(FILTER(BBDD!$J:$J,BBDD!$G:$G=C34,BBDD!$H:$H=F34,BBDD!$I:$I=G34),""NO TIENE PROCESO""))*D34"),0.013000000000000001) -> 0.013 | I34: =J34+K34 -> 15.5 | J34: =SUMIFS('👷horas'!$J:$J,'👷horas'!$D:$D,A34,'👷horas'!$E:$E,B34,'👷horas'!$F:$F,F34,'👷horas'!$G:$G,G34) -> 15.5 | K34: =SUMIFS('👷horas'!$K:$K,'👷horas'!$D:$D,A34,'👷horas'!$E:$E,B34,'👷horas'!$F:$F,F34,'👷horas'!$G:$G,G34) -> 0 | L34: =I34/D34 -> 11.923077 | M34: =IF(P34="TERMINADO",0,H34-(J34+K34)) -> 0 | N34: =1-(I34/H34) -> -1191.3077 | O34: =IF(NOT(ISNUMBER(H34)),0,IF(P34="Terminado",1,IF(J34=0,0,MIN(1,J34/H34)))) -> 1 | P34: Terminado | Q34: =IF(COUNTIFS(A:A,A34,P:P,"Terminado")=COUNTIF(A:A,A34),"Terminado",IF(COUNTIFS(A:A,A34,P:P,"En proceso")>0,"En proceso","Pendiente")) -> Terminado | R34: =IFERROR(__xludf.DUMMYFUNCTION("SPARKLINE(O34,{""charttype"",""bar"";""max"",1;""color1"",IF(P34=""Terminado"",""#4CAF50"",IF(O34>=0.5,""#FFA500"",""#F44336""))})"),"")
A35: Druni CC Biosfera | B35: Selcos metacrilato | C35: BASTIDOR DE METACRILATO RECTO | D35: 36 | E35: 46097 | F35: =IFERROR(__xludf.DUMMYFUNCTION("FILTER(BBDD!H:H,BBDD!G:G=C35)"),"Fabricación") -> Fabricación | G35: =IFERROR(__xludf.DUMMYFUNCTION("FILTER(BBDD!I:I,BBDD!G:G=C35)"),"Ensamblaje") -> Ensamblaje | H35: =IFERROR(__xludf.DUMMYFUNCTION("(IFERROR(FILTER(BBDD!$J:$J,BBDD!$G:$G=C35,BBDD!$H:$H=F35,BBDD!$I:$I=G35),""NO TIENE PROCESO""))*D35"),32.4) -> 32.4 | I35: =J35+K35 -> 32.9 | J35: =SUMIFS('👷horas'!$J:$J,'👷horas'!$D:$D,A35,'👷horas'!$E:$E,B35,'👷horas'!$F:$F,F35,'👷horas'!$G:$G,G35) -> 28.9 | K35: =SUMIFS('👷horas'!$K:$K,'👷horas'!$D:$D,A35,'👷horas'!$E:$E,B35,'👷horas'!$F:$F,F35,'👷horas'!$G:$G,G35) -> 4 | L35: =I35/D35 -> 0.91388889 | M35: =IF(P35="TERMINADO",0,H35-(J35+K35)) -> 0 | N35: =1-(I35/H35) -> -0.015432099 | O35: =IF(NOT(ISNUMBER(H35)),0,IF(P35="Terminado",1,IF(J35=0,0,MIN(1,J35/H35)))) -> 1 | P35: Terminado | Q35: =IF(COUNTIFS(A:A,A35,P:P,"Terminado")=COUNTIF(A:A,A35),"Terminado",IF(COUNTIFS(A:A,A35,P:P,"En proceso")>0,"En proceso","Pendiente")) -> Terminado | R35: =IFERROR(__xludf.DUMMYFUNCTION("SPARKLINE(O35,{""charttype"",""bar"";""max"",1;""color1"",IF(P35=""Terminado"",""#4CAF50"",IF(O35>=0.5,""#FFA500"",""#F44336""))})"),"")
A36: Druni CC Biosfera | B36: Selcos metacrilato | C36: BASTIDOR DE METACRILATO RECTO | D36: 36 | E36: 46097 | F36: =IFERROR(__xludf.DUMMYFUNCTION("""COMPUTED_VALUE"""),"Fabricación") -> Fabricación | G36: =IFERROR(__xludf.DUMMYFUNCTION("""COMPUTED_VALUE"""),"Embalaje/carga/descarga material") -> Embalaje/carga/descarga material | H36: =IFERROR(__xludf.DUMMYFUNCTION("(IFERROR(FILTER(BBDD!$J:$J,BBDD!$G:$G=C36,BBDD!$H:$H=F36,BBDD!$I:$I=G36),""NO TIENE PROCESO""))*D36"),6.12) -> 6.12 | I36: =J36+K36 -> 2 | J36: =SUMIFS('👷horas'!$J:$J,'👷horas'!$D:$D,A36,'👷horas'!$E:$E,B36,'👷horas'!$F:$F,F36,'👷horas'!$G:$G,G36) -> 2 | K36: =SUMIFS('👷horas'!$K:$K,'👷horas'!$D:$D,A36,'👷horas'!$E:$E,B36,'👷horas'!$F:$F,F36,'👷horas'!$G:$G,G36) -> 0 | L36: =I36/D36 -> 0.055555556 | M36: =IF(P36="TERMINADO",0,H36-(J36+K36)) -> 0 | N36: =1-(I36/H36) -> 0.67320261 | O36: =IF(NOT(ISNUMBER(H36)),0,IF(P36="Terminado",1,IF(J36=0,0,MIN(1,J36/H36)))) -> 1 | P36: Terminado | Q36: =IF(COUNTIFS(A:A,A36,P:P,"Terminado")=COUNTIF(A:A,A36),"Terminado",IF(COUNTIFS(A:A,A36,P:P,"En proceso")>0,"En proceso","Pendiente")) -> Terminado | R36: =IFERROR(__xludf.DUMMYFUNCTION("SPARKLINE(O36,{""charttype"",""bar"";""max"",1;""color1"",IF(P36=""Terminado"",""#4CAF50"",IF(O36>=0.5,""#FFA500"",""#F44336""))})"),"")
A37: Druni CC Meridiano fase 2 | B37: Hair | C37: HAIR - ESPEJO | D37: 12.24 | E37: 46097 | F37: =IFERROR(__xludf.DUMMYFUNCTION("FILTER(BBDD!H:H,BBDD!G:G=C37)"),"Fabricación") -> Fabricación | G37: =IFERROR(__xludf.DUMMYFUNCTION("FILTER(BBDD!I:I,BBDD!G:G=C37)"),"Pegado de composite/chapa") -> Pegado de composite/chapa | H37: =IFERROR(__xludf.DUMMYFUNCTION("(IFERROR(FILTER(BBDD!$J:$J,BBDD!$G:$G=C37,BBDD!$H:$H=F37,BBDD!$I:$I=G37),""NO TIENE PROCESO""))*D37"),6.364800000000001) -> 6.3648 | I37: =J37+K37 -> 6 | J37: =SUMIFS('👷horas'!$J:$J,'👷horas'!$D:$D,A37,'👷horas'!$E:$E,B37,'👷horas'!$F:$F,F37,'👷horas'!$G:$G,G37) -> 6 | K37: =SUMIFS('👷horas'!$K:$K,'👷horas'!$D:$D,A37,'👷horas'!$E:$E,B37,'👷horas'!$F:$F,F37,'👷horas'!$G:$G,G37) -> 0 | L37: =I37/D37 -> 0.49019608 | M37: =IF(P37="TERMINADO",0,H37-(J37+K37)) -> 0 | N37: =1-(I37/H37) -> 0.057315234 | O37: =IF(NOT(ISNUMBER(H37)),0,IF(P37="Terminado",1,IF(J37=0,0,MIN(1,J37/H37)))) -> 1 | P37: Terminado | Q37: =IF(COUNTIFS(A:A,A37,P:P,"Terminado")=COUNTIF(A:A,A37),"Terminado",IF(COUNTIFS(A:A,A37,P:P,"En proceso")>0,"En proceso","Pendiente")) -> Terminado | R37: =IFERROR(__xludf.DUMMYFUNCTION("SPARKLINE(O37,{""charttype"",""bar"";""max"",1;""color1"",IF(P37=""Terminado"",""#4CAF50"",IF(O37>=0.5,""#FFA500"",""#F44336""))})"),"")
A38: Druni CC Meridiano fase 2 | B38: Hair | C38: HAIR - ESPEJO | D38: 12.24 | E38: 46097 | F38: =IFERROR(__xludf.DUMMYFUNCTION("""COMPUTED_VALUE"""),"Fabricación") -> Fabricación | G38: =IFERROR(__xludf.DUMMYFUNCTION("""COMPUTED_VALUE"""),"Embalaje/carga/descarga material") -> Embalaje/carga/descarga material | H38: =IFERROR(__xludf.DUMMYFUNCTION("(IFERROR(FILTER(BBDD!$J:$J,BBDD!$G:$G=C38,BBDD!$H:$H=F38,BBDD!$I:$I=G38),""NO TIENE PROCESO""))*D38"),5.6304) -> 5.6304 | I38: =J38+K38 -> 3.5 | J38: =SUMIFS('👷horas'!$J:$J,'👷horas'!$D:$D,A38,'👷horas'!$E:$E,B38,'👷horas'!$F:$F,F38,'👷horas'!$G:$G,G38) -> 3.5 | K38: =SUMIFS('👷horas'!$K:$K,'👷horas'!$D:$D,A38,'👷horas'!$E:$E,B38,'👷horas'!$F:$F,F38,'👷horas'!$G:$G,G38) -> 0 | L38: =I38/D38 -> 0.28594771 | M38: =IF(P38="TERMINADO",0,H38-(J38+K38)) -> 0 | N38: =1-(I38/H38) -> 0.37837454 | O38: =IF(NOT(ISNUMBER(H38)),0,IF(P38="Terminado",1,IF(J38=0,0,MIN(1,J38/H38)))) -> 1 | P38: Terminado | Q38: =IF(COUNTIFS(A:A,A38,P:P,"Terminado")=COUNTIF(A:A,A38),"Terminado",IF(COUNTIFS(A:A,A38,P:P,"En proceso")>0,"En proceso","Pendiente")) -> Terminado | R38: =IFERROR(__xludf.DUMMYFUNCTION("SPARKLINE(O38,{""charttype"",""bar"";""max"",1;""color1"",IF(P38=""Terminado"",""#4CAF50"",IF(O38>=0.5,""#FFA500"",""#F44336""))})"),"")
A39: Druni CC Meridiano fase 2 | B39: Hair | C39: HAIR - ESPEJO | D39: 12.24 | E39: 46097 | F39: =IFERROR(__xludf.DUMMYFUNCTION("""COMPUTED_VALUE"""),"CNC") -> CNC | G39: =IFERROR(__xludf.DUMMYFUNCTION("""COMPUTED_VALUE"""),"CNC") -> CNC | H39: =IFERROR(__xludf.DUMMYFUNCTION("(IFERROR(FILTER(BBDD!$J:$J,BBDD!$G:$G=C39,BBDD!$H:$H=F39,BBDD!$I:$I=G39),""NO TIENE PROCESO""))*D39"),4.5288) -> 4.5288 | I39: =J39+K39 -> 2.0416667 | J39: =SUMIFS('👷horas'!$J:$J,'👷horas'!$D:$D,A39,'👷horas'!$E:$E,B39,'👷horas'!$F:$F,F39,'👷horas'!$G:$G,G39) -> 2.0416667 | K39: =SUMIFS('👷horas'!$K:$K,'👷horas'!$D:$D,A39,'👷horas'!$E:$E,B39,'👷horas'!$F:$F,F39,'👷horas'!$G:$G,G39) -> 0 | L39: =I39/D39 -> 0.16680283 | M39: =IF(P39="TERMINADO",0,H39-(J39+K39)) -> 0 | N39: =1-(I39/H39) -> 0.54918153 | O39: =IF(NOT(ISNUMBER(H39)),0,IF(P39="Terminado",1,IF(J39=0,0,MIN(1,J39/H39)))) -> 1 | P39: Terminado | Q39: =IF(COUNTIFS(A:A,A39,P:P,"Terminado")=COUNTIF(A:A,A39),"Terminado",IF(COUNTIFS(A:A,A39,P:P,"En proceso")>0,"En proceso","Pendiente")) -> Terminado | R39: =IFERROR(__xludf.DUMMYFUNCTION("SPARKLINE(O39,{""charttype"",""bar"";""max"",1;""color1"",IF(P39=""Terminado"",""#4CAF50"",IF(O39>=0.5,""#FFA500"",""#F44336""))})"),"")
A40: Druni CC Meridiano fase 2 | B40: Hair | C40: HAIR - ESPEJO | D40: 9 | E40: 46097 | F40: =IFERROR(__xludf.DUMMYFUNCTION("""COMPUTED_VALUE"""),"Fabricación") -> Fabricación | G40: =IFERROR(__xludf.DUMMYFUNCTION("""COMPUTED_VALUE"""),"Ensamblaje") -> Ensamblaje | H40: =IFERROR(__xludf.DUMMYFUNCTION("(IFERROR(FILTER(BBDD!$J:$J,BBDD!$G:$G=C40,BBDD!$H:$H=F40,BBDD!$I:$I=G40),""NO TIENE PROCESO""))*D40"),2.88) -> 2.88 | I40: =J40+K40 -> 3.7 | J40: =SUMIFS('👷horas'!$J:$J,'👷horas'!$D:$D,A40,'👷horas'!$E:$E,B40,'👷horas'!$F:$F,F40,'👷horas'!$G:$G,G40) -> 3.7 | K40: =SUMIFS('👷horas'!$K:$K,'👷horas'!$D:$D,A40,'👷horas'!$E:$E,B40,'👷horas'!$F:$F,F40,'👷horas'!$G:$G,G40) -> 0 | L40: =I40/D40 -> 0.41111111 | M40: =IF(P40="TERMINADO",0,H40-(J40+K40)) -> 0 | N40: =1-(I40/H40) -> -0.28472222 | O40: =IF(NOT(ISNUMBER(H40)),0,IF(P40="Terminado",1,IF(J40=0,0,MIN(1,J40/H40)))) -> 1 | P40: Terminado | Q40: =IF(COUNTIFS(A:A,A40,P:P,"Terminado")=COUNTIF(A:A,A40),"Terminado",IF(COUNTIFS(A:A,A40,P:P,"En proceso")>0,"En proceso","Pendiente")) -> Terminado | R40: =IFERROR(__xludf.DUMMYFUNCTION("SPARKLINE(O40,{""charttype"",""bar"";""max"",1;""color1"",IF(P40=""Terminado"",""#4CAF50"",IF(O40>=0.5,""#FFA500"",""#F44336""))})"),"")
A41: Druni CC Meridiano fase 2 | B41: Hair | C41: HAIR - ESPEJO | D41: 9 | E41: 46097 | F41: =IFERROR(__xludf.DUMMYFUNCTION("""COMPUTED_VALUE"""),"Fabricación") -> Fabricación | G41: =IFERROR(__xludf.DUMMYFUNCTION("""COMPUTED_VALUE"""),"Colocación de perfiles") -> Colocación de perfiles | H41: =IFERROR(__xludf.DUMMYFUNCTION("(IFERROR(FILTER(BBDD!$J:$J,BBDD!$G:$G=C41,BBDD!$H:$H=F41,BBDD!$I:$I=G41),""NO TIENE PROCESO""))*D41"),1.3499999999999999) -> 1.35 | I41: =J41+K41 -> 4 | J41: =SUMIFS('👷horas'!$J:$J,'👷horas'!$D:$D,A41,'👷horas'!$E:$E,B41,'👷horas'!$F:$F,F41,'👷horas'!$G:$G,G41) -> 2 | K41: =SUMIFS('👷horas'!$K:$K,'👷horas'!$D:$D,A41,'👷horas'!$E:$E,B41,'👷horas'!$F:$F,F41,'👷horas'!$G:$G,G41) -> 2 | L41: =I41/D41 -> 0.44444444 | M41: =IF(P41="TERMINADO",0,H41-(J41+K41)) -> 0 | N41: =1-(I41/H41) -> -1.962963 | O41: =IF(NOT(ISNUMBER(H41)),0,IF(P41="Terminado",1,IF(J41=0,0,MIN(1,J41/H41)))) -> 1 | P41: Terminado | Q41: =IF(COUNTIFS(A:A,A41,P:P,"Terminado")=COUNTIF(A:A,A41),"Terminado",IF(COUNTIFS(A:A,A41,P:P,"En proceso")>0,"En proceso","Pendiente")) -> Terminado | R41: =IFERROR(__xludf.DUMMYFUNCTION("SPARKLINE(O41,{""charttype"",""bar"";""max"",1;""color1"",IF(P41=""Terminado"",""#4CAF50"",IF(O41>=0.5,""#FFA500"",""#F44336""))})"),"")
A42: Druni CC Meridiano fase 2 | B42: Hair | C42: HAIR - ESPEJO | D42: 9 | E42: 46097 | F42: =IFERROR(__xludf.DUMMYFUNCTION("""COMPUTED_VALUE"""),"Pintura") -> Pintura | G42: =IFERROR(__xludf.DUMMYFUNCTION("""COMPUTED_VALUE"""),"Imprimación/Pintura") -> Imprimación/Pintura | H42: =IFERROR(__xludf.DUMMYFUNCTION("(IFERROR(FILTER(BBDD!$J:$J,BBDD!$G:$G=C42,BBDD!$H:$H=F42,BBDD!$I:$I=G42),""NO TIENE PROCESO""))*D42"),0.9) -> 0.9 | I42: =J42+K42 -> 0.9 | J42: =SUMIFS('👷horas'!$J:$J,'👷horas'!$D:$D,A42,'👷horas'!$E:$E,B42,'👷horas'!$F:$F,F42,'👷horas'!$G:$G,G42) -> 0.9 | K42: =SUMIFS('👷horas'!$K:$K,'👷horas'!$D:$D,A42,'👷horas'!$E:$E,B42,'👷horas'!$F:$F,F42,'👷horas'!$G:$G,G42) -> 0 | L42: =I42/D42 -> 0.1 | M42: =IF(P42="TERMINADO",0,H42-(J42+K42)) -> 0 | N42: =1-(I42/H42) -> 0 | O42: =IF(NOT(ISNUMBER(H42)),0,IF(P42="Terminado",1,IF(J42=0,0,MIN(1,J42/H42)))) -> 1 | P42: Terminado | Q42: =IF(COUNTIFS(A:A,A42,P:P,"Terminado")=COUNTIF(A:A,A42),"Terminado",IF(COUNTIFS(A:A,A42,P:P,"En proceso")>0,"En proceso","Pendiente")) -> Terminado | R42: =IFERROR(__xludf.DUMMYFUNCTION("SPARKLINE(O42,{""charttype"",""bar"";""max"",1;""color1"",IF(P42=""Terminado"",""#4CAF50"",IF(O42>=0.5,""#FFA500"",""#F44336""))})"),"")
A43: Druni CC Meridiano fase 2 | B43: Selcos metacrilato | C43: BASTIDOR DE METACRILATO RECTO | D43: 7.2 | E43: 46097 | F43: =IFERROR(__xludf.DUMMYFUNCTION("FILTER(BBDD!H:H,BBDD!G:G=C43)"),"Fabricación") -> Fabricación | G43: =IFERROR(__xludf.DUMMYFUNCTION("FILTER(BBDD!I:I,BBDD!G:G=C43)"),"Ensamblaje") -> Ensamblaje | H43: =IFERROR(__xludf.DUMMYFUNCTION("(IFERROR(FILTER(BBDD!$J:$J,BBDD!$G:$G=C43,BBDD!$H:$H=F43,BBDD!$I:$I=G43),""NO TIENE PROCESO""))*D43"),6.4799999999999995) -> 6.48 | I43: =J43+K43 -> 6.58 | J43: =SUMIFS('👷horas'!$J:$J,'👷horas'!$D:$D,A43,'👷horas'!$E:$E,B43,'👷horas'!$F:$F,F43,'👷horas'!$G:$G,G43) -> 6.58 | K43: =SUMIFS('👷horas'!$K:$K,'👷horas'!$D:$D,A43,'👷horas'!$E:$E,B43,'👷horas'!$F:$F,F43,'👷horas'!$G:$G,G43) -> 0 | L43: =I43/D43 -> 0.91388889 | M43: =IF(P43="TERMINADO",0,H43-(J43+K43)) -> 0 | N43: =1-(I43/H43) -> -0.015432099 | O43: =IF(NOT(ISNUMBER(H43)),0,IF(P43="Terminado",1,IF(J43=0,0,MIN(1,J43/H43)))) -> 1 | P43: Terminado | Q43: =IF(COUNTIFS(A:A,A43,P:P,"Terminado")=COUNTIF(A:A,A43),"Terminado",IF(COUNTIFS(A:A,A43,P:P,"En proceso")>0,"En proceso","Pendiente")) -> Terminado | R43: =IFERROR(__xludf.DUMMYFUNCTION("SPARKLINE(O43,{""charttype"",""bar"";""max"",1;""color1"",IF(P43=""Terminado"",""#4CAF50"",IF(O43>=0.5,""#FFA500"",""#F44336""))})"),"")
A44: Druni CC Meridiano fase 2 | B44: Selcos metacrilato | C44: BASTIDOR DE METACRILATO RECTO | D44: 7.2 | E44: 46097 | F44: =IFERROR(__xludf.DUMMYFUNCTION("""COMPUTED_VALUE"""),"Fabricación") -> Fabricación | G44: =IFERROR(__xludf.DUMMYFUNCTION("""COMPUTED_VALUE"""),"Embalaje/carga/descarga material") -> Embalaje/carga/descarga material | H44: =IFERROR(__xludf.DUMMYFUNCTION("(IFERROR(FILTER(BBDD!$J:$J,BBDD!$G:$G=C44,BBDD!$H:$H=F44,BBDD!$I:$I=G44),""NO TIENE PROCESO""))*D44"),1.2240000000000002) -> 1.224 | I44: =J44+K44 -> 0.75 | J44: =SUMIFS('👷horas'!$J:$J,'👷horas'!$D:$D,A44,'👷horas'!$E:$E,B44,'👷horas'!$F:$F,F44,'👷horas'!$G:$G,G44) -> 0.75 | K44: =SUMIFS('👷horas'!$K:$K,'👷horas'!$D:$D,A44,'👷horas'!$E:$E,B44,'👷horas'!$F:$F,F44,'👷horas'!$G:$G,G44) -> 0 | L44: =I44/D44 -> 0.10416667 | M44: =IF(P44="TERMINADO",0,H44-(J44+K44)) -> 0 | N44: =1-(I44/H44) -> 0.3872549 | O44: =IF(NOT(ISNUMBER(H44)),0,IF(P44="Terminado",1,IF(J44=0,0,MIN(1,J44/H44)))) -> 1 | P44: Terminado | Q44: =IF(COUNTIFS(A:A,A44,P:P,"Terminado")=COUNTIF(A:A,A44),"Terminado",IF(COUNTIFS(A:A,A44,P:P,"En proceso")>0,"En proceso","Pendiente")) -> Terminado | R44: =IFERROR(__xludf.DUMMYFUNCTION("SPARKLINE(O44,{""charttype"",""bar"";""max"",1;""color1"",IF(P44=""Terminado"",""#4CAF50"",IF(O44>=0.5,""#FFA500"",""#F44336""))})"),"")
A45: Druni CC Meridiano fase 2 | B45: Revestimiento | C45: PREPARACION DE CHAPA | D45: 58 | E45: 46097 | F45: =IFERROR(__xludf.DUMMYFUNCTION("FILTER(BBDD!H:H,BBDD!G:G=C45)"),"Fabricación") -> Fabricación | G45: =IFERROR(__xludf.DUMMYFUNCTION("FILTER(BBDD!I:I,BBDD!G:G=C45)"),"Embalaje/carga/descarga material") -> Embalaje/carga/descarga material | H45: =IFERROR(__xludf.DUMMYFUNCTION("(IFERROR(FILTER(BBDD!$J:$J,BBDD!$G:$G=C45,BBDD!$H:$H=F45,BBDD!$I:$I=G45),""NO TIENE PROCESO""))*D45"),1.4500000000000002) -> 1.45 | I45: =J45+K45 -> 1 | J45: =SUMIFS('👷horas'!$J:$J,'👷horas'!$D:$D,A45,'👷horas'!$E:$E,B45,'👷horas'!$F:$F,F45,'👷horas'!$G:$G,G45) -> 1 | K45: =SUMIFS('👷horas'!$K:$K,'👷horas'!$D:$D,A45,'👷horas'!$E:$E,B45,'👷horas'!$F:$F,F45,'👷horas'!$G:$G,G45) -> 0 | L45: =I45/D45 -> 0.017241379 | M45: =IF(P45="TERMINADO",0,H45-(J45+K45)) -> 0 | N45: =1-(I45/H45) -> 0.31034483 | O45: =IF(NOT(ISNUMBER(H45)),0,IF(P45="Terminado",1,IF(J45=0,0,MIN(1,J45/H45)))) -> 1 | P45: Terminado | Q45: =IF(COUNTIFS(A:A,A45,P:P,"Terminado")=COUNTIF(A:A,A45),"Terminado",IF(COUNTIFS(A:A,A45,P:P,"En proceso")>0,"En proceso","Pendiente")) -> Terminado | R45: =IFERROR(__xludf.DUMMYFUNCTION("SPARKLINE(O45,{""charttype"",""bar"";""max"",1;""color1"",IF(P45=""Terminado"",""#4CAF50"",IF(O45>=0.5,""#FFA500"",""#F44336""))})"),"")
A46: Urbysol | B46: Revestimiento | C46: PREPARACION DE CHAPA | D46: 17 | E46: 46098 | F46: =IFERROR(__xludf.DUMMYFUNCTION("FILTER(BBDD!H:H,BBDD!G:G=C46)"),"Fabricación") -> Fabricación | G46: =IFERROR(__xludf.DUMMYFUNCTION("FILTER(BBDD!I:I,BBDD!G:G=C46)"),"Embalaje/carga/descarga material") -> Embalaje/carga/descarga material | H46: =IFERROR(__xludf.DUMMYFUNCTION("(IFERROR(FILTER(BBDD!$J:$J,BBDD!$G:$G=C46,BBDD!$H:$H=F46,BBDD!$I:$I=G46),""NO TIENE PROCESO""))*D46"),0.42500000000000004) -> 0.425 | I46: =J46+K46 -> 1.6666667 | J46: =SUMIFS('👷horas'!$J:$J,'👷horas'!$D:$D,A46,'👷horas'!$E:$E,B46,'👷horas'!$F:$F,F46,'👷horas'!$G:$G,G46) -> 1.6666667 | K46: =SUMIFS('👷horas'!$K:$K,'👷horas'!$D:$D,A46,'👷horas'!$E:$E,B46,'👷horas'!$F:$F,F46,'👷horas'!$G:$G,G46) -> 0 | L46: =I46/D46 -> 0.098039216 | M46: =IF(P46="TERMINADO",0,H46-(J46+K46)) -> 0 | N46: =1-(I46/H46) -> -2.9215686 | O46: =IF(NOT(ISNUMBER(H46)),0,IF(P46="Terminado",1,IF(J46=0,0,MIN(1,J46/H46)))) -> 1 | P46: Terminado | Q46: =IF(COUNTIFS(A:A,A46,P:P,"Terminado")=COUNTIF(A:A,A46),"Terminado",IF(COUNTIFS(A:A,A46,P:P,"En proceso")>0,"En proceso","Pendiente")) -> Terminado | R46: =IFERROR(__xludf.DUMMYFUNCTION("SPARKLINE(O46,{""charttype"",""bar"";""max"",1;""color1"",IF(P46=""Terminado"",""#4CAF50"",IF(O46>=0.5,""#FFA500"",""#F44336""))})"),"")
A47: Casadecor | B47: Bastidor especial | C47: BASTIDOR DE TABICA 150X12 | D47: 0.3 | E47: 46099 | F47: =IFERROR(__xludf.DUMMYFUNCTION("FILTER(BBDD!H:H,BBDD!G:G=C47)"),"CNC") -> CNC | G47: =IFERROR(__xludf.DUMMYFUNCTION("FILTER(BBDD!I:I,BBDD!G:G=C47)"),"CNC") -> CNC | H47: =IFERROR(__xludf.DUMMYFUNCTION("(IFERROR(FILTER(BBDD!$J:$J,BBDD!$G:$G=C47,BBDD!$H:$H=F47,BBDD!$I:$I=G47),""NO TIENE PROCESO""))*D47"),0.06) -> 0.06 | I47: =J47+K47 -> 0 | J47: =SUMIFS('👷horas'!$J:$J,'👷horas'!$D:$D,A47,'👷horas'!$E:$E,B47,'👷horas'!$F:$F,F47,'👷horas'!$G:$G,G47) -> 0 | K47: =SUMIFS('👷horas'!$K:$K,'👷horas'!$D:$D,A47,'👷horas'!$E:$E,B47,'👷horas'!$F:$F,F47,'👷horas'!$G:$G,G47) -> 0 | L47: =I47/D47 -> 0 | M47: =IF(P47="TERMINADO",0,H47-(J47+K47)) -> 0 | N47: =1-(I47/H47) -> 1 | O47: =IF(NOT(ISNUMBER(H47)),0,IF(P47="Terminado",1,IF(J47=0,0,MIN(1,J47/H47)))) -> 1 | P47: Terminado | Q47: =IF(COUNTIFS(A:A,A47,P:P,"Terminado")=COUNTIF(A:A,A47),"Terminado",IF(COUNTIFS(A:A,A47,P:P,"En proceso")>0,"En proceso","Pendiente")) -> Terminado | R47: =IFERROR(__xludf.DUMMYFUNCTION("SPARKLINE(O47,{""charttype"",""bar"";""max"",1;""color1"",IF(P47=""Terminado"",""#4CAF50"",IF(O47>=0.5,""#FFA500"",""#F44336""))})"),"")
A48: Casadecor | B48: Bastidor especial | C48: BASTIDOR DE TABICA 150X12 | D48: 0.3 | E48: 46099 | F48: =IFERROR(__xludf.DUMMYFUNCTION("""COMPUTED_VALUE"""),"Fabricación") -> Fabricación | G48: =IFERROR(__xludf.DUMMYFUNCTION("""COMPUTED_VALUE"""),"Ensamblaje") -> Ensamblaje | H48: =IFERROR(__xludf.DUMMYFUNCTION("(IFERROR(FILTER(BBDD!$J:$J,BBDD!$G:$G=C48,BBDD!$H:$H=F48,BBDD!$I:$I=G48),""NO TIENE PROCESO""))*D48"),0.186) -> 0.186 | I48: =J48+K48 -> 0.25 | J48: =SUMIFS('👷horas'!$J:$J,'👷horas'!$D:$D,A48,'👷horas'!$E:$E,B48,'👷horas'!$F:$F,F48,'👷horas'!$G:$G,G48) -> 0.25 | K48: =SUMIFS('👷horas'!$K:$K,'👷horas'!$D:$D,A48,'👷horas'!$E:$E,B48,'👷horas'!$F:$F,F48,'👷horas'!$G:$G,G48) -> 0 | L48: =I48/D48 -> 0.83333333 | M48: =IF(P48="TERMINADO",0,H48-(J48+K48)) -> 0 | N48: =1-(I48/H48) -> -0.34408602 | O48: =IF(NOT(ISNUMBER(H48)),0,IF(P48="Terminado",1,IF(J48=0,0,MIN(1,J48/H48)))) -> 1 | P48: Terminado | Q48: =IF(COUNTIFS(A:A,A48,P:P,"Terminado")=COUNTIF(A:A,A48),"Terminado",IF(COUNTIFS(A:A,A48,P:P,"En proceso")>0,"En proceso","Pendiente")) -> Terminado | R48: =IFERROR(__xludf.DUMMYFUNCTION("SPARKLINE(O48,{""charttype"",""bar"";""max"",1;""color1"",IF(P48=""Terminado"",""#4CAF50"",IF(O48>=0.5,""#FFA500"",""#F44336""))})"),"")
A49: Casadecor | B49: Bastidor especial | C49: BASTIDOR DE TABICA 150X12 | D49: 0.3 | E49: 46099 | F49: =IFERROR(__xludf.DUMMYFUNCTION("""COMPUTED_VALUE"""),"Fabricación") -> Fabricación | G49: =IFERROR(__xludf.DUMMYFUNCTION("""COMPUTED_VALUE"""),"Colocación de perfiles") -> Colocación de perfiles | H49: =IFERROR(__xludf.DUMMYFUNCTION("(IFERROR(FILTER(BBDD!$J:$J,BBDD!$G:$G=C49,BBDD!$H:$H=F49,BBDD!$I:$I=G49),""NO TIENE PROCESO""))*D49"),0.06) -> 0.06 | I49: =J49+K49 -> 0.083333333 | J49: =SUMIFS('👷horas'!$J:$J,'👷horas'!$D:$D,A49,'👷horas'!$E:$E,B49,'👷horas'!$F:$F,F49,'👷horas'!$G:$G,G49) -> 0 | K49: =SUMIFS('👷horas'!$K:$K,'👷horas'!$D:$D,A49,'👷horas'!$E:$E,B49,'👷horas'!$F:$F,F49,'👷horas'!$G:$G,G49) -> 0.083333333 | L49: =I49/D49 -> 0.27777778 | M49: =IF(P49="TERMINADO",0,H49-(J49+K49)) -> 0 | N49: =1-(I49/H49) -> -0.38888889 | O49: =IF(NOT(ISNUMBER(H49)),0,IF(P49="Terminado",1,IF(J49=0,0,MIN(1,J49/H49)))) -> 1 | P49: Terminado | Q49: =IF(COUNTIFS(A:A,A49,P:P,"Terminado")=COUNTIF(A:A,A49),"Terminado",IF(COUNTIFS(A:A,A49,P:P,"En proceso")>0,"En proceso","Pendiente")) -> Terminado | R49: =IFERROR(__xludf.DUMMYFUNCTION("SPARKLINE(O49,{""charttype"",""bar"";""max"",1;""color1"",IF(P49=""Terminado"",""#4CAF50"",IF(O49>=0.5,""#FFA500"",""#F44336""))})"),"")
A50: Casadecor | B50: Bastidor especial | C50: BASTIDOR DE TABICA 150X12 | D50: 0.3 | E50: 46099 | F50: =IFERROR(__xludf.DUMMYFUNCTION("""COMPUTED_VALUE"""),"Fabricación") -> Fabricación | G50: =IFERROR(__xludf.DUMMYFUNCTION("""COMPUTED_VALUE"""),"Embalaje/carga/descarga material") -> Embalaje/carga/descarga material | H50: =IFERROR(__xludf.DUMMYFUNCTION("(IFERROR(FILTER(BBDD!$J:$J,BBDD!$G:$G=C50,BBDD!$H:$H=F50,BBDD!$I:$I=G50),""NO TIENE PROCESO""))*D50"),0.045) -> 0.045 | I50: =J50+K50 -> 0 | J50: =SUMIFS('👷horas'!$J:$J,'👷horas'!$D:$D,A50,'👷horas'!$E:$E,B50,'👷horas'!$F:$F,F50,'👷horas'!$G:$G,G50) -> 0 | K50: =SUMIFS('👷horas'!$K:$K,'👷horas'!$D:$D,A50,'👷horas'!$E:$E,B50,'👷horas'!$F:$F,F50,'👷horas'!$G:$G,G50) -> 0 | L50: =I50/D50 -> 0 | M50: =IF(P50="TERMINADO",0,H50-(J50+K50)) -> 0 | N50: =1-(I50/H50) -> 1 | O50: =IF(NOT(ISNUMBER(H50)),0,IF(P50="Terminado",1,IF(J50=0,0,MIN(1,J50/H50)))) -> 1 | P50: Terminado | Q50: =IF(COUNTIFS(A:A,A50,P:P,"Terminado")=COUNTIF(A:A,A50),"Terminado",IF(COUNTIFS(A:A,A50,P:P,"En proceso")>0,"En proceso","Pendiente")) -> Terminado | R50: =IFERROR(__xludf.DUMMYFUNCTION("SPARKLINE(O50,{""charttype"",""bar"";""max"",1;""color1"",IF(P50=""Terminado"",""#4CAF50"",IF(O50>=0.5,""#FFA500"",""#F44336""))})"),"")
A51: Casadecor | B51: Bastidor especial | C51: BASTIDOR DE TABICA 150X12 | D51: 0.3 | E51: 46099 | F51: =IFERROR(__xludf.DUMMYFUNCTION("""COMPUTED_VALUE"""),"Pintura") -> Pintura | G51: =IFERROR(__xludf.DUMMYFUNCTION("""COMPUTED_VALUE"""),"Lijado y/o Masillado") -> Lijado y/o Masillado | H51: =IFERROR(__xludf.DUMMYFUNCTION("(IFERROR(FILTER(BBDD!$J:$J,BBDD!$G:$G=C51,BBDD!$H:$H=F51,BBDD!$I:$I=G51),""NO TIENE PROCESO""))*D51"),0.15) -> 0.15 | I51: =J51+K51 -> 0 | J51: =SUMIFS('👷horas'!$J:$J,'👷horas'!$D:$D,A51,'👷horas'!$E:$E,B51,'👷horas'!$F:$F,F51,'👷horas'!$G:$G,G51) -> 0 | K51: =SUMIFS('👷horas'!$K:$K,'👷horas'!$D:$D,A51,'👷horas'!$E:$E,B51,'👷horas'!$F:$F,F51,'👷horas'!$G:$G,G51) -> 0 | L51: =I51/D51 -> 0 | M51: =IF(P51="TERMINADO",0,H51-(J51+K51)) -> 0 | N51: =1-(I51/H51) -> 1 | O51: =IF(NOT(ISNUMBER(H51)),0,IF(P51="Terminado",1,IF(J51=0,0,MIN(1,J51/H51)))) -> 1 | P51: Terminado | Q51: =IF(COUNTIFS(A:A,A51,P:P,"Terminado")=COUNTIF(A:A,A51),"Terminado",IF(COUNTIFS(A:A,A51,P:P,"En proceso")>0,"En proceso","Pendiente")) -> Terminado | R51: =IFERROR(__xludf.DUMMYFUNCTION("SPARKLINE(O51,{""charttype"",""bar"";""max"",1;""color1"",IF(P51=""Terminado"",""#4CAF50"",IF(O51>=0.5,""#FFA500"",""#F44336""))})"),"")
A52: Casadecor | B52: Bastidor especial | C52: BASTIDOR DE TABICA 150X12 | D52: 0.3 | E52: 46099 | F52: =IFERROR(__xludf.DUMMYFUNCTION("""COMPUTED_VALUE"""),"Pintura") -> Pintura | G52: =IFERROR(__xludf.DUMMYFUNCTION("""COMPUTED_VALUE"""),"Imprimación/Pintura") -> Imprimación/Pintura | H52: =IFERROR(__xludf.DUMMYFUNCTION("(IFERROR(FILTER(BBDD!$J:$J,BBDD!$G:$G=C52,BBDD!$H:$H=F52,BBDD!$I:$I=G52),""NO TIENE PROCESO""))*D52"),0.12) -> 0.12 | I52: =J52+K52 -> 0.42 | J52: =SUMIFS('👷horas'!$J:$J,'👷horas'!$D:$D,A52,'👷horas'!$E:$E,B52,'👷horas'!$F:$F,F52,'👷horas'!$G:$G,G52) -> 0 | K52: =SUMIFS('👷horas'!$K:$K,'👷horas'!$D:$D,A52,'👷horas'!$E:$E,B52,'👷horas'!$F:$F,F52,'👷horas'!$G:$G,G52) -> 0.42 | L52: =I52/D52 -> 1.4 | M52: =IF(P52="TERMINADO",0,H52-(J52+K52)) -> 0 | N52: =1-(I52/H52) -> -2.5 | O52: =IF(NOT(ISNUMBER(H52)),0,IF(P52="Terminado",1,IF(J52=0,0,MIN(1,J52/H52)))) -> 1 | P52: Terminado | Q52: =IF(COUNTIFS(A:A,A52,P:P,"Terminado")=COUNTIF(A:A,A52),"Terminado",IF(COUNTIFS(A:A,A52,P:P,"En proceso")>0,"En proceso","Pendiente")) -> Terminado | R52: =IFERROR(__xludf.DUMMYFUNCTION("SPARKLINE(O52,{""charttype"",""bar"";""max"",1;""color1"",IF(P52=""Terminado"",""#4CAF50"",IF(O52>=0.5,""#FFA500"",""#F44336""))})"),"")
A53: Druni Maisonnave Alicante | B53: Revestimiento | C53: PREPARACION DE CHAPA | D53: 3 | E53: 46104 | F53: =IFERROR(__xludf.DUMMYFUNCTION("FILTER(BBDD!H:H,BBDD!G:G=C53)"),"Fabricación") -> Fabricación | G53: =IFERROR(__xludf.DUMMYFUNCTION("FILTER(BBDD!I:I,BBDD!G:G=C53)"),"Embalaje/carga/descarga material") -> Embalaje/carga/descarga material | H53: =IFERROR(__xludf.DUMMYFUNCTION("(IFERROR(FILTER(BBDD!$J:$J,BBDD!$G:$G=C53,BBDD!$H:$H=F53,BBDD!$I:$I=G53),""NO TIENE PROCESO""))*D53"),0.07500000000000001) -> 0.075 | I53: =J53+K53 -> 2 | J53: =SUMIFS('👷horas'!$J:$J,'👷horas'!$D:$D,A53,'👷horas'!$E:$E,B53,'👷horas'!$F:$F,F53,'👷horas'!$G:$G,G53) -> 2 | K53: =SUMIFS('👷horas'!$K:$K,'👷horas'!$D:$D,A53,'👷horas'!$E:$E,B53,'👷horas'!$F:$F,F53,'👷horas'!$G:$G,G53) -> 0 | L53: =I53/D53 -> 0.66666667 | M53: =IF(P53="TERMINADO",0,H53-(J53+K53)) -> 0 | N53: =1-(I53/H53) -> -25.666667 | O53: =IF(NOT(ISNUMBER(H53)),0,IF(P53="Terminado",1,IF(J53=0,0,MIN(1,J53/H53)))) -> 1 | P53: Terminado | Q53: =IF(COUNTIFS(A:A,A53,P:P,"Terminado")=COUNTIF(A:A,A53),"Terminado",IF(COUNTIFS(A:A,A53,P:P,"En proceso")>0,"En proceso","Pendiente")) -> Terminado | R53: =IFERROR(__xludf.DUMMYFUNCTION("SPARKLINE(O53,{""charttype"",""bar"";""max"",1;""color1"",IF(P53=""Terminado"",""#4CAF50"",IF(O53>=0.5,""#FFA500"",""#F44336""))})"),"")
A54: Culdesac-Coldculture | B54: Punto | C54: BASTIDOR ESPECIAL CURVA CULDESAC | D54: 4.7 | E54: 46112 | F54: =IFERROR(__xludf.DUMMYFUNCTION("FILTER(BBDD!H:H,BBDD!G:G=C54)"),"CNC") -> CNC | G54: =IFERROR(__xludf.DUMMYFUNCTION("FILTER(BBDD!I:I,BBDD!G:G=C54)"),"CNC") -> CNC | H54: =IFERROR(__xludf.DUMMYFUNCTION("(IFERROR(FILTER(BBDD!$J:$J,BBDD!$G:$G=C54,BBDD!$H:$H=F54,BBDD!$I:$I=G54),""NO TIENE PROCESO""))*D54"),0.9400000000000001) -> 0.94 | I54: =J54+K54 -> 0.466 | J54: =SUMIFS('👷horas'!$J:$J,'👷horas'!$D:$D,A54,'👷horas'!$E:$E,B54,'👷horas'!$F:$F,F54,'👷horas'!$G:$G,G54) -> 0.466 | K54: =SUMIFS('👷horas'!$K:$K,'👷horas'!$D:$D,A54,'👷horas'!$E:$E,B54,'👷horas'!$F:$F,F54,'👷horas'!$G:$G,G54) -> 0 | L54: =I54/D54 -> 0.099148936 | M54: =IF(P54="TERMINADO",0,H54-(J54+K54)) -> 0 | N54: =1-(I54/H54) -> 0.50425532 | O54: =IF(NOT(ISNUMBER(H54)),0,IF(P54="Terminado",1,IF(J54=0,0,MIN(1,J54/H54)))) -> 1 | P54: Terminado | Q54: =IF(COUNTIFS(A:A,A54,P:P,"Terminado")=COUNTIF(A:A,A54),"Terminado",IF(COUNTIFS(A:A,A54,P:P,"En proceso")>0,"En proceso","Pendiente")) -> Terminado | R54: =IFERROR(__xludf.DUMMYFUNCTION("SPARKLINE(O54,{""charttype"",""bar"";""max"",1;""color1"",IF(P54=""Terminado"",""#4CAF50"",IF(O54>=0.5,""#FFA500"",""#F44336""))})"),"")
A55: Culdesac-Coldculture | B55: Punto | C55: BASTIDOR ESPECIAL CURVA CULDESAC | D55: 4.7 | E55: 46112 | F55: =IFERROR(__xludf.DUMMYFUNCTION("""COMPUTED_VALUE"""),"Fabricación") -> Fabricación | G55: =IFERROR(__xludf.DUMMYFUNCTION("""COMPUTED_VALUE"""),"Ensamblaje") -> Ensamblaje | H55: =IFERROR(__xludf.DUMMYFUNCTION("(IFERROR(FILTER(BBDD!$J:$J,BBDD!$G:$G=C55,BBDD!$H:$H=F55,BBDD!$I:$I=G55),""NO TIENE PROCESO""))*D55"),5.708753715498938) -> 5.7087537 | I55: =J55+K55 -> 4.5 | J55: =SUMIFS('👷horas'!$J:$J,'👷horas'!$D:$D,A55,'👷horas'!$E:$E,B55,'👷horas'!$F:$F,F55,'👷horas'!$G:$G,G55) -> 3 | K55: =SUMIFS('👷horas'!$K:$K,'👷horas'!$D:$D,A55,'👷horas'!$E:$E,B55,'👷horas'!$F:$F,F55,'👷horas'!$G:$G,G55) -> 1.5 | L55: =I55/D55 -> 0.95744681 | M55: =IF(P55="TERMINADO",0,H55-(J55+K55)) -> 0 | N55: =1-(I55/H55) -> 0.21173688 | O55: =IF(NOT(ISNUMBER(H55)),0,IF(P55="Terminado",1,IF(J55=0,0,MIN(1,J55/H55)))) -> 1 | P55: Terminado | Q55: =IF(COUNTIFS(A:A,A55,P:P,"Terminado")=COUNTIF(A:A,A55),"Terminado",IF(COUNTIFS(A:A,A55,P:P,"En proceso")>0,"En proceso","Pendiente")) -> Terminado | R55: =IFERROR(__xludf.DUMMYFUNCTION("SPARKLINE(O55,{""charttype"",""bar"";""max"",1;""color1"",IF(P55=""Terminado"",""#4CAF50"",IF(O55>=0.5,""#FFA500"",""#F44336""))})"),"")
A56: Culdesac-Coldculture | B56: Punto | C56: BASTIDOR ESPECIAL CURVA CULDESAC | D56: 4.7 | E56: 46112 | F56: =IFERROR(__xludf.DUMMYFUNCTION("""COMPUTED_VALUE"""),"Fabricación") -> Fabricación | G56: =IFERROR(__xludf.DUMMYFUNCTION("""COMPUTED_VALUE"""),"Colocación de perfiles") -> Colocación de perfiles | H56: =IFERROR(__xludf.DUMMYFUNCTION("(IFERROR(FILTER(BBDD!$J:$J,BBDD!$G:$G=C56,BBDD!$H:$H=F56,BBDD!$I:$I=G56),""NO TIENE PROCESO""))*D56"),2.935753715498939) -> 2.9357537 | I56: =J56+K56 -> 3 | J56: =SUMIFS('👷horas'!$J:$J,'👷horas'!$D:$D,A56,'👷horas'!$E:$E,B56,'👷horas'!$F:$F,F56,'👷horas'!$G:$G,G56) -> 3 | K56: =SUMIFS('👷horas'!$K:$K,'👷horas'!$D:$D,A56,'👷horas'!$E:$E,B56,'👷horas'!$F:$F,F56,'👷horas'!$G:$G,G56) -> 0 | L56: =I56/D56 -> 0.63829787 | M56: =IF(P56="TERMINADO",0,H56-(J56+K56)) -> 0 | N56: =1-(I56/H56) -> -0.021884085 | O56: =IF(NOT(ISNUMBER(H56)),0,IF(P56="Terminado",1,IF(J56=0,0,MIN(1,J56/H56)))) -> 1 | P56: Terminado | Q56: =IF(COUNTIFS(A:A,A56,P:P,"Terminado")=COUNTIF(A:A,A56),"Terminado",IF(COUNTIFS(A:A,A56,P:P,"En proceso")>0,"En proceso","Pendiente")) -> Terminado | R56: =IFERROR(__xludf.DUMMYFUNCTION("SPARKLINE(O56,{""charttype"",""bar"";""max"",1;""color1"",IF(P56=""Terminado"",""#4CAF50"",IF(O56>=0.5,""#FFA500"",""#F44336""))})"),"")
A57: Culdesac-Coldculture | B57: Punto | C57: BASTIDOR ESPECIAL CURVA CULDESAC | D57: 4.7 | E57: 46112 | F57: =IFERROR(__xludf.DUMMYFUNCTION("""COMPUTED_VALUE"""),"Fabricación") -> Fabricación | G57: =IFERROR(__xludf.DUMMYFUNCTION("""COMPUTED_VALUE"""),"Embalaje/carga/descarga material") -> Embalaje/carga/descarga material | H57: =IFERROR(__xludf.DUMMYFUNCTION("(IFERROR(FILTER(BBDD!$J:$J,BBDD!$G:$G=C57,BBDD!$H:$H=F57,BBDD!$I:$I=G57),""NO TIENE PROCESO""))*D57"),0.705) -> 0.705 | I57: =J57+K57 -> 0.5 | J57: =SUMIFS('👷horas'!$J:$J,'👷horas'!$D:$D,A57,'👷horas'!$E:$E,B57,'👷horas'!$F:$F,F57,'👷horas'!$G:$G,G57) -> 0.5 | K57: =SUMIFS('👷horas'!$K:$K,'👷horas'!$D:$D,A57,'👷horas'!$E:$E,B57,'👷horas'!$F:$F,F57,'👷horas'!$G:$G,G57) -> 0 | L57: =I57/D57 -> 0.10638298 | M57: =IF(P57="TERMINADO",0,H57-(J57+K57)) -> 0 | N57: =1-(I57/H57) -> 0.29078014 | O57: =IF(NOT(ISNUMBER(H57)),0,IF(P57="Terminado",1,IF(J57=0,0,MIN(1,J57/H57)))) -> 1 | P57: Terminado | Q57: =IF(COUNTIFS(A:A,A57,P:P,"Terminado")=COUNTIF(A:A,A57),"Terminado",IF(COUNTIFS(A:A,A57,P:P,"En proceso")>0,"En proceso","Pendiente")) -> Terminado | R57: =IFERROR(__xludf.DUMMYFUNCTION("SPARKLINE(O57,{""charttype"",""bar"";""max"",1;""color1"",IF(P57=""Terminado"",""#4CAF50"",IF(O57>=0.5,""#FFA500"",""#F44336""))})"),"")
A58: Culdesac-Coldculture | B58: Punto | C58: BASTIDOR ESPECIAL CURVA CULDESAC | D58: 4.7 | E58: 46112 | F58: =IFERROR(__xludf.DUMMYFUNCTION("""COMPUTED_VALUE"""),"Pintura") -> Pintura | G58: =IFERROR(__xludf.DUMMYFUNCTION("""COMPUTED_VALUE"""),"Lijado y/o Masillado") -> Lijado y/o Masillado | H58: =IFERROR(__xludf.DUMMYFUNCTION("(IFERROR(FILTER(BBDD!$J:$J,BBDD!$G:$G=C58,BBDD!$H:$H=F58,BBDD!$I:$I=G58),""NO TIENE PROCESO""))*D58"),2.82) -> 2.82 | I58: =J58+K58 -> 9.5 | J58: =SUMIFS('👷horas'!$J:$J,'👷horas'!$D:$D,A58,'👷horas'!$E:$E,B58,'👷horas'!$F:$F,F58,'👷horas'!$G:$G,G58) -> 9 | K58: =SUMIFS('👷horas'!$K:$K,'👷horas'!$D:$D,A58,'👷horas'!$E:$E,B58,'👷horas'!$F:$F,F58,'👷horas'!$G:$G,G58) -> 0.5 | L58: =I58/D58 -> 2.0212766 | M58: =IF(P58="TERMINADO",0,H58-(J58+K58)) -> 0 | N58: =1-(I58/H58) -> -2.3687943 | O58: =IF(NOT(ISNUMBER(H58)),0,IF(P58="Terminado",1,IF(J58=0,0,MIN(1,J58/H58)))) -> 1 | P58: Terminado | Q58: =IF(COUNTIFS(A:A,A58,P:P,"Terminado")=COUNTIF(A:A,A58),"Terminado",IF(COUNTIFS(A:A,A58,P:P,"En proceso")>0,"En proceso","Pendiente")) -> Terminado | R58: =IFERROR(__xludf.DUMMYFUNCTION("SPARKLINE(O58,{""charttype"",""bar"";""max"",1;""color1"",IF(P58=""Terminado"",""#4CAF50"",IF(O58>=0.5,""#FFA500"",""#F44336""))})"),"")
A59: Culdesac-Coldculture | B59: Punto | C59: BASTIDOR ESPECIAL CURVA CULDESAC | D59: 4.7 | E59: 46112 | F59: =IFERROR(__xludf.DUMMYFUNCTION("""COMPUTED_VALUE"""),"Pintura") -> Pintura | G59: =IFERROR(__xludf.DUMMYFUNCTION("""COMPUTED_VALUE"""),"Imprimación/Pintura") -> Imprimación/Pintura | H59: =IFERROR(__xludf.DUMMYFUNCTION("(IFERROR(FILTER(BBDD!$J:$J,BBDD!$G:$G=C59,BBDD!$H:$H=F59,BBDD!$I:$I=G59),""NO TIENE PROCESO""))*D59"),1.8800000000000001) -> 1.88 | I59: =J59+K59 -> 3 | J59: =SUMIFS('👷horas'!$J:$J,'👷horas'!$D:$D,A59,'👷horas'!$E:$E,B59,'👷horas'!$F:$F,F59,'👷horas'!$G:$G,G59) -> 2 | K59: =SUMIFS('👷horas'!$K:$K,'👷horas'!$D:$D,A59,'👷horas'!$E:$E,B59,'👷horas'!$F:$F,F59,'👷horas'!$G:$G,G59) -> 1 | L59: =I59/D59 -> 0.63829787 | M59: =IF(P59="TERMINADO",0,H59-(J59+K59)) -> 0 | N59: =1-(I59/H59) -> -0.59574468 | O59: =IF(NOT(ISNUMBER(H59)),0,IF(P59="Terminado",1,IF(J59=0,0,MIN(1,J59/H59)))) -> 1 | P59: Terminado | Q59: =IF(COUNTIFS(A:A,A59,P:P,"Terminado")=COUNTIF(A:A,A59),"Terminado",IF(COUNTIFS(A:A,A59,P:P,"En proceso")>0,"En proceso","Pendiente")) -> Terminado | R59: =IFERROR(__xludf.DUMMYFUNCTION("SPARKLINE(O59,{""charttype"",""bar"";""max"",1;""color1"",IF(P59=""Terminado"",""#4CAF50"",IF(O59>=0.5,""#FFA500"",""#F44336""))})"),"")
A60: Culdesac-Coldculture | B60: Estanteria | C60: ESTANTERIA CULDESAC - PERFIL METACRILATO | D60: 18 | E60: 46112 | F60: =IFERROR(__xludf.DUMMYFUNCTION("FILTER(BBDD!H:H,BBDD!G:G=C60)"),"Fabricación") -> Fabricación | G60: =IFERROR(__xludf.DUMMYFUNCTION("FILTER(BBDD!I:I,BBDD!G:G=C60)"),"Ensamblaje") -> Ensamblaje | H60: =IFERROR(__xludf.DUMMYFUNCTION("(IFERROR(FILTER(BBDD!$J:$J,BBDD!$G:$G=C60,BBDD!$H:$H=F60,BBDD!$I:$I=G60),""NO TIENE PROCESO""))*D60"),23.94) -> 23.94 | I60: =J60+K60 -> 78 | J60: =SUMIFS('👷horas'!$J:$J,'👷horas'!$D:$D,A60,'👷horas'!$E:$E,B60,'👷horas'!$F:$F,F60,'👷horas'!$G:$G,G60) -> 58 | K60: =SUMIFS('👷horas'!$K:$K,'👷horas'!$D:$D,A60,'👷horas'!$E:$E,B60,'👷horas'!$F:$F,F60,'👷horas'!$G:$G,G60) -> 20 | L60: =I60/D60 -> 4.3333333 | M60: =IF(P60="TERMINADO",0,H60-(J60+K60)) -> 0 | N60: =1-(I60/H60) -> -2.2581454 | O60: =IF(NOT(ISNUMBER(H60)),0,IF(P60="Terminado",1,IF(J60=0,0,MIN(1,J60/H60)))) -> 1 | P60: Terminado | Q60: =IF(COUNTIFS(A:A,A60,P:P,"Terminado")=COUNTIF(A:A,A60),"Terminado",IF(COUNTIFS(A:A,A60,P:P,"En proceso")>0,"En proceso","Pendiente")) -> Terminado | R60: =IFERROR(__xludf.DUMMYFUNCTION("SPARKLINE(O60,{""charttype"",""bar"";""max"",1;""color1"",IF(P60=""Terminado"",""#4CAF50"",IF(O60>=0.5,""#FFA500"",""#F44336""))})"),"")
A61: Culdesac-Coldculture | B61: Estanteria | C61: ESTANTERIA CULDESAC - PERFIL METACRILATO | D61: 18 | E61: 46112 | F61: =IFERROR(__xludf.DUMMYFUNCTION("""COMPUTED_VALUE"""),"Fabricación") -> Fabricación | G61: =IFERROR(__xludf.DUMMYFUNCTION("""COMPUTED_VALUE"""),"Colocación de perfiles") -> Colocación de perfiles | H61: =IFERROR(__xludf.DUMMYFUNCTION("(IFERROR(FILTER(BBDD!$J:$J,BBDD!$G:$G=C61,BBDD!$H:$H=F61,BBDD!$I:$I=G61),""NO TIENE PROCESO""))*D61"),29.88) -> 29.88 | I61: =J61+K61 -> 25.25 | J61: =SUMIFS('👷horas'!$J:$J,'👷horas'!$D:$D,A61,'👷horas'!$E:$E,B61,'👷horas'!$F:$F,F61,'👷horas'!$G:$G,G61) -> 8.5 | K61: =SUMIFS('👷horas'!$K:$K,'👷horas'!$D:$D,A61,'👷horas'!$E:$E,B61,'👷horas'!$F:$F,F61,'👷horas'!$G:$G,G61) -> 16.75 | L61: =I61/D61 -> 1.4027778 | M61: =IF(P61="TERMINADO",0,H61-(J61+K61)) -> 0 | N61: =1-(I61/H61) -> 0.15495315 | O61: =IF(NOT(ISNUMBER(H61)),0,IF(P61="Terminado",1,IF(J61=0,0,MIN(1,J61/H61)))) -> 1 | P61: Terminado | Q61: =IF(COUNTIFS(A:A,A61,P:P,"Terminado")=COUNTIF(A:A,A61),"Terminado",IF(COUNTIFS(A:A,A61,P:P,"En proceso")>0,"En proceso","Pendiente")) -> Terminado | R61: =IFERROR(__xludf.DUMMYFUNCTION("SPARKLINE(O61,{""charttype"",""bar"";""max"",1;""color1"",IF(P61=""Terminado"",""#4CAF50"",IF(O61>=0.5,""#FFA500"",""#F44336""))})"),"")
A62: Culdesac-Coldculture | B62: Policarbonato | C62: TIEMPO PRESUPUESTO | D62: 1 | E62: 46112 | F62: Fabricación | G62: Corte manual | H62: 6 | I62: =J62+K62 -> 7 | J62: =SUMIFS('👷horas'!$J:$J,'👷horas'!$D:$D,A62,'👷horas'!$E:$E,B62,'👷horas'!$F:$F,F62,'👷horas'!$G:$G,G62) -> 7 | K62: =SUMIFS('👷horas'!$K:$K,'👷horas'!$D:$D,A62,'👷horas'!$E:$E,B62,'👷horas'!$F:$F,F62,'👷horas'!$G:$G,G62) -> 0 | L62: =I62/D62 -> 7 | M62: =IF(P62="TERMINADO",0,H62-(J62+K62)) -> 0 | N62: =1-(I62/H62) -> -0.16666667 | O62: =IF(NOT(ISNUMBER(H62)),0,IF(P62="Terminado",1,IF(J62=0,0,MIN(1,J62/H62)))) -> 1 | P62: Terminado | Q62: =IF(COUNTIFS(A:A,A62,P:P,"Terminado")=COUNTIF(A:A,A62),"Terminado",IF(COUNTIFS(A:A,A62,P:P,"En proceso")>0,"En proceso","Pendiente")) -> Terminado | R62: =IFERROR(__xludf.DUMMYFUNCTION("SPARKLINE(O62,{""charttype"",""bar"";""max"",1;""color1"",IF(P62=""Terminado"",""#4CAF50"",IF(O62>=0.5,""#FFA500"",""#F44336""))})"),"")
A63: Culdesac-Coldculture | B63: Policarbonato | C63: TIEMPO PRESUPUESTO | D63: 1 | E63: 46112 | F63: Fabricación | G63: Transporte material | H63: 1 | I63: =J63+K63 -> 5.5 | J63: =SUMIFS('👷horas'!$J:$J,'👷horas'!$D:$D,A63,'👷horas'!$E:$E,B63,'👷horas'!$F:$F,F63,'👷horas'!$G:$G,G63) -> 5.5 | K63: =SUMIFS('👷horas'!$K:$K,'👷horas'!$D:$D,A63,'👷horas'!$E:$E,B63,'👷horas'!$F:$F,F63,'👷horas'!$G:$G,G63) -> 0 | L63: =I63/D63 -> 5.5 | M63: =IF(P63="TERMINADO",0,H63-(J63+K63)) -> 0 | N63: =1-(I63/H63) -> -4.5 | O63: =IF(NOT(ISNUMBER(H63)),0,IF(P63="Terminado",1,IF(J63=0,0,MIN(1,J63/H63)))) -> 1 | P63: Terminado | Q63: =IF(COUNTIFS(A:A,A63,P:P,"Terminado")=COUNTIF(A:A,A63),"Terminado",IF(COUNTIFS(A:A,A63,P:P,"En proceso")>0,"En proceso","Pendiente")) -> Terminado | R63: =IFERROR(__xludf.DUMMYFUNCTION("SPARKLINE(O63,{""charttype"",""bar"";""max"",1;""color1"",IF(P63=""Terminado"",""#4CAF50"",IF(O63>=0.5,""#FFA500"",""#F44336""))})"),"")
A64: Druni Catarroja | B64: Cruz | C64: BASTIDOR DE TABICA 150X12 | D64: 13.8 | E64: 46113 | F64: =IFERROR(__xludf.DUMMYFUNCTION("FILTER(BBDD!H:H,BBDD!G:G=C64)"),"CNC") -> CNC | G64: =IFERROR(__xludf.DUMMYFUNCTION("FILTER(BBDD!I:I,BBDD!G:G=C64)"),"CNC") -> CNC | H64: =IFERROR(__xludf.DUMMYFUNCTION("(IFERROR(FILTER(BBDD!$J:$J,BBDD!$G:$G=C64,BBDD!$H:$H=F64,BBDD!$I:$I=G64),""NO TIENE PROCESO""))*D64"),2.7600000000000002) -> 2.76 | I64: =J64+K64 -> 1.7388 | J64: =SUMIFS('👷horas'!$J:$J,'👷horas'!$D:$D,A64,'👷horas'!$E:$E,B64,'👷horas'!$F:$F,F64,'👷horas'!$G:$G,G64) -> 1.7388 | K64: =SUMIFS('👷horas'!$K:$K,'👷horas'!$D:$D,A64,'👷horas'!$E:$E,B64,'👷horas'!$F:$F,F64,'👷horas'!$G:$G,G64) -> 0 | L64: =I64/D64 -> 0.126 | M64: =IF(P64="TERMINADO",0,H64-(J64+K64)) -> 0 | N64: =1-(I64/H64) -> 0.37 | O64: =IF(NOT(ISNUMBER(H64)),0,IF(P64="Terminado",1,IF(J64=0,0,MIN(1,J64/H64)))) -> 1 | P64: Terminado | Q64: =IF(COUNTIFS(A:A,A64,P:P,"Terminado")=COUNTIF(A:A,A64),"Terminado",IF(COUNTIFS(A:A,A64,P:P,"En proceso")>0,"En proceso","Pendiente")) -> Terminado | R64: =IFERROR(__xludf.DUMMYFUNCTION("SPARKLINE(O64,{""charttype"",""bar"";""max"",1;""color1"",IF(P64=""Terminado"",""#4CAF50"",IF(O64>=0.5,""#FFA500"",""#F44336""))})"),"")
A65: Druni Catarroja | B65: Cruz | C65: BASTIDOR DE TABICA 150X12 | D65: 13.8 | E65: 46113 | F65: =IFERROR(__xludf.DUMMYFUNCTION("""COMPUTED_VALUE"""),"Fabricación") -> Fabricación | G65: =IFERROR(__xludf.DUMMYFUNCTION("""COMPUTED_VALUE"""),"Ensamblaje") -> Ensamblaje | H65: =IFERROR(__xludf.DUMMYFUNCTION("(IFERROR(FILTER(BBDD!$J:$J,BBDD!$G:$G=C65,BBDD!$H:$H=F65,BBDD!$I:$I=G65),""NO TIENE PROCESO""))*D65"),8.556000000000001) -> 8.556 | I65: =J65+K65 -> 8 | J65: =SUMIFS('👷horas'!$J:$J,'👷horas'!$D:$D,A65,'👷horas'!$E:$E,B65,'👷horas'!$F:$F,F65,'👷horas'!$G:$G,G65) -> 8 | K65: =SUMIFS('👷horas'!$K:$K,'👷horas'!$D:$D,A65,'👷horas'!$E:$E,B65,'👷horas'!$F:$F,F65,'👷horas'!$G:$G,G65) -> 0 | L65: =I65/D65 -> 0.57971014 | M65: =IF(P65="TERMINADO",0,H65-(J65+K65)) -> 0 | N65: =1-(I65/H65) -> 0.064983637 | O65: =IF(NOT(ISNUMBER(H65)),0,IF(P65="Terminado",1,IF(J65=0,0,MIN(1,J65/H65)))) -> 1 | P65: Terminado | Q65: =IF(COUNTIFS(A:A,A65,P:P,"Terminado")=COUNTIF(A:A,A65),"Terminado",IF(COUNTIFS(A:A,A65,P:P,"En proceso")>0,"En proceso","Pendiente")) -> Terminado | R65: =IFERROR(__xludf.DUMMYFUNCTION("SPARKLINE(O65,{""charttype"",""bar"";""max"",1;""color1"",IF(P65=""Terminado"",""#4CAF50"",IF(O65>=0.5,""#FFA500"",""#F44336""))})"),"")
A66: Druni Catarroja | B66: Cruz | C66: BASTIDOR DE TABICA 150X12 | D66: 13.8 | E66: 46113 | F66: =IFERROR(__xludf.DUMMYFUNCTION("""COMPUTED_VALUE"""),"Fabricación") -> Fabricación | G66: =IFERROR(__xludf.DUMMYFUNCTION("""COMPUTED_VALUE"""),"Colocación de perfiles") -> Colocación de perfiles | H66: =IFERROR(__xludf.DUMMYFUNCTION("(IFERROR(FILTER(BBDD!$J:$J,BBDD!$G:$G=C66,BBDD!$H:$H=F66,BBDD!$I:$I=G66),""NO TIENE PROCESO""))*D66"),2.7600000000000002) -> 2.76 | I66: =J66+K66 -> 3 | J66: =SUMIFS('👷horas'!$J:$J,'👷horas'!$D:$D,A66,'👷horas'!$E:$E,B66,'👷horas'!$F:$F,F66,'👷horas'!$G:$G,G66) -> 3 | K66: =SUMIFS('👷horas'!$K:$K,'👷horas'!$D:$D,A66,'👷horas'!$E:$E,B66,'👷horas'!$F:$F,F66,'👷horas'!$G:$G,G66) -> 0 | L66: =I66/D66 -> 0.2173913 | M66: =IF(P66="TERMINADO",0,H66-(J66+K66)) -> 0 | N66: =1-(I66/H66) -> -0.086956522 | O66: =IF(NOT(ISNUMBER(H66)),0,IF(P66="Terminado",1,IF(J66=0,0,MIN(1,J66/H66)))) -> 1 | P66: Terminado | Q66: =IF(COUNTIFS(A:A,A66,P:P,"Terminado")=COUNTIF(A:A,A66),"Terminado",IF(COUNTIFS(A:A,A66,P:P,"En proceso")>0,"En proceso","Pendiente")) -> Terminado | R66: =IFERROR(__xludf.DUMMYFUNCTION("SPARKLINE(O66,{""charttype"",""bar"";""max"",1;""color1"",IF(P66=""Terminado"",""#4CAF50"",IF(O66>=0.5,""#FFA500"",""#F44336""))})"),"")
A67: Druni Catarroja | B67: Cruz | C67: BASTIDOR DE TABICA 150X12 | D67: 13.8 | E67: 46113 | F67: =IFERROR(__xludf.DUMMYFUNCTION("""COMPUTED_VALUE"""),"Fabricación") -> Fabricación | G67: =IFERROR(__xludf.DUMMYFUNCTION("""COMPUTED_VALUE"""),"Embalaje/carga/descarga material") -> Embalaje/carga/descarga material | H67: =IFERROR(__xludf.DUMMYFUNCTION("(IFERROR(FILTER(BBDD!$J:$J,BBDD!$G:$G=C67,BBDD!$H:$H=F67,BBDD!$I:$I=G67),""NO TIENE PROCESO""))*D67"),2.07) -> 2.07 | I67: =J67+K67 -> 1.5 | J67: =SUMIFS('👷horas'!$J:$J,'👷horas'!$D:$D,A67,'👷horas'!$E:$E,B67,'👷horas'!$F:$F,F67,'👷horas'!$G:$G,G67) -> 1.5 | K67: =SUMIFS('👷horas'!$K:$K,'👷horas'!$D:$D,A67,'👷horas'!$E:$E,B67,'👷horas'!$F:$F,F67,'👷horas'!$G:$G,G67) -> 0 | L67: =I67/D67 -> 0.10869565 | M67: =IF(P67="TERMINADO",0,H67-(J67+K67)) -> 0 | N67: =1-(I67/H67) -> 0.27536232 | O67: =IF(NOT(ISNUMBER(H67)),0,IF(P67="Terminado",1,IF(J67=0,0,MIN(1,J67/H67)))) -> 1 | P67: Terminado | Q67: =IF(COUNTIFS(A:A,A67,P:P,"Terminado")=COUNTIF(A:A,A67),"Terminado",IF(COUNTIFS(A:A,A67,P:P,"En proceso")>0,"En proceso","Pendiente")) -> Terminado | R67: =IFERROR(__xludf.DUMMYFUNCTION("SPARKLINE(O67,{""charttype"",""bar"";""max"",1;""color1"",IF(P67=""Terminado"",""#4CAF50"",IF(O67>=0.5,""#FFA500"",""#F44336""))})"),"")
A68: Druni Catarroja | B68: Cruz | C68: BASTIDOR DE TABICA 150X12 | D68: 13.8 | E68: 46113 | F68: =IFERROR(__xludf.DUMMYFUNCTION("""COMPUTED_VALUE"""),"Pintura") -> Pintura | G68: =IFERROR(__xludf.DUMMYFUNCTION("""COMPUTED_VALUE"""),"Lijado y/o Masillado") -> Lijado y/o Masillado | H68: =IFERROR(__xludf.DUMMYFUNCTION("(IFERROR(FILTER(BBDD!$J:$J,BBDD!$G:$G=C68,BBDD!$H:$H=F68,BBDD!$I:$I=G68),""NO TIENE PROCESO""))*D68"),6.9) -> 6.9 | I68: =J68+K68 -> 11.5 | J68: =SUMIFS('👷horas'!$J:$J,'👷horas'!$D:$D,A68,'👷horas'!$E:$E,B68,'👷horas'!$F:$F,F68,'👷horas'!$G:$G,G68) -> 9.5 | K68: =SUMIFS('👷horas'!$K:$K,'👷horas'!$D:$D,A68,'👷horas'!$E:$E,B68,'👷horas'!$F:$F,F68,'👷horas'!$G:$G,G68) -> 2 | L68: =I68/D68 -> 0.83333333 | M68: =IF(P68="TERMINADO",0,H68-(J68+K68)) -> 0 | N68: =1-(I68/H68) -> -0.66666667 | O68: =IF(NOT(ISNUMBER(H68)),0,IF(P68="Terminado",1,IF(J68=0,0,MIN(1,J68/H68)))) -> 1 | P68: Terminado | Q68: =IF(COUNTIFS(A:A,A68,P:P,"Terminado")=COUNTIF(A:A,A68),"Terminado",IF(COUNTIFS(A:A,A68,P:P,"En proceso")>0,"En proceso","Pendiente")) -> Terminado | R68: =IFERROR(__xludf.DUMMYFUNCTION("SPARKLINE(O68,{""charttype"",""bar"";""max"",1;""color1"",IF(P68=""Terminado"",""#4CAF50"",IF(O68>=0.5,""#FFA500"",""#F44336""))})"),"")
A69: Druni Catarroja | B69: Cruz | C69: BASTIDOR DE TABICA 150X12 | D69: 13.8 | E69: 46113 | F69: =IFERROR(__xludf.DUMMYFUNCTION("""COMPUTED_VALUE"""),"Pintura") -> Pintura | G69: =IFERROR(__xludf.DUMMYFUNCTION("""COMPUTED_VALUE"""),"Imprimación/Pintura") -> Imprimación/Pintura | H69: =IFERROR(__xludf.DUMMYFUNCTION("(IFERROR(FILTER(BBDD!$J:$J,BBDD!$G:$G=C69,BBDD!$H:$H=F69,BBDD!$I:$I=G69),""NO TIENE PROCESO""))*D69"),5.5200000000000005) -> 5.52 | I69: =J69+K69 -> 4.5 | J69: =SUMIFS('👷horas'!$J:$J,'👷horas'!$D:$D,A69,'👷horas'!$E:$E,B69,'👷horas'!$F:$F,F69,'👷horas'!$G:$G,G69) -> 4.5 | K69: =SUMIFS('👷horas'!$K:$K,'👷horas'!$D:$D,A69,'👷horas'!$E:$E,B69,'👷horas'!$F:$F,F69,'👷horas'!$G:$G,G69) -> 0 | L69: =I69/D69 -> 0.32608696 | M69: =IF(P69="TERMINADO",0,H69-(J69+K69)) -> 0 | N69: =1-(I69/H69) -> 0.18478261 | O69: =IF(NOT(ISNUMBER(H69)),0,IF(P69="Terminado",1,IF(J69=0,0,MIN(1,J69/H69)))) -> 1 | P69: Terminado | Q69: =IF(COUNTIFS(A:A,A69,P:P,"Terminado")=COUNTIF(A:A,A69),"Terminado",IF(COUNTIFS(A:A,A69,P:P,"En proceso")>0,"En proceso","Pendiente")) -> Terminado | R69: =IFERROR(__xludf.DUMMYFUNCTION("SPARKLINE(O69,{""charttype"",""bar"";""max"",1;""color1"",IF(P69=""Terminado"",""#4CAF50"",IF(O69>=0.5,""#FFA500"",""#F44336""))})"),"")
A70: Druni Catarroja | B70: Sol | C70: BASTIDOR DE METACRILATO CURVO | D70: 10.03 | E70: 46113 | F70: =IFERROR(__xludf.DUMMYFUNCTION("FILTER(BBDD!H:H,BBDD!G:G=C70)"),"Fabricación") -> Fabricación | G70: =IFERROR(__xludf.DUMMYFUNCTION("FILTER(BBDD!I:I,BBDD!G:G=C70)"),"Ensamblaje") -> Ensamblaje | H70: =IFERROR(__xludf.DUMMYFUNCTION("(IFERROR(FILTER(BBDD!$J:$J,BBDD!$G:$G=C70,BBDD!$H:$H=F70,BBDD!$I:$I=G70),""NO TIENE PROCESO""))*D70"),25.075) -> 25.075 | I70: =J70+K70 -> 17 | J70: =SUMIFS('👷horas'!$J:$J,'👷horas'!$D:$D,A70,'👷horas'!$E:$E,B70,'👷horas'!$F:$F,F70,'👷horas'!$G:$G,G70) -> 14.5 | K70: =SUMIFS('👷horas'!$K:$K,'👷horas'!$D:$D,A70,'👷horas'!$E:$E,B70,'👷horas'!$F:$F,F70,'👷horas'!$G:$G,G70) -> 2.5 | L70: =I70/D70 -> 1.6949153 | M70: =IF(P70="TERMINADO",0,H70-(J70+K70)) -> 0 | N70: =1-(I70/H70) -> 0.3220339 | O70: =IF(NOT(ISNUMBER(H70)),0,IF(P70="Terminado",1,IF(J70=0,0,MIN(1,J70/H70)))) -> 1 | P70: Terminado | Q70: =IF(COUNTIFS(A:A,A70,P:P,"Terminado")=COUNTIF(A:A,A70),"Terminado",IF(COUNTIFS(A:A,A70,P:P,"En proceso")>0,"En proceso","Pendiente")) -> Terminado | R70: =IFERROR(__xludf.DUMMYFUNCTION("SPARKLINE(O70,{""charttype"",""bar"";""max"",1;""color1"",IF(P70=""Terminado"",""#4CAF50"",IF(O70>=0.5,""#FFA500"",""#F44336""))})"),"")
A71: Druni Catarroja | B71: Sol | C71: BASTIDOR DE METACRILATO CURVO | D71: 10.03 | E71: 46113 | F71: =IFERROR(__xludf.DUMMYFUNCTION("""COMPUTED_VALUE"""),"Fabricación") -> Fabricación | G71: =IFERROR(__xludf.DUMMYFUNCTION("""COMPUTED_VALUE"""),"Embalaje/carga/descarga material") -> Embalaje/carga/descarga material | H71: =IFERROR(__xludf.DUMMYFUNCTION("(IFERROR(FILTER(BBDD!$J:$J,BBDD!$G:$G=C71,BBDD!$H:$H=F71,BBDD!$I:$I=G71),""NO TIENE PROCESO""))*D71"),1.3039) -> 1.3039 | I71: =J71+K71 -> 1 | J71: =SUMIFS('👷horas'!$J:$J,'👷horas'!$D:$D,A71,'👷horas'!$E:$E,B71,'👷horas'!$F:$F,F71,'👷horas'!$G:$G,G71) -> 1 | K71: =SUMIFS('👷horas'!$K:$K,'👷horas'!$D:$D,A71,'👷horas'!$E:$E,B71,'👷horas'!$F:$F,F71,'👷horas'!$G:$G,G71) -> 0 | L71: =I71/D71 -> 0.099700897 | M71: =IF(P71="TERMINADO",0,H71-(J71+K71)) -> 0 | N71: =1-(I71/H71) -> 0.23307002 | O71: =IF(NOT(ISNUMBER(H71)),0,IF(P71="Terminado",1,IF(J71=0,0,MIN(1,J71/H71)))) -> 1 | P71: Terminado | Q71: =IF(COUNTIFS(A:A,A71,P:P,"Terminado")=COUNTIF(A:A,A71),"Terminado",IF(COUNTIFS(A:A,A71,P:P,"En proceso")>0,"En proceso","Pendiente")) -> Terminado | R71: =IFERROR(__xludf.DUMMYFUNCTION("SPARKLINE(O71,{""charttype"",""bar"";""max"",1;""color1"",IF(P71=""Terminado"",""#4CAF50"",IF(O71>=0.5,""#FFA500"",""#F44336""))})"),"")
A72: Inventario | B72: Gracos | C72: BASTIDOR DE TABICA CURVA 150X12 | D72: 25.1 | E72: 46113 | F72: =IFERROR(__xludf.DUMMYFUNCTION("FILTER(BBDD!H:H,BBDD!G:G=C72)"),"CNC") -> CNC | G72: =IFERROR(__xludf.DUMMYFUNCTION("FILTER(BBDD!I:I,BBDD!G:G=C72)"),"CNC") -> CNC | H72: =IFERROR(__xludf.DUMMYFUNCTION("(IFERROR(FILTER(BBDD!$J:$J,BBDD!$G:$G=C72,BBDD!$H:$H=F72,BBDD!$I:$I=G72),""NO TIENE PROCESO""))*D72"),5.0200000000000005) -> 5.02 | I72: =J72+K72 -> 2.0621 | J72: =SUMIFS('👷horas'!$J:$J,'👷horas'!$D:$D,A72,'👷horas'!$E:$E,B72,'👷horas'!$F:$F,F72,'👷horas'!$G:$G,G72) -> 2.0621 | K72: =SUMIFS('👷horas'!$K:$K,'👷horas'!$D:$D,A72,'👷horas'!$E:$E,B72,'👷horas'!$F:$F,F72,'👷horas'!$G:$G,G72) -> 0 | L72: =I72/D72 -> 0.082155378 | M72: =IF(P72="TERMINADO",0,H72-(J72+K72)) -> 0 | N72: =1-(I72/H72) -> 0.58922311 | O72: =IF(NOT(ISNUMBER(H72)),0,IF(P72="Terminado",1,IF(J72=0,0,MIN(1,J72/H72)))) -> 1 | P72: Terminado | Q72: =IF(COUNTIFS(A:A,A72,P:P,"Terminado")=COUNTIF(A:A,A72),"Terminado",IF(COUNTIFS(A:A,A72,P:P,"En proceso")>0,"En proceso","Pendiente")) -> Terminado | R72: =IFERROR(__xludf.DUMMYFUNCTION("SPARKLINE(O72,{""charttype"",""bar"";""max"",1;""color1"",IF(P72=""Terminado"",""#4CAF50"",IF(O72>=0.5,""#FFA500"",""#F44336""))})"),"")
A73: Inventario | B73: Gracos | C73: BASTIDOR DE TABICA CURVA 150X12 | D73: 25.1 | E73: 46113 | F73: =IFERROR(__xludf.DUMMYFUNCTION("""COMPUTED_VALUE"""),"Fabricación") -> Fabricación | G73: =IFERROR(__xludf.DUMMYFUNCTION("""COMPUTED_VALUE"""),"Ensamblaje") -> Ensamblaje | H73: =IFERROR(__xludf.DUMMYFUNCTION("(IFERROR(FILTER(BBDD!$J:$J,BBDD!$G:$G=C73,BBDD!$H:$H=F73,BBDD!$I:$I=G73),""NO TIENE PROCESO""))*D73"),19.829) -> 19.829 | I73: =J73+K73 -> 16.5 | J73: =SUMIFS('👷horas'!$J:$J,'👷horas'!$D:$D,A73,'👷horas'!$E:$E,B73,'👷horas'!$F:$F,F73,'👷horas'!$G:$G,G73) -> 15.5 | K73: =SUMIFS('👷horas'!$K:$K,'👷horas'!$D:$D,A73,'👷horas'!$E:$E,B73,'👷horas'!$F:$F,F73,'👷horas'!$G:$G,G73) -> 1 | L73: =I73/D73 -> 0.65737052 | M73: =IF(P73="TERMINADO",0,H73-(J73+K73)) -> 0 | N73: =1-(I73/H73) -> 0.16788542 | O73: =IF(NOT(ISNUMBER(H73)),0,IF(P73="Terminado",1,IF(J73=0,0,MIN(1,J73/H73)))) -> 1 | P73: Terminado | Q73: =IF(COUNTIFS(A:A,A73,P:P,"Terminado")=COUNTIF(A:A,A73),"Terminado",IF(COUNTIFS(A:A,A73,P:P,"En proceso")>0,"En proceso","Pendiente")) -> Terminado | R73: =IFERROR(__xludf.DUMMYFUNCTION("SPARKLINE(O73,{""charttype"",""bar"";""max"",1;""color1"",IF(P73=""Terminado"",""#4CAF50"",IF(O73>=0.5,""#FFA500"",""#F44336""))})"),"")
A74: Inventario | B74: Gracos | C74: BASTIDOR DE TABICA CURVA 150X12 | D74: 25.1 | E74: 46113 | F74: =IFERROR(__xludf.DUMMYFUNCTION("""COMPUTED_VALUE"""),"Fabricación") -> Fabricación | G74: =IFERROR(__xludf.DUMMYFUNCTION("""COMPUTED_VALUE"""),"Colocación de perfiles") -> Colocación de perfiles | H74: =IFERROR(__xludf.DUMMYFUNCTION("(IFERROR(FILTER(BBDD!$J:$J,BBDD!$G:$G=C74,BBDD!$H:$H=F74,BBDD!$I:$I=G74),""NO TIENE PROCESO""))*D74"),5.0200000000000005) -> 5.02 | I74: =J74+K74 -> 2 | J74: =SUMIFS('👷horas'!$J:$J,'👷horas'!$D:$D,A74,'👷horas'!$E:$E,B74,'👷horas'!$F:$F,F74,'👷horas'!$G:$G,G74) -> 2 | K74: =SUMIFS('👷horas'!$K:$K,'👷horas'!$D:$D,A74,'👷horas'!$E:$E,B74,'👷horas'!$F:$F,F74,'👷horas'!$G:$G,G74) -> 0 | L74: =I74/D74 -> 0.079681275 | M74: =IF(P74="TERMINADO",0,H74-(J74+K74)) -> 0 | N74: =1-(I74/H74) -> 0.60159363 | O74: =IF(NOT(ISNUMBER(H74)),0,IF(P74="Terminado",1,IF(J74=0,0,MIN(1,J74/H74)))) -> 1 | P74: Terminado | Q74: =IF(COUNTIFS(A:A,A74,P:P,"Terminado")=COUNTIF(A:A,A74),"Terminado",IF(COUNTIFS(A:A,A74,P:P,"En proceso")>0,"En proceso","Pendiente")) -> Terminado | R74: =IFERROR(__xludf.DUMMYFUNCTION("SPARKLINE(O74,{""charttype"",""bar"";""max"",1;""color1"",IF(P74=""Terminado"",""#4CAF50"",IF(O74>=0.5,""#FFA500"",""#F44336""))})"),"")
A75: Inventario | B75: Gracos | C75: BASTIDOR DE TABICA CURVA 150X12 | D75: 25.1 | E75: 46113 | F75: =IFERROR(__xludf.DUMMYFUNCTION("""COMPUTED_VALUE"""),"Fabricación") -> Fabricación | G75: =IFERROR(__xludf.DUMMYFUNCTION("""COMPUTED_VALUE"""),"Embalaje/carga/descarga material") -> Embalaje/carga/descarga material | H75: =IFERROR(__xludf.DUMMYFUNCTION("(IFERROR(FILTER(BBDD!$J:$J,BBDD!$G:$G=C75,BBDD!$H:$H=F75,BBDD!$I:$I=G75),""NO TIENE PROCESO""))*D75"),3.765) -> 3.765 | I75: =J75+K75 -> 3.5 | J75: =SUMIFS('👷horas'!$J:$J,'👷horas'!$D:$D,A75,'👷horas'!$E:$E,B75,'👷horas'!$F:$F,F75,'👷horas'!$G:$G,G75) -> 3.5 | K75: =SUMIFS('👷horas'!$K:$K,'👷horas'!$D:$D,A75,'👷horas'!$E:$E,B75,'👷horas'!$F:$F,F75,'👷horas'!$G:$G,G75) -> 0 | L75: =I75/D75 -> 0.13944223 | M75: =IF(P75="TERMINADO",0,H75-(J75+K75)) -> 0 | N75: =1-(I75/H75) -> 0.070385126 | O75: =IF(NOT(ISNUMBER(H75)),0,IF(P75="Terminado",1,IF(J75=0,0,MIN(1,J75/H75)))) -> 1 | P75: Terminado | Q75: =IF(COUNTIFS(A:A,A75,P:P,"Terminado")=COUNTIF(A:A,A75),"Terminado",IF(COUNTIFS(A:A,A75,P:P,"En proceso")>0,"En proceso","Pendiente")) -> Terminado | R75: =IFERROR(__xludf.DUMMYFUNCTION("SPARKLINE(O75,{""charttype"",""bar"";""max"",1;""color1"",IF(P75=""Terminado"",""#4CAF50"",IF(O75>=0.5,""#FFA500"",""#F44336""))})"),"")
A76: Inventario | B76: Gracos | C76: BASTIDOR DE TABICA CURVA 150X12 | D76: 25.1 | E76: 46113 | F76: =IFERROR(__xludf.DUMMYFUNCTION("""COMPUTED_VALUE"""),"Pintura") -> Pintura | G76: =IFERROR(__xludf.DUMMYFUNCTION("""COMPUTED_VALUE"""),"Lijado y/o Masillado") -> Lijado y/o Masillado | H76: =IFERROR(__xludf.DUMMYFUNCTION("(IFERROR(FILTER(BBDD!$J:$J,BBDD!$G:$G=C76,BBDD!$H:$H=F76,BBDD!$I:$I=G76),""NO TIENE PROCESO""))*D76"),15.06) -> 15.06 | I76: =J76+K76 -> 29 | J76: =SUMIFS('👷horas'!$J:$J,'👷horas'!$D:$D,A76,'👷horas'!$E:$E,B76,'👷horas'!$F:$F,F76,'👷horas'!$G:$G,G76) -> 25.75 | K76: =SUMIFS('👷horas'!$K:$K,'👷horas'!$D:$D,A76,'👷horas'!$E:$E,B76,'👷horas'!$F:$F,F76,'👷horas'!$G:$G,G76) -> 3.25 | L76: =I76/D76 -> 1.1553785 | M76: =IF(P76="TERMINADO",0,H76-(J76+K76)) -> 0 | N76: =1-(I76/H76) -> -0.92563081 | O76: =IF(NOT(ISNUMBER(H76)),0,IF(P76="Terminado",1,IF(J76=0,0,MIN(1,J76/H76)))) -> 1 | P76: Terminado | Q76: =IF(COUNTIFS(A:A,A76,P:P,"Terminado")=COUNTIF(A:A,A76),"Terminado",IF(COUNTIFS(A:A,A76,P:P,"En proceso")>0,"En proceso","Pendiente")) -> Terminado | R76: =IFERROR(__xludf.DUMMYFUNCTION("SPARKLINE(O76,{""charttype"",""bar"";""max"",1;""color1"",IF(P76=""Terminado"",""#4CAF50"",IF(O76>=0.5,""#FFA500"",""#F44336""))})"),"")
A77: Inventario | B77: Gracos | C77: BASTIDOR DE TABICA CURVA 150X12 | D77: 25.1 | E77: 46113 | F77: =IFERROR(__xludf.DUMMYFUNCTION("""COMPUTED_VALUE"""),"Pintura") -> Pintura | G77: =IFERROR(__xludf.DUMMYFUNCTION("""COMPUTED_VALUE"""),"Imprimación/Pintura") -> Imprimación/Pintura | H77: =IFERROR(__xludf.DUMMYFUNCTION("(IFERROR(FILTER(BBDD!$J:$J,BBDD!$G:$G=C77,BBDD!$H:$H=F77,BBDD!$I:$I=G77),""NO TIENE PROCESO""))*D77"),10.040000000000001) -> 10.04 | I77: =J77+K77 -> 7 | J77: =SUMIFS('👷horas'!$J:$J,'👷horas'!$D:$D,A77,'👷horas'!$E:$E,B77,'👷horas'!$F:$F,F77,'👷horas'!$G:$G,G77) -> 4 | K77: =SUMIFS('👷horas'!$K:$K,'👷horas'!$D:$D,A77,'👷horas'!$E:$E,B77,'👷horas'!$F:$F,F77,'👷horas'!$G:$G,G77) -> 3 | L77: =I77/D77 -> 0.27888446 | M77: =IF(P77="TERMINADO",0,H77-(J77+K77)) -> 0 | N77: =1-(I77/H77) -> 0.30278884 | O77: =IF(NOT(ISNUMBER(H77)),0,IF(P77="Terminado",1,IF(J77=0,0,MIN(1,J77/H77)))) -> 1 | P77: Terminado | Q77: =IF(COUNTIFS(A:A,A77,P:P,"Terminado")=COUNTIF(A:A,A77),"Terminado",IF(COUNTIFS(A:A,A77,P:P,"En proceso")>0,"En proceso","Pendiente")) -> Terminado | R77: =IFERROR(__xludf.DUMMYFUNCTION("SPARKLINE(O77,{""charttype"",""bar"";""max"",1;""color1"",IF(P77=""Terminado"",""#4CAF50"",IF(O77>=0.5,""#FFA500"",""#F44336""))})"),"")
A78: Druni CC Safari | B78: Gracos | C78: BASTIDOR DE TABICA CURVA 150X12 | D78: 9.85 | E78: 46113 | F78: =IFERROR(__xludf.DUMMYFUNCTION("FILTER(BBDD!H:H,BBDD!G:G=C78)"),"CNC") -> CNC | G78: =IFERROR(__xludf.DUMMYFUNCTION("FILTER(BBDD!I:I,BBDD!G:G=C78)"),"CNC") -> CNC | H78: =IFERROR(__xludf.DUMMYFUNCTION("(IFERROR(FILTER(BBDD!$J:$J,BBDD!$G:$G=C78,BBDD!$H:$H=F78,BBDD!$I:$I=G78),""NO TIENE PROCESO""))*D78"),1.97) -> 1.97 | I78: =J78+K78 -> 1.0933333 | J78: =SUMIFS('👷horas'!$J:$J,'👷horas'!$D:$D,A78,'👷horas'!$E:$E,B78,'👷horas'!$F:$F,F78,'👷horas'!$G:$G,G78) -> 1.0933333 | K78: =SUMIFS('👷horas'!$K:$K,'👷horas'!$D:$D,A78,'👷horas'!$E:$E,B78,'👷horas'!$F:$F,F78,'👷horas'!$G:$G,G78) -> 0 | L78: =I78/D78 -> 0.11099831 | M78: =IF(P78="TERMINADO",0,H78-(J78+K78)) -> 0 | N78: =1-(I78/H78) -> 0.44500846 | O78: =IF(NOT(ISNUMBER(H78)),0,IF(P78="Terminado",1,IF(J78=0,0,MIN(1,J78/H78)))) -> 1 | P78: Terminado | Q78: =IF(COUNTIFS(A:A,A78,P:P,"Terminado")=COUNTIF(A:A,A78),"Terminado",IF(COUNTIFS(A:A,A78,P:P,"En proceso")>0,"En proceso","Pendiente")) -> Terminado | R78: =IFERROR(__xludf.DUMMYFUNCTION("SPARKLINE(O78,{""charttype"",""bar"";""max"",1;""color1"",IF(P78=""Terminado"",""#4CAF50"",IF(O78>=0.5,""#FFA500"",""#F44336""))})"),"")
A79: Druni CC Safari | B79: Gracos | C79: BASTIDOR DE TABICA CURVA 150X12 | D79: 9.85 | E79: 46113 | F79: =IFERROR(__xludf.DUMMYFUNCTION("""COMPUTED_VALUE"""),"Fabricación") -> Fabricación | G79: =IFERROR(__xludf.DUMMYFUNCTION("""COMPUTED_VALUE"""),"Ensamblaje") -> Ensamblaje | H79: =IFERROR(__xludf.DUMMYFUNCTION("(IFERROR(FILTER(BBDD!$J:$J,BBDD!$G:$G=C79,BBDD!$H:$H=F79,BBDD!$I:$I=G79),""NO TIENE PROCESO""))*D79"),7.7815) -> 7.7815 | I79: =J79+K79 -> 7 | J79: =SUMIFS('👷horas'!$J:$J,'👷horas'!$D:$D,A79,'👷horas'!$E:$E,B79,'👷horas'!$F:$F,F79,'👷horas'!$G:$G,G79) -> 5 | K79: =SUMIFS('👷horas'!$K:$K,'👷horas'!$D:$D,A79,'👷horas'!$E:$E,B79,'👷horas'!$F:$F,F79,'👷horas'!$G:$G,G79) -> 2 | L79: =I79/D79 -> 0.7106599 | M79: =IF(P79="TERMINADO",0,H79-(J79+K79)) -> 0 | N79: =1-(I79/H79) -> 0.10043051 | O79: =IF(NOT(ISNUMBER(H79)),0,IF(P79="Terminado",1,IF(J79=0,0,MIN(1,J79/H79)))) -> 1 | P79: Terminado | Q79: =IF(COUNTIFS(A:A,A79,P:P,"Terminado")=COUNTIF(A:A,A79),"Terminado",IF(COUNTIFS(A:A,A79,P:P,"En proceso")>0,"En proceso","Pendiente")) -> Terminado | R79: =IFERROR(__xludf.DUMMYFUNCTION("SPARKLINE(O79,{""charttype"",""bar"";""max"",1;""color1"",IF(P79=""Terminado"",""#4CAF50"",IF(O79>=0.5,""#FFA500"",""#F44336""))})"),"")
A80: Druni CC Safari | B80: Gracos | C80: BASTIDOR DE TABICA CURVA 150X12 | D80: 9.85 | E80: 46113 | F80: =IFERROR(__xludf.DUMMYFUNCTION("""COMPUTED_VALUE"""),"Fabricación") -> Fabricación | G80: =IFERROR(__xludf.DUMMYFUNCTION("""COMPUTED_VALUE"""),"Colocación de perfiles") -> Colocación de perfiles | H80: =IFERROR(__xludf.DUMMYFUNCTION("(IFERROR(FILTER(BBDD!$J:$J,BBDD!$G:$G=C80,BBDD!$H:$H=F80,BBDD!$I:$I=G80),""NO TIENE PROCESO""))*D80"),1.97) -> 1.97 | I80: =J80+K80 -> 2.5 | J80: =SUMIFS('👷horas'!$J:$J,'👷horas'!$D:$D,A80,'👷horas'!$E:$E,B80,'👷horas'!$F:$F,F80,'👷horas'!$G:$G,G80) -> 2.5 | K80: =SUMIFS('👷horas'!$K:$K,'👷horas'!$D:$D,A80,'👷horas'!$E:$E,B80,'👷horas'!$F:$F,F80,'👷horas'!$G:$G,G80) -> 0 | L80: =I80/D80 -> 0.25380711 | M80: =IF(P80="TERMINADO",0,H80-(J80+K80)) -> 0 | N80: =1-(I80/H80) -> -0.26903553 | O80: =IF(NOT(ISNUMBER(H80)),0,IF(P80="Terminado",1,IF(J80=0,0,MIN(1,J80/H80)))) -> 1 | P80: Terminado | Q80: =IF(COUNTIFS(A:A,A80,P:P,"Terminado")=COUNTIF(A:A,A80),"Terminado",IF(COUNTIFS(A:A,A80,P:P,"En proceso")>0,"En proceso","Pendiente")) -> Terminado | R80: =IFERROR(__xludf.DUMMYFUNCTION("SPARKLINE(O80,{""charttype"",""bar"";""max"",1;""color1"",IF(P80=""Terminado"",""#4CAF50"",IF(O80>=0.5,""#FFA500"",""#F44336""))})"),"")
A81: Druni CC Safari | B81: Gracos | C81: BASTIDOR DE TABICA CURVA 150X12 | D81: 9.85 | E81: 46113 | F81: =IFERROR(__xludf.DUMMYFUNCTION("""COMPUTED_VALUE"""),"Fabricación") -> Fabricación | G81: =IFERROR(__xludf.DUMMYFUNCTION("""COMPUTED_VALUE"""),"Embalaje/carga/descarga material") -> Embalaje/carga/descarga material | H81: =IFERROR(__xludf.DUMMYFUNCTION("(IFERROR(FILTER(BBDD!$J:$J,BBDD!$G:$G=C81,BBDD!$H:$H=F81,BBDD!$I:$I=G81),""NO TIENE PROCESO""))*D81"),1.4774999999999998) -> 1.4775 | I81: =J81+K81 -> 1 | J81: =SUMIFS('👷horas'!$J:$J,'👷horas'!$D:$D,A81,'👷horas'!$E:$E,B81,'👷horas'!$F:$F,F81,'👷horas'!$G:$G,G81) -> 1 | K81: =SUMIFS('👷horas'!$K:$K,'👷horas'!$D:$D,A81,'👷horas'!$E:$E,B81,'👷horas'!$F:$F,F81,'👷horas'!$G:$G,G81) -> 0 | L81: =I81/D81 -> 0.10152284 | M81: =IF(P81="TERMINADO",0,H81-(J81+K81)) -> 0 | N81: =1-(I81/H81) -> 0.32318105 | O81: =IF(NOT(ISNUMBER(H81)),0,IF(P81="Terminado",1,IF(J81=0,0,MIN(1,J81/H81)))) -> 1 | P81: Terminado | Q81: =IF(COUNTIFS(A:A,A81,P:P,"Terminado")=COUNTIF(A:A,A81),"Terminado",IF(COUNTIFS(A:A,A81,P:P,"En proceso")>0,"En proceso","Pendiente")) -> Terminado | R81: =IFERROR(__xludf.DUMMYFUNCTION("SPARKLINE(O81,{""charttype"",""bar"";""max"",1;""color1"",IF(P81=""Terminado"",""#4CAF50"",IF(O81>=0.5,""#FFA500"",""#F44336""))})"),"")
A82: Druni CC Safari | B82: Gracos | C82: BASTIDOR DE TABICA CURVA 150X12 | D82: 9.85 | E82: 46113 | F82: =IFERROR(__xludf.DUMMYFUNCTION("""COMPUTED_VALUE"""),"Pintura") -> Pintura | G82: =IFERROR(__xludf.DUMMYFUNCTION("""COMPUTED_VALUE"""),"Lijado y/o Masillado") -> Lijado y/o Masillado | H82: =IFERROR(__xludf.DUMMYFUNCTION("(IFERROR(FILTER(BBDD!$J:$J,BBDD!$G:$G=C82,BBDD!$H:$H=F82,BBDD!$I:$I=G82),""NO TIENE PROCESO""))*D82"),5.909999999999999) -> 5.91 | I82: =J82+K82 -> 5 | J82: =SUMIFS('👷horas'!$J:$J,'👷horas'!$D:$D,A82,'👷horas'!$E:$E,B82,'👷horas'!$F:$F,F82,'👷horas'!$G:$G,G82) -> 3.5 | K82: =SUMIFS('👷horas'!$K:$K,'👷horas'!$D:$D,A82,'👷horas'!$E:$E,B82,'👷horas'!$F:$F,F82,'👷horas'!$G:$G,G82) -> 1.5 | L82: =I82/D82 -> 0.50761421 | M82: =IF(P82="TERMINADO",0,H82-(J82+K82)) -> 0 | N82: =1-(I82/H82) -> 0.15397631 | O82: =IF(NOT(ISNUMBER(H82)),0,IF(P82="Terminado",1,IF(J82=0,0,MIN(1,J82/H82)))) -> 1 | P82: Terminado | Q82: =IF(COUNTIFS(A:A,A82,P:P,"Terminado")=COUNTIF(A:A,A82),"Terminado",IF(COUNTIFS(A:A,A82,P:P,"En proceso")>0,"En proceso","Pendiente")) -> Terminado | R82: =IFERROR(__xludf.DUMMYFUNCTION("SPARKLINE(O82,{""charttype"",""bar"";""max"",1;""color1"",IF(P82=""Terminado"",""#4CAF50"",IF(O82>=0.5,""#FFA500"",""#F44336""))})"),"")
A83: Druni CC Safari | B83: Gracos | C83: BASTIDOR DE TABICA CURVA 150X12 | D83: 9.85 | E83: 46113 | F83: =IFERROR(__xludf.DUMMYFUNCTION("""COMPUTED_VALUE"""),"Pintura") -> Pintura | G83: =IFERROR(__xludf.DUMMYFUNCTION("""COMPUTED_VALUE"""),"Imprimación/Pintura") -> Imprimación/Pintura | H83: =IFERROR(__xludf.DUMMYFUNCTION("(IFERROR(FILTER(BBDD!$J:$J,BBDD!$G:$G=C83,BBDD!$H:$H=F83,BBDD!$I:$I=G83),""NO TIENE PROCESO""))*D83"),3.94) -> 3.94 | I83: =J83+K83 -> 3.647 | J83: =SUMIFS('👷horas'!$J:$J,'👷horas'!$D:$D,A83,'👷horas'!$E:$E,B83,'👷horas'!$F:$F,F83,'👷horas'!$G:$G,G83) -> 3.647 | K83: =SUMIFS('👷horas'!$K:$K,'👷horas'!$D:$D,A83,'👷horas'!$E:$E,B83,'👷horas'!$F:$F,F83,'👷horas'!$G:$G,G83) -> 0 | L83: =I83/D83 -> 0.37025381 | M83: =IF(P83="TERMINADO",0,H83-(J83+K83)) -> 0 | N83: =1-(I83/H83) -> 0.074365482 | O83: =IF(NOT(ISNUMBER(H83)),0,IF(P83="Terminado",1,IF(J83=0,0,MIN(1,J83/H83)))) -> 1 | P83: Terminado | Q83: =IF(COUNTIFS(A:A,A83,P:P,"Terminado")=COUNTIF(A:A,A83),"Terminado",IF(COUNTIFS(A:A,A83,P:P,"En proceso")>0,"En proceso","Pendiente")) -> Terminado | R83: =IFERROR(__xludf.DUMMYFUNCTION("SPARKLINE(O83,{""charttype"",""bar"";""max"",1;""color1"",IF(P83=""Terminado"",""#4CAF50"",IF(O83>=0.5,""#FFA500"",""#F44336""))})"),"")
A84: Druni CC Safari | B84: Selcos metacrilato | C84: BASTIDOR DE METACRILATO RECTO | D84: 46.8 | E84: 46113 | F84: =IFERROR(__xludf.DUMMYFUNCTION("FILTER(BBDD!H:H,BBDD!G:G=C84)"),"Fabricación") -> Fabricación | G84: =IFERROR(__xludf.DUMMYFUNCTION("FILTER(BBDD!I:I,BBDD!G:G=C84)"),"Ensamblaje") -> Ensamblaje | H84: =IFERROR(__xludf.DUMMYFUNCTION("(IFERROR(FILTER(BBDD!$J:$J,BBDD!$G:$G=C84,BBDD!$H:$H=F84,BBDD!$I:$I=G84),""NO TIENE PROCESO""))*D84"),42.11999999999999) -> 42.12 | I84: =J84+K84 -> 42.77 | J84: =SUMIFS('👷horas'!$J:$J,'👷horas'!$D:$D,A84,'👷horas'!$E:$E,B84,'👷horas'!$F:$F,F84,'👷horas'!$G:$G,G84) -> 31.77 | K84: =SUMIFS('👷horas'!$K:$K,'👷horas'!$D:$D,A84,'👷horas'!$E:$E,B84,'👷horas'!$F:$F,F84,'👷horas'!$G:$G,G84) -> 11 | L84: =I84/D84 -> 0.91388889 | M84: =IF(P84="TERMINADO",0,H84-(J84+K84)) -> 0 | N84: =1-(I84/H84) -> -0.015432099 | O84: =IF(NOT(ISNUMBER(H84)),0,IF(P84="Terminado",1,IF(J84=0,0,MIN(1,J84/H84)))) -> 1 | P84: Terminado | Q84: =IF(COUNTIFS(A:A,A84,P:P,"Terminado")=COUNTIF(A:A,A84),"Terminado",IF(COUNTIFS(A:A,A84,P:P,"En proceso")>0,"En proceso","Pendiente")) -> Terminado | R84: =IFERROR(__xludf.DUMMYFUNCTION("SPARKLINE(O84,{""charttype"",""bar"";""max"",1;""color1"",IF(P84=""Terminado"",""#4CAF50"",IF(O84>=0.5,""#FFA500"",""#F44336""))})"),"")
A85: Druni CC Safari | B85: Selcos metacrilato | C85: BASTIDOR DE METACRILATO RECTO | D85: 46.8 | E85: 46113 | F85: =IFERROR(__xludf.DUMMYFUNCTION("""COMPUTED_VALUE"""),"Fabricación") -> Fabricación | G85: =IFERROR(__xludf.DUMMYFUNCTION("""COMPUTED_VALUE"""),"Embalaje/carga/descarga material") -> Embalaje/carga/descarga material | H85: =IFERROR(__xludf.DUMMYFUNCTION("(IFERROR(FILTER(BBDD!$J:$J,BBDD!$G:$G=C85,BBDD!$H:$H=F85,BBDD!$I:$I=G85),""NO TIENE PROCESO""))*D85"),7.956) -> 7.956 | I85: =J85+K85 -> 8.0735294 | J85: =SUMIFS('👷horas'!$J:$J,'👷horas'!$D:$D,A85,'👷horas'!$E:$E,B85,'👷horas'!$F:$F,F85,'👷horas'!$G:$G,G85) -> 7.5 | K85: =SUMIFS('👷horas'!$K:$K,'👷horas'!$D:$D,A85,'👷horas'!$E:$E,B85,'👷horas'!$F:$F,F85,'👷horas'!$G:$G,G85) -> 0.57352941 | L85: =I85/D85 -> 0.17251131 | M85: =IF(P85="TERMINADO",0,H85-(J85+K85)) -> 0 | N85: =1-(I85/H85) -> -0.014772425 | O85: =IF(NOT(ISNUMBER(H85)),0,IF(P85="Terminado",1,IF(J85=0,0,MIN(1,J85/H85)))) -> 1 | P85: Terminado | Q85: =IF(COUNTIFS(A:A,A85,P:P,"Terminado")=COUNTIF(A:A,A85),"Terminado",IF(COUNTIFS(A:A,A85,P:P,"En proceso")>0,"En proceso","Pendiente")) -> Terminado | R85: =IFERROR(__xludf.DUMMYFUNCTION("SPARKLINE(O85,{""charttype"",""bar"";""max"",1;""color1"",IF(P85=""Terminado"",""#4CAF50"",IF(O85>=0.5,""#FFA500"",""#F44336""))})"),"")
A86: Druni CC Safari | B86: Cruz | C86: BASTIDOR DE TABICA 150X12 | D86: =9.84*2 -> 19.68 | E86: 46113 | F86: =IFERROR(__xludf.DUMMYFUNCTION("FILTER(BBDD!H:H,BBDD!G:G=C86)"),"CNC") -> CNC | G86: =IFERROR(__xludf.DUMMYFUNCTION("FILTER(BBDD!I:I,BBDD!G:G=C86)"),"CNC") -> CNC | H86: =IFERROR(__xludf.DUMMYFUNCTION("(IFERROR(FILTER(BBDD!$J:$J,BBDD!$G:$G=C86,BBDD!$H:$H=F86,BBDD!$I:$I=G86),""NO TIENE PROCESO""))*D86"),3.936) -> 3.936 | I86: =J86+K86 -> 0.85 | J86: =SUMIFS('👷horas'!$J:$J,'👷horas'!$D:$D,A86,'👷horas'!$E:$E,B86,'👷horas'!$F:$F,F86,'👷horas'!$G:$G,G86) -> 0.85 | K86: =SUMIFS('👷horas'!$K:$K,'👷horas'!$D:$D,A86,'👷horas'!$E:$E,B86,'👷horas'!$F:$F,F86,'👷horas'!$G:$G,G86) -> 0 | L86: =I86/D86 -> 0.043191057 | M86: =IF(P86="TERMINADO",0,H86-(J86+K86)) -> 0 | N86: =1-(I86/H86) -> 0.78404472 | O86: =IF(NOT(ISNUMBER(H86)),0,IF(P86="Terminado",1,IF(J86=0,0,MIN(1,J86/H86)))) -> 1 | P86: Terminado | Q86: =IF(COUNTIFS(A:A,A86,P:P,"Terminado")=COUNTIF(A:A,A86),"Terminado",IF(COUNTIFS(A:A,A86,P:P,"En proceso")>0,"En proceso","Pendiente")) -> Terminado | R86: =IFERROR(__xludf.DUMMYFUNCTION("SPARKLINE(O86,{""charttype"",""bar"";""max"",1;""color1"",IF(P86=""Terminado"",""#4CAF50"",IF(O86>=0.5,""#FFA500"",""#F44336""))})"),"")
A87: Druni CC Safari | B87: Cruz | C87: BASTIDOR DE TABICA 150X12 | D87: =9.84*2 -> 19.68 | E87: 46113 | F87: =IFERROR(__xludf.DUMMYFUNCTION("""COMPUTED_VALUE"""),"Fabricación") -> Fabricación | G87: =IFERROR(__xludf.DUMMYFUNCTION("""COMPUTED_VALUE"""),"Ensamblaje") -> Ensamblaje | H87: =IFERROR(__xludf.DUMMYFUNCTION("(IFERROR(FILTER(BBDD!$J:$J,BBDD!$G:$G=C87,BBDD!$H:$H=F87,BBDD!$I:$I=G87),""NO TIENE PROCESO""))*D87"),12.2016) -> 12.2016 | I87: =J87+K87 -> 9.58 | J87: =SUMIFS('👷horas'!$J:$J,'👷horas'!$D:$D,A87,'👷horas'!$E:$E,B87,'👷horas'!$F:$F,F87,'👷horas'!$G:$G,G87) -> 3.58 | K87: =SUMIFS('👷horas'!$K:$K,'👷horas'!$D:$D,A87,'👷horas'!$E:$E,B87,'👷horas'!$F:$F,F87,'👷horas'!$G:$G,G87) -> 6 | L87: =I87/D87 -> 0.48678862 | M87: =IF(P87="TERMINADO",0,H87-(J87+K87)) -> 0 | N87: =1-(I87/H87) -> 0.21485707 | O87: =IF(NOT(ISNUMBER(H87)),0,IF(P87="Terminado",1,IF(J87=0,0,MIN(1,J87/H87)))) -> 1 | P87: Terminado | Q87: =IF(COUNTIFS(A:A,A87,P:P,"Terminado")=COUNTIF(A:A,A87),"Terminado",IF(COUNTIFS(A:A,A87,P:P,"En proceso")>0,"En proceso","Pendiente")) -> Terminado | R87: =IFERROR(__xludf.DUMMYFUNCTION("SPARKLINE(O87,{""charttype"",""bar"";""max"",1;""color1"",IF(P87=""Terminado"",""#4CAF50"",IF(O87>=0.5,""#FFA500"",""#F44336""))})"),"")
A88: Druni CC Safari | B88: Cruz | C88: BASTIDOR DE TABICA 150X12 | D88: =9.84*2 -> 19.68 | E88: 46113 | F88: =IFERROR(__xludf.DUMMYFUNCTION("""COMPUTED_VALUE"""),"Fabricación") -> Fabricación | G88: =IFERROR(__xludf.DUMMYFUNCTION("""COMPUTED_VALUE"""),"Colocación de perfiles") -> Colocación de perfiles | H88: =IFERROR(__xludf.DUMMYFUNCTION("(IFERROR(FILTER(BBDD!$J:$J,BBDD!$G:$G=C88,BBDD!$H:$H=F88,BBDD!$I:$I=G88),""NO TIENE PROCESO""))*D88"),3.936) -> 3.936 | I88: =J88+K88 -> 3 | J88: =SUMIFS('👷horas'!$J:$J,'👷horas'!$D:$D,A88,'👷horas'!$E:$E,B88,'👷horas'!$F:$F,F88,'👷horas'!$G:$G,G88) -> 2 | K88: =SUMIFS('👷horas'!$K:$K,'👷horas'!$D:$D,A88,'👷horas'!$E:$E,B88,'👷horas'!$F:$F,F88,'👷horas'!$G:$G,G88) -> 1 | L88: =I88/D88 -> 0.15243902 | M88: =IF(P88="TERMINADO",0,H88-(J88+K88)) -> 0 | N88: =1-(I88/H88) -> 0.23780488 | O88: =IF(NOT(ISNUMBER(H88)),0,IF(P88="Terminado",1,IF(J88=0,0,MIN(1,J88/H88)))) -> 1 | P88: Terminado | Q88: =IF(COUNTIFS(A:A,A88,P:P,"Terminado")=COUNTIF(A:A,A88),"Terminado",IF(COUNTIFS(A:A,A88,P:P,"En proceso")>0,"En proceso","Pendiente")) -> Terminado | R88: =IFERROR(__xludf.DUMMYFUNCTION("SPARKLINE(O88,{""charttype"",""bar"";""max"",1;""color1"",IF(P88=""Terminado"",""#4CAF50"",IF(O88>=0.5,""#FFA500"",""#F44336""))})"),"")
A89: Druni CC Safari | B89: Cruz | C89: BASTIDOR DE TABICA 150X12 | D89: =9.84*2 -> 19.68 | E89: 46113 | F89: =IFERROR(__xludf.DUMMYFUNCTION("""COMPUTED_VALUE"""),"Fabricación") -> Fabricación | G89: =IFERROR(__xludf.DUMMYFUNCTION("""COMPUTED_VALUE"""),"Embalaje/carga/descarga material") -> Embalaje/carga/descarga material | H89: =IFERROR(__xludf.DUMMYFUNCTION("(IFERROR(FILTER(BBDD!$J:$J,BBDD!$G:$G=C89,BBDD!$H:$H=F89,BBDD!$I:$I=G89),""NO TIENE PROCESO""))*D89"),2.952) -> 2.952 | I89: =J89+K89 -> 1.1764706 | J89: =SUMIFS('👷horas'!$J:$J,'👷horas'!$D:$D,A89,'👷horas'!$E:$E,B89,'👷horas'!$F:$F,F89,'👷horas'!$G:$G,G89) -> 1 | K89: =SUMIFS('👷horas'!$K:$K,'👷horas'!$D:$D,A89,'👷horas'!$E:$E,B89,'👷horas'!$F:$F,F89,'👷horas'!$G:$G,G89) -> 0.17647059 | L89: =I89/D89 -> 0.05978001 | M89: =IF(P89="TERMINADO",0,H89-(J89+K89)) -> 0 | N89: =1-(I89/H89) -> 0.6014666 | O89: =IF(NOT(ISNUMBER(H89)),0,IF(P89="Terminado",1,IF(J89=0,0,MIN(1,J89/H89)))) -> 1 | P89: Terminado | Q89: =IF(COUNTIFS(A:A,A89,P:P,"Terminado")=COUNTIF(A:A,A89),"Terminado",IF(COUNTIFS(A:A,A89,P:P,"En proceso")>0,"En proceso","Pendiente")) -> Terminado | R89: =IFERROR(__xludf.DUMMYFUNCTION("SPARKLINE(O89,{""charttype"",""bar"";""max"",1;""color1"",IF(P89=""Terminado"",""#4CAF50"",IF(O89>=0.5,""#FFA500"",""#F44336""))})"),"")
A90: Druni CC Safari | B90: Cruz | C90: BASTIDOR DE TABICA 150X12 | D90: =9.84*2 -> 19.68 | E90: 46113 | F90: =IFERROR(__xludf.DUMMYFUNCTION("""COMPUTED_VALUE"""),"Pintura") -> Pintura | G90: =IFERROR(__xludf.DUMMYFUNCTION("""COMPUTED_VALUE"""),"Lijado y/o Masillado") -> Lijado y/o Masillado | H90: =IFERROR(__xludf.DUMMYFUNCTION("(IFERROR(FILTER(BBDD!$J:$J,BBDD!$G:$G=C90,BBDD!$H:$H=F90,BBDD!$I:$I=G90),""NO TIENE PROCESO""))*D90"),9.84) -> 9.84 | I90: =J90+K90 -> 12.0579 | J90: =SUMIFS('👷horas'!$J:$J,'👷horas'!$D:$D,A90,'👷horas'!$E:$E,B90,'👷horas'!$F:$F,F90,'👷horas'!$G:$G,G90) -> 8.0579 | K90: =SUMIFS('👷horas'!$K:$K,'👷horas'!$D:$D,A90,'👷horas'!$E:$E,B90,'👷horas'!$F:$F,F90,'👷horas'!$G:$G,G90) -> 4 | L90: =I90/D90 -> 0.61269817 | M90: =IF(P90="TERMINADO",0,H90-(J90+K90)) -> 0 | N90: =1-(I90/H90) -> -0.22539634 | O90: =IF(NOT(ISNUMBER(H90)),0,IF(P90="Terminado",1,IF(J90=0,0,MIN(1,J90/H90)))) -> 1 | P90: Terminado | Q90: =IF(COUNTIFS(A:A,A90,P:P,"Terminado")=COUNTIF(A:A,A90),"Terminado",IF(COUNTIFS(A:A,A90,P:P,"En proceso")>0,"En proceso","Pendiente")) -> Terminado | R90: =IFERROR(__xludf.DUMMYFUNCTION("SPARKLINE(O90,{""charttype"",""bar"";""max"",1;""color1"",IF(P90=""Terminado"",""#4CAF50"",IF(O90>=0.5,""#FFA500"",""#F44336""))})"),"")
A91: Druni CC Safari | B91: Cruz | C91: BASTIDOR DE TABICA 150X12 | D91: =9.84*2 -> 19.68 | E91: 46113 | F91: =IFERROR(__xludf.DUMMYFUNCTION("""COMPUTED_VALUE"""),"Pintura") -> Pintura | G91: =IFERROR(__xludf.DUMMYFUNCTION("""COMPUTED_VALUE"""),"Imprimación/Pintura") -> Imprimación/Pintura | H91: =IFERROR(__xludf.DUMMYFUNCTION("(IFERROR(FILTER(BBDD!$J:$J,BBDD!$G:$G=C91,BBDD!$H:$H=F91,BBDD!$I:$I=G91),""NO TIENE PROCESO""))*D91"),7.872) -> 7.872 | I91: =J91+K91 -> 6.295 | J91: =SUMIFS('👷horas'!$J:$J,'👷horas'!$D:$D,A91,'👷horas'!$E:$E,B91,'👷horas'!$F:$F,F91,'👷horas'!$G:$G,G91) -> 6.295 | K91: =SUMIFS('👷horas'!$K:$K,'👷horas'!$D:$D,A91,'👷horas'!$E:$E,B91,'👷horas'!$F:$F,F91,'👷horas'!$G:$G,G91) -> 0 | L91: =I91/D91 -> 0.31986789 | M91: =IF(P91="TERMINADO",0,H91-(J91+K91)) -> 0 | N91: =1-(I91/H91) -> 0.20033028 | O91: =IF(NOT(ISNUMBER(H91)),0,IF(P91="Terminado",1,IF(J91=0,0,MIN(1,J91/H91)))) -> 1 | P91: Terminado | Q91: =IF(COUNTIFS(A:A,A91,P:P,"Terminado")=COUNTIF(A:A,A91),"Terminado",IF(COUNTIFS(A:A,A91,P:P,"En proceso")>0,"En proceso","Pendiente")) -> Terminado | R91: =IFERROR(__xludf.DUMMYFUNCTION("SPARKLINE(O91,{""charttype"",""bar"";""max"",1;""color1"",IF(P91=""Terminado"",""#4CAF50"",IF(O91>=0.5,""#FFA500"",""#F44336""))})"),"")
A92: Druni CC Safari | B92: Parafarmacia | C92: BASTIDOR DE TABICA CURVA 150X12 | D92: 33.04 | E92: 46113 | F92: =IFERROR(__xludf.DUMMYFUNCTION("FILTER(BBDD!H:H,BBDD!G:G=C92)"),"CNC") -> CNC | G92: =IFERROR(__xludf.DUMMYFUNCTION("FILTER(BBDD!I:I,BBDD!G:G=C92)"),"CNC") -> CNC | H92: =IFERROR(__xludf.DUMMYFUNCTION("(IFERROR(FILTER(BBDD!$J:$J,BBDD!$G:$G=C92,BBDD!$H:$H=F92,BBDD!$I:$I=G92),""NO TIENE PROCESO""))*D92"),6.6080000000000005) -> 6.608 | I92: =J92+K92 -> 2 | J92: =SUMIFS('👷horas'!$J:$J,'👷horas'!$D:$D,A92,'👷horas'!$E:$E,B92,'👷horas'!$F:$F,F92,'👷horas'!$G:$G,G92) -> 2 | K92: =SUMIFS('👷horas'!$K:$K,'👷horas'!$D:$D,A92,'👷horas'!$E:$E,B92,'👷horas'!$F:$F,F92,'👷horas'!$G:$G,G92) -> 0 | L92: =I92/D92 -> 0.060532688 | M92: =IF(P92="TERMINADO",0,H92-(J92+K92)) -> 0 | N92: =1-(I92/H92) -> 0.69733656 | O92: =IF(NOT(ISNUMBER(H92)),0,IF(P92="Terminado",1,IF(J92=0,0,MIN(1,J92/H92)))) -> 1 | P92: Terminado | Q92: =IF(COUNTIFS(A:A,A92,P:P,"Terminado")=COUNTIF(A:A,A92),"Terminado",IF(COUNTIFS(A:A,A92,P:P,"En proceso")>0,"En proceso","Pendiente")) -> Terminado | R92: =IFERROR(__xludf.DUMMYFUNCTION("SPARKLINE(O92,{""charttype"",""bar"";""max"",1;""color1"",IF(P92=""Terminado"",""#4CAF50"",IF(O92>=0.5,""#FFA500"",""#F44336""))})"),"")
A93: Druni CC Safari | B93: Parafarmacia | C93: BASTIDOR DE TABICA CURVA 150X12 | D93: 33.04 | E93: 46113 | F93: =IFERROR(__xludf.DUMMYFUNCTION("""COMPUTED_VALUE"""),"Fabricación") -> Fabricación | G93: =IFERROR(__xludf.DUMMYFUNCTION("""COMPUTED_VALUE"""),"Ensamblaje") -> Ensamblaje | H93: =IFERROR(__xludf.DUMMYFUNCTION("(IFERROR(FILTER(BBDD!$J:$J,BBDD!$G:$G=C93,BBDD!$H:$H=F93,BBDD!$I:$I=G93),""NO TIENE PROCESO""))*D93"),26.1016) -> 26.1016 | I93: =J93+K93 -> 29.17 | J93: =SUMIFS('👷horas'!$J:$J,'👷horas'!$D:$D,A93,'👷horas'!$E:$E,B93,'👷horas'!$F:$F,F93,'👷horas'!$G:$G,G93) -> 20.17 | K93: =SUMIFS('👷horas'!$K:$K,'👷horas'!$D:$D,A93,'👷horas'!$E:$E,B93,'👷horas'!$F:$F,F93,'👷horas'!$G:$G,G93) -> 9 | L93: =I93/D93 -> 0.88286925 | M93: =IF(P93="TERMINADO",0,H93-(J93+K93)) -> 0 | N93: =1-(I93/H93) -> -0.11755601 | O93: =IF(NOT(ISNUMBER(H93)),0,IF(P93="Terminado",1,IF(J93=0,0,MIN(1,J93/H93)))) -> 1 | P93: Terminado | Q93: =IF(COUNTIFS(A:A,A93,P:P,"Terminado")=COUNTIF(A:A,A93),"Terminado",IF(COUNTIFS(A:A,A93,P:P,"En proceso")>0,"En proceso","Pendiente")) -> Terminado | R93: =IFERROR(__xludf.DUMMYFUNCTION("SPARKLINE(O93,{""charttype"",""bar"";""max"",1;""color1"",IF(P93=""Terminado"",""#4CAF50"",IF(O93>=0.5,""#FFA500"",""#F44336""))})"),"")
A94: Druni CC Safari | B94: Parafarmacia | C94: BASTIDOR DE TABICA CURVA 150X12 | D94: 33.04 | E94: 46113 | F94: =IFERROR(__xludf.DUMMYFUNCTION("""COMPUTED_VALUE"""),"Fabricación") -> Fabricación | G94: =IFERROR(__xludf.DUMMYFUNCTION("""COMPUTED_VALUE"""),"Colocación de perfiles") -> Colocación de perfiles | H94: =IFERROR(__xludf.DUMMYFUNCTION("(IFERROR(FILTER(BBDD!$J:$J,BBDD!$G:$G=C94,BBDD!$H:$H=F94,BBDD!$I:$I=G94),""NO TIENE PROCESO""))*D94"),6.6080000000000005) -> 6.608 | I94: =J94+K94 -> 8 | J94: =SUMIFS('👷horas'!$J:$J,'👷horas'!$D:$D,A94,'👷horas'!$E:$E,B94,'👷horas'!$F:$F,F94,'👷horas'!$G:$G,G94) -> 8 | K94: =SUMIFS('👷horas'!$K:$K,'👷horas'!$D:$D,A94,'👷horas'!$E:$E,B94,'👷horas'!$F:$F,F94,'👷horas'!$G:$G,G94) -> 0 | L94: =I94/D94 -> 0.24213075 | M94: =IF(P94="TERMINADO",0,H94-(J94+K94)) -> 0 | N94: =1-(I94/H94) -> -0.21065375 | O94: =IF(NOT(ISNUMBER(H94)),0,IF(P94="Terminado",1,IF(J94=0,0,MIN(1,J94/H94)))) -> 1 | P94: Terminado | Q94: =IF(COUNTIFS(A:A,A94,P:P,"Terminado")=COUNTIF(A:A,A94),"Terminado",IF(COUNTIFS(A:A,A94,P:P,"En proceso")>0,"En proceso","Pendiente")) -> Terminado | R94: =IFERROR(__xludf.DUMMYFUNCTION("SPARKLINE(O94,{""charttype"",""bar"";""max"",1;""color1"",IF(P94=""Terminado"",""#4CAF50"",IF(O94>=0.5,""#FFA500"",""#F44336""))})"),"")
A95: Druni CC Safari | B95: Parafarmacia | C95: BASTIDOR DE TABICA CURVA 150X12 | D95: 33.04 | E95: 46113 | F95: =IFERROR(__xludf.DUMMYFUNCTION("""COMPUTED_VALUE"""),"Fabricación") -> Fabricación | G95: =IFERROR(__xludf.DUMMYFUNCTION("""COMPUTED_VALUE"""),"Embalaje/carga/descarga material") -> Embalaje/carga/descarga material | H95: =IFERROR(__xludf.DUMMYFUNCTION("(IFERROR(FILTER(BBDD!$J:$J,BBDD!$G:$G=C95,BBDD!$H:$H=F95,BBDD!$I:$I=G95),""NO TIENE PROCESO""))*D95"),4.9559999999999995) -> 4.956 | I95: =J95+K95 -> 4.8529412 | J95: =SUMIFS('👷horas'!$J:$J,'👷horas'!$D:$D,A95,'👷horas'!$E:$E,B95,'👷horas'!$F:$F,F95,'👷horas'!$G:$G,G95) -> 4.5 | K95: =SUMIFS('👷horas'!$K:$K,'👷horas'!$D:$D,A95,'👷horas'!$E:$E,B95,'👷horas'!$F:$F,F95,'👷horas'!$G:$G,G95) -> 0.35294118 | L95: =I95/D95 -> 0.14688079 | M95: =IF(P95="TERMINADO",0,H95-(J95+K95)) -> 0 | N95: =1-(I95/H95) -> 0.020794759 | O95: =IF(NOT(ISNUMBER(H95)),0,IF(P95="Terminado",1,IF(J95=0,0,MIN(1,J95/H95)))) -> 1 | P95: Terminado | Q95: =IF(COUNTIFS(A:A,A95,P:P,"Terminado")=COUNTIF(A:A,A95),"Terminado",IF(COUNTIFS(A:A,A95,P:P,"En proceso")>0,"En proceso","Pendiente")) -> Terminado | R95: =IFERROR(__xludf.DUMMYFUNCTION("SPARKLINE(O95,{""charttype"",""bar"";""max"",1;""color1"",IF(P95=""Terminado"",""#4CAF50"",IF(O95>=0.5,""#FFA500"",""#F44336""))})"),"")
A96: Druni CC Safari | B96: Parafarmacia | C96: BASTIDOR DE TABICA CURVA 150X12 | D96: 33.04 | E96: 46113 | F96: =IFERROR(__xludf.DUMMYFUNCTION("""COMPUTED_VALUE"""),"Pintura") -> Pintura | G96: =IFERROR(__xludf.DUMMYFUNCTION("""COMPUTED_VALUE"""),"Lijado y/o Masillado") -> Lijado y/o Masillado | H96: =IFERROR(__xludf.DUMMYFUNCTION("(IFERROR(FILTER(BBDD!$J:$J,BBDD!$G:$G=C96,BBDD!$H:$H=F96,BBDD!$I:$I=G96),""NO TIENE PROCESO""))*D96"),19.823999999999998) -> 19.824 | I96: =J96+K96 -> 20.4421 | J96: =SUMIFS('👷horas'!$J:$J,'👷horas'!$D:$D,A96,'👷horas'!$E:$E,B96,'👷horas'!$F:$F,F96,'👷horas'!$G:$G,G96) -> 10.9421 | K96: =SUMIFS('👷horas'!$K:$K,'👷horas'!$D:$D,A96,'👷horas'!$E:$E,B96,'👷horas'!$F:$F,F96,'👷horas'!$G:$G,G96) -> 9.5 | L96: =I96/D96 -> 0.61870763 | M96: =IF(P96="TERMINADO",0,H96-(J96+K96)) -> 0 | N96: =1-(I96/H96) -> -0.031179379 | O96: =IF(NOT(ISNUMBER(H96)),0,IF(P96="Terminado",1,IF(J96=0,0,MIN(1,J96/H96)))) -> 1 | P96: Terminado | Q96: =IF(COUNTIFS(A:A,A96,P:P,"Terminado")=COUNTIF(A:A,A96),"Terminado",IF(COUNTIFS(A:A,A96,P:P,"En proceso")>0,"En proceso","Pendiente")) -> Terminado | R96: =IFERROR(__xludf.DUMMYFUNCTION("SPARKLINE(O96,{""charttype"",""bar"";""max"",1;""color1"",IF(P96=""Terminado"",""#4CAF50"",IF(O96>=0.5,""#FFA500"",""#F44336""))})"),"")
A97: Druni CC Safari | B97: Parafarmacia | C97: BASTIDOR DE TABICA CURVA 150X12 | D97: 33.04 | E97: 46113 | F97: =IFERROR(__xludf.DUMMYFUNCTION("""COMPUTED_VALUE"""),"Pintura") -> Pintura | G97: =IFERROR(__xludf.DUMMYFUNCTION("""COMPUTED_VALUE"""),"Imprimación/Pintura") -> Imprimación/Pintura | H97: =IFERROR(__xludf.DUMMYFUNCTION("(IFERROR(FILTER(BBDD!$J:$J,BBDD!$G:$G=C97,BBDD!$H:$H=F97,BBDD!$I:$I=G97),""NO TIENE PROCESO""))*D97"),13.216000000000001) -> 13.216 | I97: =J97+K97 -> 7.267 | J97: =SUMIFS('👷horas'!$J:$J,'👷horas'!$D:$D,A97,'👷horas'!$E:$E,B97,'👷horas'!$F:$F,F97,'👷horas'!$G:$G,G97) -> 4.767 | K97: =SUMIFS('👷horas'!$K:$K,'👷horas'!$D:$D,A97,'👷horas'!$E:$E,B97,'👷horas'!$F:$F,F97,'👷horas'!$G:$G,G97) -> 2.5 | L97: =I97/D97 -> 0.21994552 | M97: =IF(P97="TERMINADO",0,H97-(J97+K97)) -> 0 | N97: =1-(I97/H97) -> 0.4501362 | O97: =IF(NOT(ISNUMBER(H97)),0,IF(P97="Terminado",1,IF(J97=0,0,MIN(1,J97/H97)))) -> 1 | P97: Terminado | Q97: =IF(COUNTIFS(A:A,A97,P:P,"Terminado")=COUNTIF(A:A,A97),"Terminado",IF(COUNTIFS(A:A,A97,P:P,"En proceso")>0,"En proceso","Pendiente")) -> Terminado | R97: =IFERROR(__xludf.DUMMYFUNCTION("SPARKLINE(O97,{""charttype"",""bar"";""max"",1;""color1"",IF(P97=""Terminado"",""#4CAF50"",IF(O97>=0.5,""#FFA500"",""#F44336""))})"),"")
A98: Druni CC Safari | B98: Hair | C98: HAIR - ESPEJO | D98: 14.96 | E98: 46113 | F98: =IFERROR(__xludf.DUMMYFUNCTION("FILTER(BBDD!H:H,BBDD!G:G=C98)"),"Fabricación") -> Fabricación | G98: =IFERROR(__xludf.DUMMYFUNCTION("FILTER(BBDD!I:I,BBDD!G:G=C98)"),"Pegado de composite/chapa") -> Pegado de composite/chapa | H98: =IFERROR(__xludf.DUMMYFUNCTION("(IFERROR(FILTER(BBDD!$J:$J,BBDD!$G:$G=C98,BBDD!$H:$H=F98,BBDD!$I:$I=G98),""NO TIENE PROCESO""))*D98"),7.7792) -> 7.7792 | I98: =J98+K98 -> 6.5 | J98: =SUMIFS('👷horas'!$J:$J,'👷horas'!$D:$D,A98,'👷horas'!$E:$E,B98,'👷horas'!$F:$F,F98,'👷horas'!$G:$G,G98) -> 4.5 | K98: =SUMIFS('👷horas'!$K:$K,'👷horas'!$D:$D,A98,'👷horas'!$E:$E,B98,'👷horas'!$F:$F,F98,'👷horas'!$G:$G,G98) -> 2 | L98: =I98/D98 -> 0.43449198 | M98: =IF(P98="TERMINADO",0,H98-(J98+K98)) -> 0 | N98: =1-(I98/H98) -> 0.1644385 | O98: =IF(NOT(ISNUMBER(H98)),0,IF(P98="Terminado",1,IF(J98=0,0,MIN(1,J98/H98)))) -> 1 | P98: Terminado | Q98: =IF(COUNTIFS(A:A,A98,P:P,"Terminado")=COUNTIF(A:A,A98),"Terminado",IF(COUNTIFS(A:A,A98,P:P,"En proceso")>0,"En proceso","Pendiente")) -> Terminado | R98: =IFERROR(__xludf.DUMMYFUNCTION("SPARKLINE(O98,{""charttype"",""bar"";""max"",1;""color1"",IF(P98=""Terminado"",""#4CAF50"",IF(O98>=0.5,""#FFA500"",""#F44336""))})"),"")
A99: Druni CC Safari | B99: Hair | C99: HAIR - ESPEJO | D99: 14.96 | E99: 46113 | F99: =IFERROR(__xludf.DUMMYFUNCTION("""COMPUTED_VALUE"""),"Fabricación") -> Fabricación | G99: =IFERROR(__xludf.DUMMYFUNCTION("""COMPUTED_VALUE"""),"Embalaje/carga/descarga material") -> Embalaje/carga/descarga material | H99: =IFERROR(__xludf.DUMMYFUNCTION("(IFERROR(FILTER(BBDD!$J:$J,BBDD!$G:$G=C99,BBDD!$H:$H=F99,BBDD!$I:$I=G99),""NO TIENE PROCESO""))*D99"),6.8816) -> 6.8816 | I99: =J99+K99 -> 1.3970588 | J99: =SUMIFS('👷horas'!$J:$J,'👷horas'!$D:$D,A99,'👷horas'!$E:$E,B99,'👷horas'!$F:$F,F99,'👷horas'!$G:$G,G99) -> 1 | K99: =SUMIFS('👷horas'!$K:$K,'👷horas'!$D:$D,A99,'👷horas'!$E:$E,B99,'👷horas'!$F:$F,F99,'👷horas'!$G:$G,G99) -> 0.39705882 | L99: =I99/D99 -> 0.093386285 | M99: =IF(P99="TERMINADO",0,H99-(J99+K99)) -> 0 | N99: =1-(I99/H99) -> 0.79698634 | O99: =IF(NOT(ISNUMBER(H99)),0,IF(P99="Terminado",1,IF(J99=0,0,MIN(1,J99/H99)))) -> 1 | P99: Terminado | Q99: =IF(COUNTIFS(A:A,A99,P:P,"Terminado")=COUNTIF(A:A,A99),"Terminado",IF(COUNTIFS(A:A,A99,P:P,"En proceso")>0,"En proceso","Pendiente")) -> Terminado | R99: =IFERROR(__xludf.DUMMYFUNCTION("SPARKLINE(O99,{""charttype"",""bar"";""max"",1;""color1"",IF(P99=""Terminado"",""#4CAF50"",IF(O99>=0.5,""#FFA500"",""#F44336""))})"),"")
A100: Druni CC Safari | B100: Hair | C100: HAIR - ESPEJO | D100: 14.96 | E100: 46113 | F100: =IFERROR(__xludf.DUMMYFUNCTION("""COMPUTED_VALUE"""),"CNC") -> CNC | G100: =IFERROR(__xludf.DUMMYFUNCTION("""COMPUTED_VALUE"""),"CNC") -> CNC | H100: =IFERROR(__xludf.DUMMYFUNCTION("(IFERROR(FILTER(BBDD!$J:$J,BBDD!$G:$G=C100,BBDD!$H:$H=F100,BBDD!$I:$I=G100),""NO TIENE PROCESO""))*D100"),5.535200000000001) -> 5.5352 | I100: =J100+K100 -> 2.4583333 | J100: =SUMIFS('👷horas'!$J:$J,'👷horas'!$D:$D,A100,'👷horas'!$E:$E,B100,'👷horas'!$F:$F,F100,'👷horas'!$G:$G,G100) -> 2.4583333 | K100: =SUMIFS('👷horas'!$K:$K,'👷horas'!$D:$D,A100,'👷horas'!$E:$E,B100,'👷horas'!$F:$F,F100,'👷horas'!$G:$G,G100) -> 0 | L100: =I100/D100 -> 0.16432709 | M100: =IF(P100="TERMINADO",0,H100-(J100+K100)) -> 0 | N100: =1-(I100/H100) -> 0.55587272 | O100: =IF(NOT(ISNUMBER(H100)),0,IF(P100="Terminado",1,IF(J100=0,0,MIN(1,J100/H100)))) -> 1 | P100: Terminado | Q100: =IF(COUNTIFS(A:A,A100,P:P,"Terminado")=COUNTIF(A:A,A100),"Terminado",IF(COUNTIFS(A:A,A100,P:P,"En proceso")>0,"En proceso","Pendiente")) -> Terminado | R100: =IFERROR(__xludf.DUMMYFUNCTION("SPARKLINE(O100,{""charttype"",""bar"";""max"",1;""color1"",IF(P100=""Terminado"",""#4CAF50"",IF(O100>=0.5,""#FFA500"",""#F44336""))})"),"")
...

Sheet 👷horas
A1: Timestamp | B1: Fecha | C1: Operario | D1: Proyecto | E1: Lámpara | F1: Área | G1: Proceso | H1: Hora Inicio | I1: Hora Fin | J1: Horas Normales | K1: Horas Extras | L1: Observaciones
B2: 46009 | C2: Ihor Alieksieiev | D2: Druni cc las arenas (Canarias) | E2: Selcos metacrilato | F2: Fabricación | G2: Ensamblaje | J2: 4
B3: 46009 | C3: Serhii Kotluienko | D3: Druni cc las arenas (Canarias) | E3: Selcos metacrilato | F3: Fabricación | G3: Ensamblaje | J3: 4
B4: 46009 | C4: Tetiana Mesriakin | D4: Druni cc las arenas (Canarias) | E4: Selcos metacrilato | F4: Fabricación | G4: Ensamblaje | J4: 4
B5: 46010 | C5: Ihor Alieksieiev | D5: Druni cc la Villa (Canarias) | E5: Parafarmacia | F5: Fabricación | G5: Embalaje/carga/descarga material | J5: 8
B6: 46010 | C6: John Castelblanco | D6: Druni cc la Villa (Canarias) | E6: Hair | F6: CNC | G6: CNC | J6: 1.8 | L6: Corte máquina cnc
B7: 46010 | C7: John Castelblanco | D7: Druni cc la Villa (Canarias) | E7: Hair | F7: CNC | G7: CNC | J7: 0.9 | L7: Corte máquina cnc
B8: 46010 | C8: Serhii Kotluienko | D8: Druni cc las arenas (Canarias) | E8: Selcos metacrilato | F8: Fabricación | G8: Ensamblaje | J8: 8
B9: 46010 | C9: Tetiana Mesriakin | D9: Druni cc las arenas (Canarias) | E9: Selcos metacrilato | F9: Fabricación | G9: Ensamblaje | J9: 8
B10: 46013 | C10: Ihor Alieksieiev | D10: Druni cc la Villa (Canarias) | E10: Cruz | F10: Fabricación | G10: Ensamblaje | J10: 8
B11: 46013 | C11: Serhii Kotluienko | D11: Druni cc las arenas (Canarias) | E11: Selcos metacrilato | F11: Fabricación | G11: Embalaje/carga/descarga material | J11: 4 | L11: y llevar a nave 1
B12: 46013 | C12: Serhii Kotluienko | D12: Druni cc las arenas (Canarias) | E12: Selcos metacrilato | F12: Fabricación | G12: Ensamblaje | J12: 4
B13: 46013 | C13: Tetiana Mesriakin | D13: Druni cc las arenas (Canarias) | E13: Selcos metacrilato | F13: Fabricación | G13: Embalaje/carga/descarga material | J13: 4 | L13: y llevar a nave 1
B14: 46013 | C14: Tetiana Mesriakin | D14: Druni cc las arenas (Canarias) | E14: Selcos metacrilato | F14: Fabricación | G14: Ensamblaje | J14: 4
B15: 46029 | C15: Claudio Peralta | D15: Druni cc la Villa (Canarias) | E15: Parafarmacia | F15: Pintura | G15: Imprimación/Pintura | J15: 4 | L15: Imprimación
B16: 46029 | C16: Claudio Peralta | D16: Druni cc la Villa (Canarias) | E16: Hair | F16: Pintura | G16: Imprimación/Pintura | J16: 1.5 | L16: Imprimación
B17: 46030 | C17: Claudio Peralta | D17: Druni cc la Villa (Canarias) | E17: Parafarmacia | F17: Pintura | G17: Imprimación/Pintura | J17: 5 | L17: Pintura
B18: 46034 | C18: Claudio Peralta | D18: Contract + | E18: Nave | F18: Limpieza | G18: Limpieza | J18: 8
B19: 46034 | C19: Ihor Alieksieiev | D19: Druni cc la Villa (Canarias) | E19: Parafarmacia | F19: Fabricación | G19: Embalaje/carga/descarga material | J19: 0.25
B20: 46034 | C20: Ihor Alieksieiev | D20: Druni cc la Villa (Canarias) | E20: Cruz | F20: Fabricación | G20: Embalaje/carga/descarga material | J20: 0.25
B21: 46034 | C21: Ihor Alieksieiev | D21: Druni cc la Villa (Canarias) | E21: Parafarmacia | F21: Carga de Material | G21: Embalaje/carga/descarga material | J21: 0.5 | L21: Transporte material
B22: 46034 | C22: Ihor Alieksieiev | D22: Druni cc la Villa (Canarias) | E22: Cruz | F22: Carga de Material | G22: Embalaje/carga/descarga material | J22: 0.5 | L22: Transporte material
B23: 46034 | C23: Ihor Alieksieiev | D23: Contract + | E23: Nave | F23: Limpieza | G23: Limpieza | J23: 6.5
B24: 46034 | C24: Serhii Kotluienko | D24: Druni cc la Villa (Canarias) | E24: Parafarmacia | F24: Fabricación | G24: Embalaje/carga/descarga material | J24: 0.25
B25: 46034 | C25: Serhii Kotluienko | D25: Druni cc la Villa (Canarias) | E25: Cruz | F25: Fabricación | G25: Embalaje/carga/descarga material | J25: 0.25
B26: 46034 | C26: Serhii Kotluienko | D26: Druni cc la Villa (Canarias) | E26: Parafarmacia | F26: Carga de Material | G26: Embalaje/carga/descarga material | J26: 0.5 | L26: Transporte material
B27: 46034 | C27: Serhii Kotluienko | D27: Druni cc la Villa (Canarias) | E27: Cruz | F27: Carga de Material | G27: Embalaje/carga/descarga material | J27: 0.5 | L27: Transporte material
B28: 46034 | C28: Serhii Kotluienko | D28: Contract + | E28: Nave | F28: Limpieza | G28: Limpieza | J28: 6.5
B29: 46034 | C29: Tetiana Mesriakin | D29: Druni cc la Villa (Canarias) | E29: Hair | F29: Fabricación | G29: Embalaje/carga/descarga material | J29: 1.5
B30: 46034 | C30: Tetiana Mesriakin | D30: Contract + | E30: Nave | F30: Limpieza | G30: Limpieza | J30: 6.5
B31: 46035 | C31: Claudio Peralta | D31: Contract + | E31: Nave | F31: Limpieza | G31: Limpieza | J31: 8
B32: 46035 | C32: Ihor Alieksieiev | D32: Contract + | E32: Nave | F32: Limpieza | G32: Limpieza | J32: 8
B33: 46035 | C33: John Castelblanco | D33: Druni Cordoba fase 2 | E33: Cruz | F33: CNC | G33: CNC | J33: 1.5 | L33: Corte máquina cnc
B34: 46035 | C34: Serhii Kotluienko | D34: Contract + | E34: Nave | F34: Limpieza | G34: Limpieza | J34: 8
B35: 46035 | C35: Tetiana Mesriakin | D35: Contract + | E35: Nave | F35: Limpieza | G35: Limpieza | J35: 8
B36: 46036 | C36: Claudio Peralta | D36: Contract + | E36: Nave | F36: Limpieza | G36: Limpieza | J36: 8
B37: 46036 | C37: Ihor Alieksieiev | D37: Contract + | E37: Nave | F37: Limpieza | G37: Limpieza | J37: 8
B38: 46036 | C38: John Castelblanco | D38: Druni cc la Villa (Canarias) | E38: Hair | F38: CNC | G38: CNC | J38: 0.5 | L38: Corte máquina cnc
B39: 46036 | C39: Serhii Kotluienko | D39: Contract + | E39: Nave | F39: Limpieza | G39: Limpieza | J39: 8
B40: 46036 | C40: Tetiana Mesriakin | D40: Contract + | E40: Nave | F40: Limpieza | G40: Limpieza | J40: 8
B41: 46037 | C41: Claudio Peralta | D41: Contract + | E41: Nave | F41: Limpieza | G41: Limpieza | J41: 7 | L41: Organizar zona estanterias chapas y zona de materiales
B42: 46037 | C42: Claudio Peralta | D42: Druni cc la Villa (Canarias) | E42: Varias lamparas | F42: Fabricación | G42: Embalaje/carga/descarga material | J42: 0.75 | L42: Cargar a contenedor todas las lámparas de La villa
B43: 46037 | C43: Claudio Peralta | D43: Druni cc las arenas (Canarias) | E43: Varias lamparas | F43: Fabricación | G43: Embalaje/carga/descarga material | J43: 0.75 | L43: Cargar a contenedor todas las lámparas de las arenas
B44: 46037 | C44: Ihor Alieksieiev | D44: Contract + | E44: Nave | F44: Limpieza | G44: Limpieza | J44: 7 | L44: Organizar zona estanterias chapas y zona de materiales
B45: 46037 | C45: Ihor Alieksieiev | D45: Druni cc la Villa (Canarias) | E45: Varias lamparas | F45: Fabricación | G45: Embalaje/carga/descarga material | J45: 0.75 | L45: Cargar a contenedor todas las lámparas de La villa
B46: 46037 | C46: Ihor Alieksieiev | D46: Druni cc las arenas (Canarias) | E46: Varias lamparas | F46: Fabricación | G46: Embalaje/carga/descarga material | J46: 0.75 | L46: Cargar a contenedor todas las lámparas de las arenas
B47: 46037 | C47: Serhii Kotluienko | D47: Contract + | E47: Nave | F47: Limpieza | G47: Limpieza | J47: 7 | L47: Organizar zona estanterias chapas y zona de materiales
B48: 46037 | C48: Serhii Kotluienko | D48: Druni cc la Villa (Canarias) | E48: Varias lamparas | F48: Fabricación | G48: Embalaje/carga/descarga material | J48: 0.75 | L48: Cargar a contenedor todas las lámparas de La villa
B49: 46037 | C49: Serhii Kotluienko | D49: Druni cc las arenas (Canarias) | E49: Varias lamparas | F49: Fabricación | G49: Embalaje/carga/descarga material | J49: 0.75 | L49: Cargar a contenedor todas las lámparas de las arenas
B50: 46037 | C50: Tetiana Mesriakin | D50: Contract + | E50: Nave | F50: Limpieza | G50: Limpieza | J50: 7 | L50: Organizar zona estanterias chapas y zona de materiales
B51: 46037 | C51: Tetiana Mesriakin | D51: Druni cc la Villa (Canarias) | E51: Varias lamparas | F51: Fabricación | G51: Embalaje/carga/descarga material | J51: 0.75 | L51: Cargar a contenedor todas las lámparas de La villa
B52: 46037 | C52: Tetiana Mesriakin | D52: Druni cc las arenas (Canarias) | E52: Varias lamparas | F52: Fabricación | G52: Embalaje/carga/descarga material | J52: 0.75 | L52: Cargar a contenedor todas las lámparas de las arenas
... B124: 46057 | C124: Claudio Peralta | D124: Contract + | E124: Nave | F124: Fabricación | G124: Supervisión/reunión | J124: 1.5 | L124: Busqeuda de maquinaria
B125: 46057 | C125: Ihor Alieksieiev | D125: Druni Cordoba fase 2 | E125: Cupula | F125: Fabricación | G125: Embalaje/carga/descarga material | J125: 6 | L125: Embalar | M125: Debido a la poca producción, realizo proceso durante la jornada
B126: 46057 | C126: Ihor Alieksieiev | D126: Prototipo | E126: Prototipo | F126: Fabricación | G126: Ensamblaje | J126: 1.5 | L126: Ensamblaje acrílico para Vlad
B127: 46057 | C127: Ihor Alieksieiev | D127: Contract + | E127: Nave | F127: Limpieza | G127: Limpieza | J127: 0.5 | L127: Limpieza
B128: 46058 | C128: Claudio Peralta | D128: Druni Cordoba fase 2 | E128: Cruz | F128: Pintura | G128: Imprimación/Pintura | J128: 3.5 | L128: Imprimación
B129: 46058 | C129: Claudio Peralta | D129: Prueba | E129: Cromado | F129: Pintura | G129: Imprimación/Pintura | J129: 2.5 | L129: Pintura
B130: 46058 | C130: Claudio Peralta | D130: Druni PonteVella | E130: Registro | F130: Fabricación | G130: Corte manual | J130: 1 | L130: Corte de fajas
B131: 46058 | C131: Claudio Peralta | D131: Arenal el rosal | E131: Revestimiento | F131: Fabricación | G131: Corte manual | J131: 0.5 | L131: Corte de composite en tiras
B132: 46058 | C132: Claudio Peralta | D132: Contract + | E132: Nave | F132: Fabricación | G132: Supervisión/reunión | J132: 0.5 | L132: Busqeuda de maquinaria
B133: 46058 | C133: Ihor Alieksieiev | D133: Ikon Light system | E133: Transporte | F133: Carga de Material | G133: Transporte material | J133: 2 | L133: Transporte de material a nave 3
B134: 46058 | C134: Ihor Alieksieiev | D134: Druni PonteVella | E134: Registro | F134: Fabricación | G134: Ensamblaje | J134: 2 | L134: Ensamble
B135: 46058 | C135: Ihor Alieksieiev | D135: Druni Cordoba fase 2 | E135: Cupula | F135: Carga de Material | G135: Embalaje/carga/descarga material | J135: 0.5 | L135: Llevar material a nave 1
B136: 46058 | C136: Ihor Alieksieiev | D136: Contract + | E136: Nave | F136: Limpieza | G136: Limpieza | J136: 3.5 | L136: Limpieza revisar material estanteria
B137: 46058 | C137: John Castelblanco | D137: Druni Parc Central | E137: Cruz | F137: CNC | G137: CNC | J137: 1.5 | L137: Corte máquina cnc
... B145: 46059 | C145: Ihor Alieksieiev | D145: Arenal CC Marineda | E145: Pilar | F145: Carga de Material | G145: Transporte material | J145: 3.5 | L145: Recoger composite
B146: 46059 | C146: Ihor Alieksieiev | D146: Druni Parc Central | E146: Cruz | F146: Fabricación | G146: Ensamblaje | J146: =2.5+1.75 -> 4.25 | L146: Ensamblaje
B147: 46059 | C147: Ihor Alieksieiev | D147: Contract + | E147: Nave | F147: Limpieza | G147: Limpieza | J147: 0.25 | L147: Limpieza
B148: 46062 | C148: Claudio Peralta | D148: Druni Cordoba fase 2 | E148: Cruz | F148: Pintura | G148: Imprimación/Pintura | J148: 2.5 | L148: Pintura
B149: 46062 | C149: Claudio Peralta | D149: Contract + | E149: Nave | F149: Limpieza | G149: Limpieza | J149: 4.5 | L149: Preparar y compactar material en hueco piso
B150: 46062 | C150: Claudio Peralta | D150: Druni Parc Central | E150: Ranura para placas | F150: Pintura | G150: Imprimación/Pintura | J150: 1 | L150: Pintura
B151: 46062 | C151: Ihor Alieksieiev | D151: Druni Parc Central | E151: Cruz | F151: Fabricación | G151: Ensamblaje | J151: 7.5 | L151: Ensamblar + preprarar ranura, lijar
B152: 46062 | C152: Ihor Alieksieiev | D152: Contract + | E152: Nave | F152: Limpieza | G152: Limpieza | J152: 0.5 | L152: Limpieza
B153: 46062 | C153: John Castelblanco | D153: Druni Parc Central | E153: Ranura para placas | F153: CNC | G153: CNC | J153: 0.5 | L153: Corte máquina cnc
B154: 46063 | C154: Claudio Peralta | D154: Ceilica | E154: Curvas madera | F154: Carga de Material | G154: Embalaje/carga/descarga material | J154: 0.5 | L154: Embalar material y llevarlo a nave 1
B155: 46063 | C155: Claudio Peralta | D155: Druni Parc Central | E155: Cruz | F155: Pintura | G155: Lijado y/o Masillado | J155: 2 | L155: Lijado de pieza
B156: 46063 | C156: Claudio Peralta | D156: BYD Barcelona | E156: Pilar | F156: Fabricación | G156: Ensamblaje | J156: 0.5 | L156: Ensamble
B157: 46063 | C157: Claudio Peralta | D157: BYD Barcelona | E157: Pilar | F157: Pintura | G157: Imprimación/Pintura | J157: 1 | L157: Imprimación
B158: 46063 | C158: Claudio Peralta | D158: Contract + | E158: Nave | F158: Limpieza | G158: Limpieza | J158: 3 | L158: Losa, hueco del pieso
... B162: 46063 | C162: Ihor Alieksieiev | D162: BYD Barcelona | E162: Perfil grand | F162: Fabricación | G162: Corte manual | J162: 1 | L162: Corte de perfil para curvado
B163: 46063 | C163: John Castelblanco | D163: BYD Barcelona | E163: Pilar | F163: CNC | G163: CNC | J163: =10/60 -> 0.16666667 | L163: Corte máquina cnc
B164: 46063 | C164: John Castelblanco | D164: Druni Parc Central | E164: Ameba | F164: CNC | G164: CNC | J164: 1 | L164: Corte máquina cnc
B165: 46064 | C165: Claudio Peralta | D165: Druni Parc Central | E165: Cruz | F165: Pintura | G165: Lijado y/o Masillado | J165: 2 | L165: Masillar
B166: 46064 | C166: Claudio Peralta | D166: Contract + | E166: Nave | F166: Limpieza | G166: Limpieza | J166: 4 | L166: Losa, hueco del pieso
B167: 46064 | C167: Claudio Peralta | D167: Prototipo | E167: Cromado | F167: Pintura | G167: Imprimación/Pintura | J167: 2 | L167: Prueba cromo perfiles munich o agolar
B168: 46064 | C168: Ihor Alieksieiev | D168: Contract + | E168: Transporte | F168: Carga de Material | G168: Transporte material | J168: 3.5 | L168: Recoger material comprado en obramat para losa de nave 2
B169: 46064 | C169: Ihor Alieksieiev | D169: Druni Cordoba fase 2 | E169: Cruz | F169: Fabricación | G169: Colocación de perfiles | J169: 3.5 | L169: Colocar perfiles
B170: 46064 | C170: Ihor Alieksieiev | D170: Druni Cordoba fase 2 | E170: Cruz | F170: Fabricación | G170: Embalaje/carga/descarga material | J170: 1 | L170: Embalar
B171: 46065 | C171: Claudio Peralta | D171: Prototipo | E171: Cromado | F171: Pintura | G171: Imprimación/Pintura | J171: 5.5 | L171: Prueba cromo perfiles munich o agolar
B172: 46065 | C172: Ihor Alieksieiev | D172: Druni Cordoba fase 2 | E172: Cruz | F172: Fabricación | G172: Embalaje/carga/descarga material | J172: 2 | L172: Embalar cruz
B173: 46065 | C173: Ihor Alieksieiev | D173: Druni Parc Central | E173: Cruz | F173: Pintura | G173: Lijado y/o Masillado | J173: 4 | L173: Lijar cruz
B174: 46065 | C174: Ihor Alieksieiev | D174: Druni Parc Central | E174: Ameba | F174: Fabricación | G174: Ensamblaje | J174: 1.5
B175: 46065 | C175: Ihor Alieksieiev | D175: Druni cc Lìlla | E175: Revestimiento | F175: Fabricación | G175: Pegado de composite/chapa | J175: 0.25 | L175: Pegar composite cuña de Lilla a contrachapado
B176: 46065 | C176: Ihor Alieksieiev | D176: Contract + | E176: Nave | F176: Limpieza | G176: Limpieza | J176: 0.25 | L176: Limpieza de nave
B177: 46066 | C177: Claudio Peralta | D177: Prototipo | E177: Cromado | F177: Pintura | G177: Imprimación/Pintura | J177: 5.5 | L177: Prueba cromo perfiles munich o agolar
B178: 46066 | C178: Ihor Alieksieiev | D178: Druni Parc Central | E178: Ameba | F178: Fabricación | G178: Ensamblaje | J178: 8 | L178: Ensamblaje
B179: 46069 | C179: Claudio Peralta | D179: Prototipo | E179: Cromado | F179: Pintura | G179: Imprimación/Pintura | J179: 7.5 | L179: Prueba cromo perfiles munich o agolar
B180: 46069 | C180: Claudio Peralta | D180: Contract + | E180: Nave | F180: Limpieza | G180: Limpieza | J180: 0.5 | L180: Limpieza de nave
B181: 46069 | C181: Ihor Alieksieiev | D181: Druni Parc Central | E181: Ameba | F181: Pintura | G181: Lijado y/o Masillado | J181: 5.5 | L181: limpieza, lijado y masillado
...

Sheet Claude Cache
A1: ⚠️ SHEET RESERVED FOR =CLAUDE... FUNCTIONS. DO NOT EDIT! ⚠️
A2: Key | B2: Value | C2: Expiration

Sheet 📄Informe de producción
A1: 📈 INFORME DE PRODUCCIÓN
A3: RESUMEN EJECUTIVO
A4: Periodo | D4: Fecha de inicio | E4: Fecha parcial/fin | F4: Días
A5: Proyecto | B5: Druni CC los alcores | D5: =IFERROR(__xludf.DUMMYFUNCTION("IFERROR(MIN(FILTER('👷 HORAS'!$A:$A,'👷 HORAS'!$C:$C=$B$5)),"""")"),"") | E5: =IFERROR(__xludf.DUMMYFUNCTION("IFERROR(MAX(FILTER('👷 HORAS'!$A:$A,'👷 HORAS'!$C:$C=$B$5)),"""")"),"") | F5: =NETWORKDAYS(D5,E5) -> 0
A7: MÉTRICAS PRINCIPALES:
A8: ━━━━━━━━━━━━━━━━━━━━━━━━━━━━━━━━━━━━━━━━━━━━━━━━━━━━━━━━━━━━━━━━━━━━━
A9: Total de metros producidos: | B9: =IFERROR(__xludf.DUMMYFUNCTION("IFERROR(SUM(UNIQUE(FILTER('🗂️ Proyectos'!D:D, ('🗂️ Proyectos'!A:A=B5)*('🗂️ Proyectos'!B:B<>""Hair"")))),0)"),68.45) -> 68.45 | C9: m
A10: Total de m2 producidos: | B10: =IFERROR(__xludf.DUMMYFUNCTION("IFERROR(SUM(UNIQUE(FILTER('🗂️ Proyectos'!D:D, '🗂️ Proyectos'!A:A=B5, '🗂️ Proyectos'!B:B=""Hair""))), 0)"),0.0) -> 0 | C10: m2
A11: Total de horas trabajadas: | B11: =SUMIF('👷 HORAS'!C:C,$B$5,'👷 HORAS'!H:H)+SUMIF('👷 HORAS'!C:C,$B$5,'👷 HORAS'!I:I) -> #N/A | C11: hrs | D11: =SUMIF('🗂️ Proyectos'!A:A,B5,'🗂️ Proyectos'!H:H) -> 199.12819 | E11: hrs proyectadas
A12: Tiempo promedio por m | B12: =IFERROR(B11/B9,"") | C12: hrs/m | D12: =IFERROR(D11/B9,"") -> 2.9091043 | E12: hrs/m
A13: Eficiencia | B13: =(D11-B11) -> #N/A | C13: hr | D13: =IF((B11/D11)<=100%,CONCATENATE("Se realizó un ",TEXT(ABS(100%-(B11/D11)),"0.0%")," más rápido de lo proyectado"),CONCATENATE("Se realizó un ",TEXT(ABS((B11/D11)-100%),"0.0%")," más lento de lo proyectado")) -> #N/A
A14: Número de operarios: | B14: =IFERROR(__xludf.DUMMYFUNCTION("IFERROR(COUNTA(UNIQUE(FILTER('👷 HORAS'!$B:$B,('👷 HORAS'!$C:$C=$B$5)*('👷 HORAS'!$B:$B<>"""")))),""0"")"),1.0) -> 1
A15: Cantidad de lámparas | B15: =IFERROR(__xludf.DUMMYFUNCTION("IFERROR(COUNTA(UNIQUE(FILTER(#REF!,('👷 HORAS'!$C:$C=$B$5)*(#REF!<>"""")))),""0"")"),1.0) -> 1
A17: DISTRIBUCIÓN POR ÁREA Y BASTIDOR:
A18: ━━━━━━━━━━━━━━━━━━━━━━━━━━━━━━━━━━━━━━━━━━━━━━━━━━━━━━━━━━━━━━━━━━━━━
B19: Área | C19: Hora normal | D19: Hora extra | E19: Hora total | G19: Hora plan
A20: =A65 -> No hay lámparas para este proyecto | B20: CNC | C20: =SUMIFS('👷 HORAS'!H:H,'👷 HORAS'!C:C,$B$5,'👷 HORAS'!D:D,$A$20,'👷 HORAS'!E:E,$B20) -> #N/A | D20: =SUMIFS('👷 HORAS'!I:I,'👷 HORAS'!C:C,$B$5,'👷 HORAS'!D:D,$A$20,'👷 HORAS'!E:E,$B20) -> #N/A | E20: =C20+D20 -> #N/A | F20: hrs | G20: =SUMIFS('🗂️ Proyectos'!$H:$H,'🗂️ Proyectos'!$A:$A,$B$5,'🗂️ Proyectos'!$B:$B,$A$20,'🗂️ Proyectos'!$F:$F,$B20) -> 0 | H20: hrs
B21: Fabricación | C21: =SUMIFS('👷 HORAS'!H:H,'👷 HORAS'!C:C,$B$5,'👷 HORAS'!D:D,$A$20,'👷 HORAS'!E:E,$B21) -> #N/A | D21: =SUMIFS('👷 HORAS'!I:I,'👷 HORAS'!C:C,$B$5,'👷 HORAS'!D:D,$A$20,'👷 HORAS'!E:E,$B21) -> #N/A | E21: =C21+D21 -> #N/A | F21: hrs | G21: =SUMIFS('🗂️ Proyectos'!$H:$H,'🗂️ Proyectos'!$A:$A,$B$5,'🗂️ Proyectos'!$B:$B,$A$20,'🗂️ Proyectos'!$F:$F,$B21) -> 0 | H21: hrs
B22: Pintura | C22: =SUMIFS('👷 HORAS'!H:H,'👷 HORAS'!C:C,$B$5,'👷 HORAS'!D:D,$A$20,'👷 HORAS'!E:E,$B22) -> #N/A | D22: =SUMIFS('👷 HORAS'!I:I,'👷 HORAS'!C:C,$B$5,'👷 HORAS'!D:D,$A$20,'👷 HORAS'!E:E,$B22) -> #N/A | E22: =C22+D22 -> #N/A | F22: hrs | G22: =SUMIFS('🗂️ Proyectos'!$H:$H,'🗂️ Proyectos'!$A:$A,$B$5,'🗂️ Proyectos'!$B:$B,$A$20,'🗂️ Proyectos'!$F:$F,$B22) -> 0 | H22: hrs
B23: Horas totales | C23: =SUM(C20:C22) -> #N/A | D23: =SUM(D20:D22) -> #N/A | E23: =C23+D23 -> #N/A | F23: hrs | G23: =SUM(G20:G22) -> 0 | H23: hrs
B25: Área | C25: Hora normal | D25: Hora extra | E25: Hora total | G25: Hora plan
A26: =A66 | B26: CNC | C26: =SUMIFS('👷 HORAS'!H:H,'👷 HORAS'!C:C,$B$5,'👷 HORAS'!D:D,$A$26,'👷 HORAS'!E:E,$B26) -> #N/A | D26: =SUMIFS('👷 HORAS'!I:I,'👷 HORAS'!C:C,$B$5,'👷 HORAS'!D:D,$A$26,'👷 HORAS'!E:E,$B26) -> #N/A | E26: =C26+D26 -> #N/A | F26: hrs | G26: =SUMIFS('🗂️ Proyectos'!$H:$H,'🗂️ Proyectos'!$A:$A,$B$5,'🗂️ Proyectos'!$B:$B,$A$26,'🗂️ Proyectos'!$F:$F,$B26) -> 0 | H26: hrs
B27: Fabricación | C27: =SUMIFS('👷 HORAS'!H:H,'👷 HORAS'!C:C,$B$5,'👷 HORAS'!D:D,$A$26,'👷 HORAS'!E:E,$B27) -> #N/A | D27: =SUMIFS('👷 HORAS'!I:I,'👷 HORAS'!C:C,$B$5,'👷 HORAS'!D:D,$A$26,'👷 HORAS'!E:E,$B27) -> #N/A | E27: =C27+D27 -> #N/A | F27: hrs | G27: =SUMIFS('🗂️ Proyectos'!$H:$H,'🗂️ Proyectos'!$A:$A,$B$5,'🗂️ Proyectos'!$B:$B,$A$26,'🗂️ Proyectos'!$F:$F,$B27) -> 0 | H27: hrs
B28: Pintura | C28: =SUMIFS('👷 HORAS'!H:H,'👷 HORAS'!C:C,$B$5,'👷 HORAS'!D:D,$A$26,'👷 HORAS'!E:E,$B28) -> #N/A | D28: =SUMIFS('👷 HORAS'!I:I,'👷 HORAS'!C:C,$B$5,'👷 HORAS'!D:D,$A$26,'👷 HORAS'!E:E,$B28) -> #N/A | E28: =C28+D28 -> #N/A | F28: hrs | G28: =SUMIFS('🗂️ Proyectos'!$H:$H,'🗂️ Proyectos'!$A:$A,$B$5,'🗂️ Proyectos'!$B:$B,$A$26,'🗂️ Proyectos'!$F:$F,$B28) -> 0 | H28: hrs
B29: Horas totales | C29: =SUM(C26:C28) -> #N/A | D29: =SUM(D26:D28) -> #N/A | E29: =C29+D29 -> #N/A | F29: hrs | G29: =SUM(G26:G28) -> 0 | H29: hrs
B31: Área | C31: Hora normal | D31: Hora extra | E31: Hora total | G31: Hora plan
A32: =A67 | B32: CNC | C32: =SUMIFS('👷 HORAS'!H:H,'👷 HORAS'!C:C,$B$5,'👷 HORAS'!D:D,$A$20,'👷 HORAS'!E:E,$B32) -> #N/A | D32: =SUMIFS('👷 HORAS'!I:I,'👷 HORAS'!C:C,$B$5,'👷 HORAS'!D:D,$A$20,'👷 HORAS'!E:E,$B32) -> #N/A | E32: =C32+D32 -> #N/A | F32: hrs | G32: =SUMIFS('🗂️ Proyectos'!$H:$H,'🗂️ Proyectos'!$A:$A,$B$5,'🗂️ Proyectos'!$B:$B,$A$20,'🗂️ Proyectos'!$F:$F,$B32) -> 0 | H32: hrs
B33: Fabricación | C33: =SUMIFS('👷 HORAS'!H:H,'👷 HORAS'!C:C,$B$5,'👷 HORAS'!D:D,$A$20,'👷 HORAS'!E:E,$B33) -> #N/A | D33: =SUMIFS('👷 HORAS'!I:I,'👷 HORAS'!C:C,$B$5,'👷 HORAS'!D:D,$A$20,'👷 HORAS'!E:E,$B33) -> #N/A | E33: =C33+D33 -> #N/A | F33: hrs | G33: =SUMIFS('🗂️ Proyectos'!$H:$H,'🗂️ Proyectos'!$A:$A,$B$5,'🗂️ Proyectos'!$B:$B,$A$20,'🗂️ Proyectos'!$F:$F,$B33) -> 0 | H33: hrs
B34: Pintura | C34: =SUMIFS('👷 HORAS'!H:H,'👷 HORAS'!C:C,$B$5,'👷 HORAS'!D:D,$A$20,'👷 HORAS'!E:E,$B34) -> #N/A | D34: =SUMIFS('👷 HORAS'!I:I,'👷 HORAS'!C:C,$B$5,'👷 HORAS'!D:D,$A$20,'👷 HORAS'!E:E,$B34) -> #N/A | E34: =C34+D34 -> #N/A | F34: hrs | G34: =SUMIFS('🗂️ Proyectos'!$H:$H,'🗂️ Proyectos'!$A:$A,$B$5,'🗂️ Proyectos'!$B:$B,$A$20,'🗂️ Proyectos'!$F:$F,$B34) -> 0 | H34: hrs
B35: Horas totales | C35: =SUM(C32:C34) -> #N/A | D35: =SUM(D32:D34) -> #N/A | E35: =C35+D35 -> #N/A | F35: hrs | G35: =SUM(G32:G34) -> 0 | H35: hrs
B37: Área | C37: Hora normal | D37: Hora extra | E37: Hora total | G37: Hora plan
A38: =A68 | B38: CNC | C38: =SUMIFS('👷 HORAS'!H:H,'👷 HORAS'!C:C,$B$5,'👷 HORAS'!D:D,$A$26,'👷 HORAS'!E:E,$B38) -> #N/A | D38: =SUMIFS('👷 HORAS'!I:I,'👷 HORAS'!C:C,$B$5,'👷 HORAS'!D:D,$A$26,'👷 HORAS'!E:E,$B38) -> #N/A | E38: =C38+D38 -> #N/A | F38: hrs | G38: =SUMIFS('🗂️ Proyectos'!$H:$H,'🗂️ Proyectos'!$A:$A,$B$5,'🗂️ Proyectos'!$B:$B,$A$26,'🗂️ Proyectos'!$F:$F,$B38) -> 0 | H38: hrs
B39: Fabricación | C39: =SUMIFS('👷 HORAS'!H:H,'👷 HORAS'!C:C,$B$5,'👷 HORAS'!D:D,$A$26,'👷 HORAS'!E:E,$B39) -> #N/A | D39: =SUMIFS('👷 HORAS'!I:I,'👷 HORAS'!C:C,$B$5,'👷 HORAS'!D:D,$A$26,'👷 HORAS'!E:E,$B39) -> #N/A | E39: =C39+D39 -> #N/A | F39: hrs | G39: =SUMIFS('🗂️ Proyectos'!$H:$H,'🗂️ Proyectos'!$A:$A,$B$5,'🗂️ Proyectos'!$B:$B,$A$26,'🗂️ Proyectos'!$F:$F,$B39) -> 0 | H39: hrs
B40: Pintura | C40: =SUMIFS('👷 HORAS'!H:H,'👷 HORAS'!C:C,$B$5,'👷 HORAS'!D:D,$A$26,'👷 HORAS'!E:E,$B40) -> #N/A | D40: =SUMIFS('👷 HORAS'!I:I,'👷 HORAS'!C:C,$B$5,'👷 HORAS'!D:D,$A$26,'👷 HORAS'!E:E,$B40) -> #N/A | E40: =C40+D40 -> #N/A | F40: hrs | G40: =SUMIFS('🗂️ Proyectos'!$H:$H,'🗂️ Proyectos'!$A:$A,$B$5,'🗂️ Proyectos'!$B:$B,$A$26,'🗂️ Proyectos'!$F:$F,$B40) -> 0 | H40: hrs
B41: Horas totales | C41: =SUM(C38:C40) -> #N/A | D41: =SUM(D38:D40) -> #N/A | E41: =C41+D41 -> #N/A | F41: hrs | G41: =SUM(G38:G40) -> 0 | H41: hrs
B43: Área | C43: Hora normal | D43: Hora extra | E43: Hora total | G43: Hora plan
A44: =A69 | B44: CNC | C44: =SUMIFS('👷 HORAS'!H:H,'👷 HORAS'!C:C,$B$5,'👷 HORAS'!D:D,$A$26,'👷 HORAS'!E:E,$B44) -> #N/A | D44: =SUMIFS('👷 HORAS'!I:I,'👷 HORAS'!C:C,$B$5,'👷 HORAS'!D:D,$A$26,'👷 HORAS'!E:E,$B44) -> #N/A | E44: =C44+D44 -> #N/A | F44: hrs | G44: =SUMIFS('🗂️ Proyectos'!$H:$H,'🗂️ Proyectos'!$A:$A,$B$5,'🗂️ Proyectos'!$B:$B,$A$26,'🗂️ Proyectos'!$F:$F,$B44) -> 0 | H44: hrs
B45: Fabricación | C45: =SUMIFS('👷 HORAS'!H:H,'👷 HORAS'!C:C,$B$5,'👷 HORAS'!D:D,$A$26,'👷 HORAS'!E:E,$B45) -> #N/A | D45: =SUMIFS('👷 HORAS'!I:I,'👷 HORAS'!C:C,$B$5,'👷 HORAS'!D:D,$A$26,'👷 HORAS'!E:E,$B45) -> #N/A | E45: =C45+D45 -> #N/A | F45: hrs | G45: =SUMIFS('🗂️ Proyectos'!$H:$H,'🗂️ Proyectos'!$A:$A,$B$5,'🗂️ Proyectos'!$B:$B,$A$26,'🗂️ Proyectos'!$F:$F,$B45) -> 0 | H45: hrs
B46: Pintura | C46: =SUMIFS('👷 HORAS'!H:H,'👷 HORAS'!C:C,$B$5,'👷 HORAS'!D:D,$A$26,'👷 HORAS'!E:E,$B46) -> #N/A | D46: =SUMIFS('👷 HORAS'!I:I,'👷 HORAS'!C:C,$B$5,'👷 HORAS'!D:D,$A$26,'👷 HORAS'!E:E,$B46) -> #N/A | E46: =C46+D46 -> #N/A | F46: hrs | G46: =SUMIFS('🗂️ Proyectos'!$H:$H,'🗂️ Proyectos'!$A:$A,$B$5,'🗂️ Proyectos'!$B:$B,$A$26,'🗂️ Proyectos'!$F:$F,$B46) -> 0 | H46: hrs
B47: Horas totales | C47: =SUM(C44:C46) -> #N/A | D47: =SUM(D44:D46) -> #N/A | E47: =C47+D47 -> #N/A | F47: hrs | G47: =SUM(G44:G46) -> 0 | H47: hrs
B49: Área | C49: Hora normal | D49: Hora extra | E49: Hora total | G49: Hora plan
A50: =A70 | B50: CNC | C50: =SUMIFS('👷 HORAS'!H:H,'👷 HORAS'!C:C,$B$5,'👷 HORAS'!D:D,$A$26,'👷 HORAS'!E:E,$B50) -> #N/A | D50: =SUMIFS('👷 HORAS'!I:I,'👷 HORAS'!C:C,$B$5,'👷 HORAS'!D:D,$A$26,'👷 HORAS'!E:E,$B50) -> #N/A | E50: =C50+D50 -> #N/A | F50: hrs | G50: =SUMIFS('🗂️ Proyectos'!$H:$H,'🗂️ Proyectos'!$A:$A,$B$5,'🗂️ Proyectos'!$B:$B,$A$26,'🗂️ Proyectos'!$F:$F,$B50) -> 0 | H50: hrs
B51: Fabricación | C51: =SUMIFS('👷 HORAS'!H:H,'👷 HORAS'!C:C,$B$5,'👷 HORAS'!D:D,$A$26,'👷 HORAS'!E:E,$B51) -> #N/A | D51: =SUMIFS('👷 HORAS'!I:I,'👷 HORAS'!C:C,$B$5,'👷 HORAS'!D:D,$A$26,'👷 HORAS'!E:E,$B51) -> #N/A | E51: =C51+D51 -> #N/A | F51: hrs | G51: =SUMIFS('🗂️ Proyectos'!$H:$H,'🗂️ Proyectos'!$A:$A,$B$5,'🗂️ Proyectos'!$B:$B,$A$26,'🗂️ Proyectos'!$F:$F,$B51) -> 0 | H51: hrs
B52: Pintura | C52: =SUMIFS('👷 HORAS'!H:H,'👷 HORAS'!C:C,$B$5,'👷 HORAS'!D:D,$A$26,'👷 HORAS'!E:E,$B52) -> #N/A | D52: =SUMIFS('👷 HORAS'!I:I,'👷 HORAS'!C:C,$B$5,'👷 HORAS'!D:D,$A$26,'👷 HORAS'!E:E,$B52) -> #N/A | E52: =C52+D52 -> #N/A | F52: hrs | G52: =SUMIFS('🗂️ Proyectos'!$H:$H,'🗂️ Proyectos'!$A:$A,$B$5,'🗂️ Proyectos'!$B:$B,$A$26,'🗂️ Proyectos'!$F:$F,$B52) -> 0 | H52: hrs
B53: Horas totales | C53: =SUM(C50:C52) -> #N/A | D53: =SUM(D50:D52) -> #N/A | E53: =C53+D53 -> #N/A | F53: hrs | G53: =SUM(G50:G52) -> 0 | H53: hrs
B55: Área | C55: Hora normal | D55: Hora extra | E55: Hora total | G55: Hora plan
A56: =A73 | B56: CNC | C56: =SUMIFS('👷 HORAS'!H:H,'👷 HORAS'!C:C,$B$5,'👷 HORAS'!D:D,$A$26,'👷 HORAS'!E:E,$B56) -> #N/A | D56: =SUMIFS('👷 HORAS'!I:I,'👷 HORAS'!C:C,$B$5,'👷 HORAS'!D:D,$A$26,'👷 HORAS'!E:E,$B56) -> #N/A | E56: =C56+D56 -> #N/A | F56: hrs | G56: =SUMIFS('🗂️ Proyectos'!$H:$H,'🗂️ Proyectos'!$A:$A,$B$5,'🗂️ Proyectos'!$B:$B,$A$26,'🗂️ Proyectos'!$F:$F,$B56) -> 0 | H56: hrs
B57: Fabricación | C57: =SUMIFS('👷 HORAS'!H:H,'👷 HORAS'!C:C,$B$5,'👷 HORAS'!D:D,$A$26,'👷 HORAS'!E:E,$B57) -> #N/A | D57: =SUMIFS('👷 HORAS'!I:I,'👷 HORAS'!C:C,$B$5,'👷 HORAS'!D:D,$A$26,'👷 HORAS'!E:E,$B57) -> #N/A | E57: =C57+D57 -> #N/A | F57: hrs | G57: =SUMIFS('🗂️ Proyectos'!$H:$H,'🗂️ Proyectos'!$A:$A,$B$5,'🗂️ Proyectos'!$B:$B,$A$26,'🗂️ Proyectos'!$F:$F,$B57) -> 0 | H57: hrs
B58: Pintura | C58: =SUMIFS('👷 HORAS'!H:H,'👷 HORAS'!C:C,$B$5,'👷 HORAS'!D:D,$A$26,'👷 HORAS'!E:E,$B58) -> #N/A | D58: =SUMIFS('👷 HORAS'!I:I,'👷 HORAS'!C:C,$B$5,'👷 HORAS'!D:D,$A$26,'👷 HORAS'!E:E,$B58) -> #N/A | E58: =C58+D58 -> #N/A | F58: hrs | G58: =SUMIFS('🗂️ Proyectos'!$H:$H,'🗂️ Proyectos'!$A:$A,$B$5,'🗂️ Proyectos'!$B:$B,$A$26,'🗂️ Proyectos'!$F:$F,$B58) -> 0 | H58: hrs
B59: Horas totales | C59: =SUM(C56:C58) -> #N/A | D59: =SUM(D56:D58) -> #N/A | E59: =C59+D59 -> #N/A | F59: hrs | G59: =SUM(G56:G58) -> 0 | H59: hrs
A62: ANALISIS MO COSTE:
A63: ━━━━━━━━━━━━━━━━━━━━━━━━━━━━━━━━━━━━━━━━━━━━━━━━━━━━━━━━━━━━━━━━━━━━━
B64: PVP | C64: Coste pto | D64: Coste real | E64: Coste esperado | F64: Diferencia | G64: %margen utilidad
A65: =IFERROR(__xludf.DUMMYFUNCTION("IFERROR(UNIQUE(FILTER('👷 HORAS'!D1:D1233,('👷 HORAS'!C1:C1233=$B$5)*(#REF!<>""""))),""No hay lámparas para este proyecto"")"),"No hay lámparas para este proyecto") -> No hay lámparas para este proyecto | B65: 2004.12 | C65: 1284.69 | D65: 1235.43 | E65: 1235.43 | F65: =E65-D65 -> 0 | G65: =(B65-D65)/B65 -> 0.38355488
B66: 6077.11 | C66: 3895.52 | D66: 3917.746 | E66: 3744.44 | F66: =E66-D66 -> -173.306 | G66: =(B66-D66)/B66 -> 0.35532745
C76: TOTAL | D76: =SUM(D65:D66) -> 5153.176 | E76: =SUM(E65:E66) -> 4979.87 | F76: Promedio | G76: =AVERAGE(G65:G66) -> 0.36944116
A78: Tiempo cnc, ensamblaje, embalaje y pintura menor en un 16,67% de lo estimado
A79: Tiempo colocación de perfiles, lijado y/o masillado mayor en un 48,09% de lo estimado
A81: Nota: Coste esperado: coste sin horas extras
A83: OBSERVACIONES Y RECOMENDACIONES:
A84: ━━━━━━━━━━━━━━━━━━━━━━━━━━━━━━━━━━━━━━━━━━━━━━━━━━━━━━━━━━━━━━
A85: Se recibio el pedido a producción el 16 febrero
A86: Primera entrega el 20 febrero
A87: Segunda entrega el 02 marzo - se pospuso el 27 febrero para entrega al 04 marzo
A88: Se realizarón horas extras, debido a los tiempos de pedido del proyecto inicialmente pactados.
A89: Se ajusto planning para no realizar más horas extras después de posponer la segunda entrega.

Sheet Plantilla horas
E2: Orden de fabricación diaria | I2: Responsable: | J2: Claudio Peralta
I4: Fecha: | J4: =TODAY() -> 46149
B6: Prioridad | C6: Proyecto | D6: Luminaria | E6: Tarea | F6: Cantidad | G6: Estimado | H6: Real | I6: Comentarios
E20: Orden de fabricación diaria | I20: Responsable: | J20: Ihor Alieksieiev
I22: Fecha: | J22: =J4 -> 46149
B24: Prioridad | C24: Proyecto | D24: Luminaria | E24: Tarea | F24: Cantidad | G24: Estimado | H24: Real | I24: Comentarios
E39: Orden de fabricación diaria | I39: Responsable: | J39: Tetiana Mesriakin
I41: Fecha: | J41: =J22 -> 46149
B43: Prioridad | C43: Proyecto | D43: Luminaria | E43: Tarea | F43: Cantidad | G43: Estimado | H43: Real | I43: Comentarios
E57: Orden de fabricación diaria | I57: Responsable: | J57: Serhii Kotluienko
I59: Fecha: | J59: =J41 -> 46149
B61: Prioridad | C61: Proyecto | D61: Luminaria | E61: Tarea | F61: Cantidad | G61: Estimado | H61: Real | I61: Comentarios
E76: Orden de fabricación diaria | I76: Responsable: | J76: Daniil Shcheglov
I78: Fecha: | J78: =J59 -> 46149
B80: Prioridad | C80: Proyecto | D80: Luminaria | E80: Tarea | F80: Cantidad | G80: Estimado | H80: Real | I80: Comentarios
E94: Orden de fabricación diaria | I94: Responsable:
I96: Fecha: | J96: =J78 -> 46149
B98: Prioridad | C98: Proyecto | D98: Luminaria | E98: Tarea | F98: Cantidad | G98: Estimado | H98: Real | I98: Comentarios
E112: Orden de fabricación diaria | I112: Responsable:
I114: Fecha: | J114: =J96 -> 46149
B116: Prioridad | C116: Proyecto | D116: Luminaria | E116: Tarea | F116: Cantidad | G116: Estimado | H116: Real | I116: Comentarios
E130: Orden de fabricación diaria | I130: Responsable: | J130: John Castelblanco
I132: Fecha: | J132: =J114 -> 46149
B134: Prioridad | C134: Proyecto | D134: Luminaria | E134: Tarea | F134: Cantidad | G134: Estimado | H134: Real | I134: Comentarios
E150: Orden de fabricación diaria | I150: Responsable: | J150: Cesar Rodriguez
I152: Fecha: | J152: =J114 -> 46149
B154: Prioridad | C154: Proyecto | D154: Luminaria | E154: Tarea | F154: Cantidad | G154: Estimado | H154: Real | I154: Comentarios
E168: Orden de fabricación diaria | I168: Responsable:
I170: Fecha: | J170: =J114 -> 46149
B172: Prioridad | C172: Proyecto | D172: Luminaria | E172: Tarea | F172: Cantidad | G172: Estimado | H172: Real | I172: Comentarios
E186: Orden de fabricación diaria | I186: Responsable:
I188: Fecha: | J188: =J114 -> 46149
B190: Prioridad | C190: Proyecto | D190: Luminaria | E190: Tarea | F190: Cantidad | G190: Estimado | H190: Real | I190: Comentarios
